Workbook

Sheet Dashboard
B2: FINANCIAL PERFORMANCE DASHBOARD
B4: Stripe · Xero · Meta Ads · Bank · Credit Card · Invoice Uploads (5,000-row capacity) · IFRS & US GAAP | Period: Apr-2026 – Jun-2026 (sample data)
B6: TOTAL REVENUE (Blended, AED) | E6: TOTAL EXPENSES (AED) | H6: NET PROFIT (AED) | K6: AR OUTSTANDING (AED)
B7: =Revenue_Summary!B34 -> 1097886.6 | E7: =Expense_Summary!E41 -> 381575.26 | H7: =Revenue_Summary!B34-Expense_Summary!E41 -> 716311.37 | K7: =Receivables!F71 -> 466237.76
B11: META AD SPEND (Gross, AED) | E11: CASH BALANCE (latest, AED) | H11: AR — UAE (AED) | K11: AR — SINGAPORE (AED)
B12: =Expense_Summary!E22 -> 65447.8 | E12: =INDEX(Bank_Raw!F4:F44,COUNT(Bank_Raw!F4:F44)) -> 499639.33 | H12: =Receivables!F68 -> 129991.27 | K12: =Receivables!F69 -> 133105.21
B16: CREDIT CARD SPEND (AED) | E16: VENDOR UPLOAD EXPENSES (AED) | H16: AP OUTSTANDING (AED) | K16: CUSTOMER INVOICE REVENUE (AED)
B17: =Expense_Summary!E30 -> 51592.82 | E17: =Expense_Summary!E38 -> 52714.23 | H17: =Payables!F76 -> 12033.26 | K17: =Revenue_Summary!E26 -> 172509.13
B21: NET PROFIT — IFRS (AED) | E21: NET INCOME — US GAAP (AED) | H21: TRIAL BALANCE STATUS | K21: STRIPE RECEIVABLES: OPEN (AED)
B22: =Financial_Statements_IFRS!C27 -> 731093.09 | E22: =Financial_Statements_GAAP!C26 -> 731093.09 | H22: =Trial_Balance!C41 -> ✓ BALANCED | K22: =Customer_Receivables_Report!G34 -> 67404.49
B26: META COST RECOVERY GAP (AED) | E26: META RECOVERY RATE | H26: CUSTOMERS ON FILE | K26: SUBSCRIPTIONS DUE THIS MONTH
B27: =Meta_Cost_Recovery!G23 -> -26062.68 | E27: =Meta_Cost_Recovery!H23 -> 1.3982209 | H27: =COUNTA(Customer_Master!A4:A5003) -> 12 | K27: =COUNTIF(Subscription_Invoicing!G5:G200,"⚠ Due") -> 2
B32: REVENUE BY CATEGORY | H32: MONTHLY REVENUE TREND (STRIPE + XERO)
B50: EXPENSE BREAKDOWN (Xero Bills) | H50: AR OUTSTANDING BY COUNTRY
B68: META AD SPEND BY CUSTOMER (Gross) | H68: ACCOUNTS PAYABLE BY VENDOR
B86: XERO RECEIVABLES BY STATUS (Total) | H86: STRIPE RECEIVABLES BY STATUS (Total)
B104: WORKBOOK GUIDE
B105: README_Setup | D105: How to connect Stripe/Xero via Power Query, or upload PDF/Word/Excel documents for Claude to extract
B106: Assumptions | D106: Edit category keywords & customer→country map here — flows through whole workbook
B107: Customer_Master | D107: Customer directory — IDs across Xero/Stripe/Meta, country, plan, relationship owner
B108: Stripe_Raw / Xero_Raw / Bank_Raw / Meta_Invoices | D108: Raw data from exports/APIs — all pre-formulated for up to 5,000 rows
B109: Credit_Card_Upload / Customer_Invoices_Upload / Vendor_Invoices_Upload | D109: Upload zones for PDF/Word/Excel source documents — 5,000-row capacity
B110: Expenses_Upload / Revenue_Upload | D110: Catch-all upload zones for misc expenses and "any other services" revenue
B111: Stripe_Invoices_Upload | D111: Stripe Invoicing receivables (Draft/Open/Paid/Void/Uncollectible)
B112: Document_Log | D112: Audit trail of every source document processed
B113: Revenue_Summary / Expense_Summary / Receivables / Payables | D113: Formula-driven analysis feeding this Dashboard
B114: Customer_Receivables_Report | D114: Per-customer invoice status breakdown — Xero AND Stripe, incl. Void/Draft/Unsent
B115: Meta_Cost_Recovery | D115: Meta ad spend cost vs. amount recovered from customers via Stripe or tagged bank transfers
B116: Subscription_Invoicing | D116: Month-by-month recurring billing schedule — shows who’s due to be invoiced and who already has been
... B119: Financial_Statements_GAAP | D119: Income Statement, Balance Sheet, Cash Flows (US GAAP terminology/ordering)

Sheet README_Setup
B2: HOW THIS DASHBOARD IS BUILT & HOW TO CONNECT LIVE DATA
B4: This workbook is fully formula-driven. It currently contains realistic SAMPLE data so you can see how every number is calculated. Replace the sample rows in the raw tabs with your real data (via Power Query refresh OR manual paste) and every summary, KPI card and chart on the Dashboard recalculates automatically.
B7: 1. WHY THIS CAN’T BE A LIVE, SELF-REFRESHING FILE OUT OF THE BOX
B8: A standalone .xlsx file cannot hold live API credentials or run a background service — Stripe and Xero both require an authenticated API call (Stripe: secret key; Xero: OAuth2 token that expires and must be refreshed). The safe, standard way to get this data into Excel is Power Query, which runs locally on your machine using YOUR credentials — Anthropic/Claude never sees or stores your keys.
B11: 2. CONNECTING STRIPE VIA POWER QUERY (refreshable, no add-in needed)
B12: • In Excel: Data tab → Get Data → From Other Sources → Blank Query → Advanced Editor. Paste the M code below, replacing YOUR_SECRET_KEY with your Stripe secret key (Developers → API keys in the Stripe Dashboard). Use a RESTRICTED key with read-only access to Charges/Payouts.
B14: let
B15: Source = Json.Document(Web.Contents("https://api.stripe.com/v1/charges",
B16: [Headers=[Authorization="Bearer YOUR_SECRET_KEY"]])),
B17: data = Source[data],
B18: #"Converted to Table" = Table.FromList(data, Splitter.SplitByNothing(), null, null, ExtraValues.Error),
B19: #"Expanded" = Table.ExpandRecordColumn(#"Converted to Table", "Column1",
... B98: Customer_Master is the single directory of customer identifiers (Xero contact ID, Stripe customer ID, Meta ad account ID) and metadata (country, industry, relationship owner, payment terms). It doesn’t feed formulas elsewhere automatically — the Assumptions country map is what drives country lookups — but it’s the reference sheet to keep both in sync when you add a new customer.

Sheet Stripe_Raw
A1: STRIPE — RAW TRANSACTION EXPORT (paste your Stripe Payments export below, starting row 4)
A2: Source: Stripe Dashboard > Payments > Export, or Power Query (see README_Setup). Replace sample data below with real export — keep same column order. This tab is pre-formulated for up to 5,000 rows (through row 5003) — just paste your data starting row 4.
A3: Date | B3: Customer | C3: Description | D3: Product/Line Item | E3: Gross Amount (AED) | F3: Stripe Fee (AED) | G3: Net Amount (AED) | H3: Currency | I3: Status | J3: Category (auto)
A4: 46113 | B4: Almoudi Group Tabuk ST | C4: WhatsApp API - Monthly Usage - Almoudi | D4: WhatsApp API - Monthly Usage | E4: 13554.67 | F4: 394.29 | G4: 13160.38 | H4: AED | I4: Paid | J4: =IFERROR(IF(ISNUMBER(SEARCH(Assumptions!$C$5,D4)),Assumptions!$D$5,IF(ISNUMBER(SEARCH(Assumptions!$C$6,D4)),Assumptions!$D$6,IF(ISNUMBER(SEARCH(Assumptions!$C$7,D4)),Assumptions!$D$7,"Other Services"))),"Other Services") -> WhatsApp
A5: 46116 | B5: Jarir Bookstore | C5: Development Retainer - Monthly - Jarir | D5: Development Retainer - Monthly | E5: 12439.23 | F5: 361.94 | G5: 12077.29 | H5: AED | I5: Paid | J5: =IF(D5="","",IFERROR(IF(ISNUMBER(SEARCH(Assumptions!$C$5,D5)),Assumptions!$D$5,IF(ISNUMBER(SEARCH(Assumptions!$C$6,D5)),Assumptions!$D$6,IF(ISNUMBER(SEARCH(Assumptions!$C$7,D5)),Assumptions!$D$7,"Other Services"))),"Other Services")) -> Development
A6: 46126 | B6: United Homeware Company (Nice) | C6: Custom Development - Sprint Invoice - United | D6: Custom Development - Sprint Invoice | E6: 1346.66 | F6: 40.25 | G6: 1306.41 | H6: AED | I6: Paid | J6: =IF(D6="","",IFERROR(IF(ISNUMBER(SEARCH(Assumptions!$C$5,D6)),Assumptions!$D$5,IF(ISNUMBER(SEARCH(Assumptions!$C$6,D6)),Assumptions!$D$6,IF(ISNUMBER(SEARCH(Assumptions!$C$7,D6)),Assumptions!$D$7,"Other Services"))),"Other Services")) -> Development
A7: 46132 | B7: Merck Serono Middle East FZ-Ltd | C7: Custom Development - Sprint Invoice - Merck | D7: Custom Development - Sprint Invoice | E7: 1256.42 | F7: 37.64 | G7: 1218.78 | H7: AED | I7: Paid | J7: =IF(D7="","",IFERROR(IF(ISNUMBER(SEARCH(Assumptions!$C$5,D7)),Assumptions!$D$5,IF(ISNUMBER(SEARCH(Assumptions!$C$6,D7)),Assumptions!$D$6,IF(ISNUMBER(SEARCH(Assumptions!$C$7,D7)),Assumptions!$D$7,"Other Services"))),"Other Services")) -> Development
A8: 46130 | B8: Almoudi Group Tabuk ST | C8: Development Retainer - Monthly - Almoudi | D8: Development Retainer - Monthly | E8: 8015.74 | F8: 233.66 | G8: 7782.08 | H8: AED | I8: Paid | J8: =IF(D8="","",IFERROR(IF(ISNUMBER(SEARCH(Assumptions!$C$5,D8)),Assumptions!$D$5,IF(ISNUMBER(SEARCH(Assumptions!$C$6,D8)),Assumptions!$D$6,IF(ISNUMBER(SEARCH(Assumptions!$C$7,D8)),Assumptions!$D$7,"Other Services"))),"Other Services")) -> Development
A9: 46137 | B9: Growth X Ventures LLC | C9: WhatsApp API - Monthly Usage - Growth | D9: WhatsApp API - Monthly Usage | E9: 14660.09 | F9: 426.34 | G9: 14233.75 | H9: AED | I9: Paid | J9: =IF(D9="","",IFERROR(IF(ISNUMBER(SEARCH(Assumptions!$C$5,D9)),Assumptions!$D$5,IF(ISNUMBER(SEARCH(Assumptions!$C$6,D9)),Assumptions!$D$6,IF(ISNUMBER(SEARCH(Assumptions!$C$7,D9)),Assumptions!$D$7,"Other Services"))),"Other Services")) -> WhatsApp
A10: 46117 | B10: I Farmer Pte Ltd | C10: Subscription - Pro Plan - I | D10: Subscription - Pro Plan | E10: 4503.4 | F10: 131.8 | G10: 4371.6 | H10: AED | I10: Paid | J10: =IF(D10="","",IFERROR(IF(ISNUMBER(SEARCH(Assumptions!$C$5,D10)),Assumptions!$D$5,IF(ISNUMBER(SEARCH(Assumptions!$C$6,D10)),Assumptions!$D$6,IF(ISNUMBER(SEARCH(Assumptions!$C$7,D10)),Assumptions!$D$7,"Other Services"))),"Other Services")) -> Subscription
A11: 46125 | B11: United Homeware Company (Nice) | C11: WhatsApp API - Monthly Usage - United | D11: WhatsApp API - Monthly Usage | E11: 2463.52 | F11: 72.64 | G11: 2390.88 | H11: AED | I11: Paid | J11: =IF(D11="","",IFERROR(IF(ISNUMBER(SEARCH(Assumptions!$C$5,D11)),Assumptions!$D$5,IF(ISNUMBER(SEARCH(Assumptions!$C$6,D11)),Assumptions!$D$6,IF(ISNUMBER(SEARCH(Assumptions!$C$7,D11)),Assumptions!$D$7,"Other Services"))),"Other Services")) -> WhatsApp
A12: 46138 | B12: Nishat Linen UAE | C12: Subscription - Pro Plan - Nishat | D12: Subscription - Pro Plan | E12: 1547.35 | F12: 46.07 | G12: 1501.28 | H12: AED | I12: Paid | J12: =IF(D12="","",IFERROR(IF(ISNUMBER(SEARCH(Assumptions!$C$5,D12)),Assumptions!$D$5,IF(ISNUMBER(SEARCH(Assumptions!$C$6,D12)),Assumptions!$D$6,IF(ISNUMBER(SEARCH(Assumptions!$C$7,D12)),Assumptions!$D$7,"Other Services"))),"Other Services")) -> Subscription
A13: 46115 | B13: United Homeware Company (Nice) | C13: Subscription - Enterprise Plan - United | D13: Subscription - Enterprise Plan | E13: 10295.1 | F13: 299.76 | G13: 9995.34 | H13: AED | I13: Paid | J13: =IF(D13="","",IFERROR(IF(ISNUMBER(SEARCH(Assumptions!$C$5,D13)),Assumptions!$D$5,IF(ISNUMBER(SEARCH(Assumptions!$C$6,D13)),Assumptions!$D$6,IF(ISNUMBER(SEARCH(Assumptions!$C$7,D13)),Assumptions!$D$7,"Other Services"))),"Other Services")) -> Subscription
A14: 46131 | B14: Nishat Linen UAE | C14: Subscription - Pro Plan - Nishat | D14: Subscription - Pro Plan | E14: 4107.36 | F14: 120.31 | G14: 3987.05 | H14: AED | I14: Paid | J14: =IF(D14="","",IFERROR(IF(ISNUMBER(SEARCH(Assumptions!$C$5,D14)),Assumptions!$D$5,IF(ISNUMBER(SEARCH(Assumptions!$C$6,D14)),Assumptions!$D$6,IF(ISNUMBER(SEARCH(Assumptions!$C$7,D14)),Assumptions!$D$7,"Other Services"))),"Other Services")) -> Subscription
A15: 46137 | B15: Almoudi Group Tabuk ST | C15: WhatsApp Business Platform Fee - Almoudi | D15: WhatsApp Business Platform Fee | E15: 5777.47 | F15: 168.75 | G15: 5608.72 | H15: AED | I15: Paid | J15: =IF(D15="","",IFERROR(IF(ISNUMBER(SEARCH(Assumptions!$C$5,D15)),Assumptions!$D$5,IF(ISNUMBER(SEARCH(Assumptions!$C$6,D15)),Assumptions!$D$6,IF(ISNUMBER(SEARCH(Assumptions!$C$7,D15)),Assumptions!$D$7,"Other Services"))),"Other Services")) -> WhatsApp
A16: 46125 | B16: Merck Serono Middle East FZ-Ltd | C16: WhatsApp API - Monthly Usage - Merck | D16: WhatsApp API - Monthly Usage | E16: 5581.15 | F16: 163.05 | G16: 5418.1 | H16: AED | I16: Paid | J16: =IF(D16="","",IFERROR(IF(ISNUMBER(SEARCH(Assumptions!$C$5,D16)),Assumptions!$D$5,IF(ISNUMBER(SEARCH(Assumptions!$C$6,D16)),Assumptions!$D$6,IF(ISNUMBER(SEARCH(Assumptions!$C$7,D16)),Assumptions!$D$7,"Other Services"))),"Other Services")) -> WhatsApp
... A57: 46180 | B57: I Farmer Pte Ltd | C57: Meta Ad Spend Recovery - Jun-2026 | D57: Meta Ad Spend Recovery | E57: 1050.14 | F57: 31.65 | G57: 1018.49 | H57: AED | I57: Paid | J57: =IF(D57="","",IFERROR(IF(ISNUMBER(SEARCH(Assumptions!$C$5,D57)),Assumptions!$D$5,IF(ISNUMBER(SEARCH(Assumptions!$C$6,D57)),Assumptions!$D$6,IF(ISNUMBER(SEARCH(Assumptions!$C$7,D57)),Assumptions!$D$7,"Other Services"))),"Other Services")) -> Other Services
J58: =IF(D58="","",IFERROR(IF(ISNUMBER(SEARCH(Assumptions!$C$5,D58)),Assumptions!$D$5,IF(ISNUMBER(SEARCH(Assumptions!$C$6,D58)),Assumptions!$D$6,IF(ISNUMBER(SEARCH(Assumptions!$C$7,D58)),Assumptions!$D$7,"Other Services"))),"Other Services"))
J59: =IF(D59="","",IFERROR(IF(ISNUMBER(SEARCH(Assumptions!$C$5,D59)),Assumptions!$D$5,IF(ISNUMBER(SEARCH(Assumptions!$C$6,D59)),Assumptions!$D$6,IF(ISNUMBER(SEARCH(Assumptions!$C$7,D59)),Assumptions!$D$7,"Other Services"))),"Other Services"))
J60: =IF(D60="","",IFERROR(IF(ISNUMBER(SEARCH(Assumptions!$C$5,D60)),Assumptions!$D$5,IF(ISNUMBER(SEARCH(Assumptions!$C$6,D60)),Assumptions!$D$6,IF(ISNUMBER(SEARCH(Assumptions!$C$7,D60)),Assumptions!$D$7,"Other Services"))),"Other Services"))
J61: =IF(D61="","",IFERROR(IF(ISNUMBER(SEARCH(Assumptions!$C$5,D61)),Assumptions!$D$5,IF(ISNUMBER(SEARCH(Assumptions!$C$6,D61)),Assumptions!$D$6,IF(ISNUMBER(SEARCH(Assumptions!$C$7,D61)),Assumptions!$D$7,"Other Services"))),"Other Services"))
J62: =IF(D62="","",IFERROR(IF(ISNUMBER(SEARCH(Assumptions!$C$5,D62)),Assumptions!$D$5,IF(ISNUMBER(SEARCH(Assumptions!$C$6,D62)),Assumptions!$D$6,IF(ISNUMBER(SEARCH(Assumptions!$C$7,D62)),Assumptions!$D$7,"Other Services"))),"Other Services"))
J63: =IF(D63="","",IFERROR(IF(ISNUMBER(SEARCH(Assumptions!$C$5,D63)),Assumptions!$D$5,IF(ISNUMBER(SEARCH(Assumptions!$C$6,D63)),Assumptions!$D$6,IF(ISNUMBER(SEARCH(Assumptions!$C$7,D63)),Assumptions!$D$7,"Other Services"))),"Other Services"))
J64: =IF(D64="","",IFERROR(IF(ISNUMBER(SEARCH(Assumptions!$C$5,D64)),Assumptions!$D$5,IF(ISNUMBER(SEARCH(Assumptions!$C$6,D64)),Assumptions!$D$6,IF(ISNUMBER(SEARCH(Assumptions!$C$7,D64)),Assumptions!$D$7,"Other Services"))),"Other Services"))
J65: =IF(D65="","",IFERROR(IF(ISNUMBER(SEARCH(Assumptions!$C$5,D65)),Assumptions!$D$5,IF(ISNUMBER(SEARCH(Assumptions!$C$6,D65)),Assumptions!$D$6,IF(ISNUMBER(SEARCH(Assumptions!$C$7,D65)),Assumptions!$D$7,"Other Services"))),"Other Services"))
J66: =IF(D66="","",IFERROR(IF(ISNUMBER(SEARCH(Assumptions!$C$5,D66)),Assumptions!$D$5,IF(ISNUMBER(SEARCH(Assumptions!$C$6,D66)),Assumptions!$D$6,IF(ISNUMBER(SEARCH(Assumptions!$C$7,D66)),Assumptions!$D$7,"Other Services"))),"Other Services"))
J67: =IF(D67="","",IFERROR(IF(ISNUMBER(SEARCH(Assumptions!$C$5,D67)),Assumptions!$D$5,IF(ISNUMBER(SEARCH(Assumptions!$C$6,D67)),Assumptions!$D$6,IF(ISNUMBER(SEARCH(Assumptions!$C$7,D67)),Assumptions!$D$7,"Other Services"))),"Other Services"))
J68: =IF(D68="","",IFERROR(IF(ISNUMBER(SEARCH(Assumptions!$C$5,D68)),Assumptions!$D$5,IF(ISNUMBER(SEARCH(Assumptions!$C$6,D68)),Assumptions!$D$6,IF(ISNUMBER(SEARCH(Assumptions!$C$7,D68)),Assumptions!$D$7,"Other Services"))),"Other Services"))
J69: =IF(D69="","",IFERROR(IF(ISNUMBER(SEARCH(Assumptions!$C$5,D69)),Assumptions!$D$5,IF(ISNUMBER(SEARCH(Assumptions!$C$6,D69)),Assumptions!$D$6,IF(ISNUMBER(SEARCH(Assumptions!$C$7,D69)),Assumptions!$D$7,"Other Services"))),"Other Services"))
... J5003: =IF(D5003="","",IFERROR(IF(ISNUMBER(SEARCH(Assumptions!$C$5,D5003)),Assumptions!$D$5,IF(ISNUMBER(SEARCH(Assumptions!$C$6,D5003)),Assumptions!$D$6,IF(ISNUMBER(SEARCH(Assumptions!$C$7,D5003)),Assumptions!$D$7,"Other Services"))),"Other Services"))

Sheet Xero_Raw
A1: XERO — RAW LEDGER EXPORT (Invoices + Bills, paste your Xero export below, starting row 4)
A2: Source: Xero > Business > Invoices/Bills > Export, or Power Query (see README_Setup). Type = "Invoice" (AR/Sales) or "Bill" (AP/Expense). This tab is pre-formulated for up to 5,000 rows (through row 5003) — just paste your data starting row 4.
A3: Date | B3: Due Date | C3: Type | D3: Contact | E3: Country (auto) | F3: Account/Line Item | G3: Description | H3: Amount (AED) | I3: Status | J3: Category (auto)
A4: 46115 | B4: 46145 | C4: Invoice | D4: Al Fardan Exchange - Sole Proprietorship L.L.C | E4: =IFERROR(VLOOKUP(D4,Assumptions!$G$5:$H$16,2,0),"Other") -> UAE | F4: Subscription - Pro Plan | G4: Subscription - Pro Plan - Apr-2026 | H4: 31821.05 | I4: Draft | J4: =IFERROR(IF(ISNUMBER(SEARCH(Assumptions!$C$5,G4)),Assumptions!$D$5,IF(ISNUMBER(SEARCH(Assumptions!$C$6,G4)),Assumptions!$D$6,IF(ISNUMBER(SEARCH(Assumptions!$C$7,G4)),Assumptions!$D$7,"Other Services"))),"Other Services") -> Subscription
A5: 46130 | B5: 46160 | C5: Invoice | D5: Curahealth K.S.C.C. | E5: =IF(D5="","",IFERROR(VLOOKUP(D5,Assumptions!$G$5:$H$16,2,0),"Other")) -> Kuwait | F5: WhatsApp Business Platform Fee | G5: WhatsApp Business Platform Fee - Apr-2026 | H5: 9674.09 | I5: Draft | J5: =IF(G5="","",IFERROR(IF(ISNUMBER(SEARCH(Assumptions!$C$5,G5)),Assumptions!$D$5,IF(ISNUMBER(SEARCH(Assumptions!$C$6,G5)),Assumptions!$D$6,IF(ISNUMBER(SEARCH(Assumptions!$C$7,G5)),Assumptions!$D$7,"Other Services"))),"Other Services")) -> WhatsApp
A6: 46128 | B6: 46158 | C6: Invoice | D6: Nishat Linen UAE | E6: =IF(D6="","",IFERROR(VLOOKUP(D6,Assumptions!$G$5:$H$16,2,0),"Other")) -> UAE | F6: Custom Development - Sprint Invoice | G6: Custom Development - Sprint Invoice - Apr-2026 | H6: 16093.84 | I6: Void | J6: =IF(G6="","",IFERROR(IF(ISNUMBER(SEARCH(Assumptions!$C$5,G6)),Assumptions!$D$5,IF(ISNUMBER(SEARCH(Assumptions!$C$6,G6)),Assumptions!$D$6,IF(ISNUMBER(SEARCH(Assumptions!$C$7,G6)),Assumptions!$D$7,"Other Services"))),"Other Services")) -> Development
A7: 46116 | B7: 46146 | C7: Invoice | D7: Misfit Technologies Pte Ltd | E7: =IF(D7="","",IFERROR(VLOOKUP(D7,Assumptions!$G$5:$H$16,2,0),"Other")) -> Singapore | F7: WhatsApp Business Platform Fee | G7: WhatsApp Business Platform Fee - Apr-2026 | H7: 7621.99 | I7: Void | J7: =IF(G7="","",IFERROR(IF(ISNUMBER(SEARCH(Assumptions!$C$5,G7)),Assumptions!$D$5,IF(ISNUMBER(SEARCH(Assumptions!$C$6,G7)),Assumptions!$D$6,IF(ISNUMBER(SEARCH(Assumptions!$C$7,G7)),Assumptions!$D$7,"Other Services"))),"Other Services")) -> WhatsApp
A8: 46127 | B8: 46157 | C8: Invoice | D8: Misfit Technologies Pte Ltd | E8: =IF(D8="","",IFERROR(VLOOKUP(D8,Assumptions!$G$5:$H$16,2,0),"Other")) -> Singapore | F8: Subscription - Enterprise Plan | G8: Subscription - Enterprise Plan - Apr-2026 | H8: 52102.53 | I8: Unsent | J8: =IF(G8="","",IFERROR(IF(ISNUMBER(SEARCH(Assumptions!$C$5,G8)),Assumptions!$D$5,IF(ISNUMBER(SEARCH(Assumptions!$C$6,G8)),Assumptions!$D$6,IF(ISNUMBER(SEARCH(Assumptions!$C$7,G8)),Assumptions!$D$7,"Other Services"))),"Other Services")) -> Subscription
A9: 46116 | B9: 46146 | C9: Invoice | D9: Almoudi Group Tabuk ST | E9: =IF(D9="","",IFERROR(VLOOKUP(D9,Assumptions!$G$5:$H$16,2,0),"Other")) -> Saudi Arabia | F9: Development Retainer - Monthly | G9: Development Retainer - Monthly - Apr-2026 | H9: 5515.54 | I9: Unsent | J9: =IF(G9="","",IFERROR(IF(ISNUMBER(SEARCH(Assumptions!$C$5,G9)),Assumptions!$D$5,IF(ISNUMBER(SEARCH(Assumptions!$C$6,G9)),Assumptions!$D$6,IF(ISNUMBER(SEARCH(Assumptions!$C$7,G9)),Assumptions!$D$7,"Other Services"))),"Other Services")) -> Development
A10: 46119 | B10: 46149 | C10: Invoice | D10: United Homeware Company (Nice) | E10: =IF(D10="","",IFERROR(VLOOKUP(D10,Assumptions!$G$5:$H$16,2,0),"Other")) -> UAE | F10: WhatsApp Business Platform Fee | G10: WhatsApp Business Platform Fee - Apr-2026 | H10: 13032.12 | I10: Draft | J10: =IF(G10="","",IFERROR(IF(ISNUMBER(SEARCH(Assumptions!$C$5,G10)),Assumptions!$D$5,IF(ISNUMBER(SEARCH(Assumptions!$C$6,G10)),Assumptions!$D$6,IF(ISNUMBER(SEARCH(Assumptions!$C$7,G10)),Assumptions!$D$7,"Other Services"))),"Other Services")) -> WhatsApp
A11: 46121 | B11: 46151 | C11: Invoice | D11: Misfit Technologies Pte Ltd | E11: =IF(D11="","",IFERROR(VLOOKUP(D11,Assumptions!$G$5:$H$16,2,0),"Other")) -> Singapore | F11: WhatsApp Business Platform Fee | G11: WhatsApp Business Platform Fee - Apr-2026 | H11: 28832.43 | I11: Void | J11: =IF(G11="","",IFERROR(IF(ISNUMBER(SEARCH(Assumptions!$C$5,G11)),Assumptions!$D$5,IF(ISNUMBER(SEARCH(Assumptions!$C$6,G11)),Assumptions!$D$6,IF(ISNUMBER(SEARCH(Assumptions!$C$7,G11)),Assumptions!$D$7,"Other Services"))),"Other Services")) -> WhatsApp
A12: 46127 | B12: 46127 | C12: Bill | D12: Salary - General & Administration | E12: =IF(D12="","",IFERROR(VLOOKUP(D12,Assumptions!$G$5:$H$16,2,0),"Other")) -> Other | F12: Salary - General & Administration | G12: Salary - General & Administration - Apr-2026 | H12: 20296.54 | I12: Paid | J12: =IF(G12="","",IFERROR(IF(ISNUMBER(SEARCH(Assumptions!$C$5,G12)),Assumptions!$D$5,IF(ISNUMBER(SEARCH(Assumptions!$C$6,G12)),Assumptions!$D$6,IF(ISNUMBER(SEARCH(Assumptions!$C$7,G12)),Assumptions!$D$7,"Other Services"))),"Other Services")) -> Other Services
A13: 46116 | B13: 46116 | C13: Bill | D13: Travel Expense | E13: =IF(D13="","",IFERROR(VLOOKUP(D13,Assumptions!$G$5:$H$16,2,0),"Other")) -> Other | F13: Travel Expense | G13: Travel Expense - Apr-2026 | H13: 1739.41 | I13: Paid | J13: =IF(G13="","",IFERROR(IF(ISNUMBER(SEARCH(Assumptions!$C$5,G13)),Assumptions!$D$5,IF(ISNUMBER(SEARCH(Assumptions!$C$6,G13)),Assumptions!$D$6,IF(ISNUMBER(SEARCH(Assumptions!$C$7,G13)),Assumptions!$D$7,"Other Services"))),"Other Services")) -> Other Services
A14: 46113 | B14: 46113 | C14: Bill | D14: Travel Expense | E14: =IF(D14="","",IFERROR(VLOOKUP(D14,Assumptions!$G$5:$H$16,2,0),"Other")) -> Other | F14: Travel Expense | G14: Travel Expense - Apr-2026 | H14: 24240.41 | I14: Paid | J14: =IF(G14="","",IFERROR(IF(ISNUMBER(SEARCH(Assumptions!$C$5,G14)),Assumptions!$D$5,IF(ISNUMBER(SEARCH(Assumptions!$C$6,G14)),Assumptions!$D$6,IF(ISNUMBER(SEARCH(Assumptions!$C$7,G14)),Assumptions!$D$7,"Other Services"))),"Other Services")) -> Other Services
A15: 46118 | B15: 46118 | C15: Bill | D15: Office Rent | E15: =IF(D15="","",IFERROR(VLOOKUP(D15,Assumptions!$G$5:$H$16,2,0),"Other")) -> Other | F15: Office Rent | G15: Office Rent - Apr-2026 | H15: 10457.14 | I15: Paid | J15: =IF(G15="","",IFERROR(IF(ISNUMBER(SEARCH(Assumptions!$C$5,G15)),Assumptions!$D$5,IF(ISNUMBER(SEARCH(Assumptions!$C$6,G15)),Assumptions!$D$6,IF(ISNUMBER(SEARCH(Assumptions!$C$7,G15)),Assumptions!$D$7,"Other Services"))),"Other Services")) -> Other Services
A16: 46119 | B16: 46119 | C16: Bill | D16: Trade License Fee | E16: =IF(D16="","",IFERROR(VLOOKUP(D16,Assumptions!$G$5:$H$16,2,0),"Other")) -> Other | F16: Trade License Fee | G16: Trade License Fee - Apr-2026 | H16: 21683.93 | I16: Paid | J16: =IF(G16="","",IFERROR(IF(ISNUMBER(SEARCH(Assumptions!$C$5,G16)),Assumptions!$D$5,IF(ISNUMBER(SEARCH(Assumptions!$C$6,G16)),Assumptions!$D$6,IF(ISNUMBER(SEARCH(Assumptions!$C$7,G16)),Assumptions!$D$7,"Other Services"))),"Other Services")) -> Other Services
... A42: 46197 | B42: 46197 | C42: Bill | D42: Office Rent | E42: =IF(D42="","",IFERROR(VLOOKUP(D42,Assumptions!$G$5:$H$16,2,0),"Other")) -> Other | F42: Office Rent | G42: Office Rent - Jun-2026 | H42: 11324.97 | I42: Paid | J42: =IF(G42="","",IFERROR(IF(ISNUMBER(SEARCH(Assumptions!$C$5,G42)),Assumptions!$D$5,IF(ISNUMBER(SEARCH(Assumptions!$C$6,G42)),Assumptions!$D$6,IF(ISNUMBER(SEARCH(Assumptions!$C$7,G42)),Assumptions!$D$7,"Other Services"))),"Other Services")) -> Other Services
E43: =IF(D43="","",IFERROR(VLOOKUP(D43,Assumptions!$G$5:$H$16,2,0),"Other")) | J43: =IF(G43="","",IFERROR(IF(ISNUMBER(SEARCH(Assumptions!$C$5,G43)),Assumptions!$D$5,IF(ISNUMBER(SEARCH(Assumptions!$C$6,G43)),Assumptions!$D$6,IF(ISNUMBER(SEARCH(Assumptions!$C$7,G43)),Assumptions!$D$7,"Other Services"))),"Other Services"))
E44: =IF(D44="","",IFERROR(VLOOKUP(D44,Assumptions!$G$5:$H$16,2,0),"Other")) | J44: =IF(G44="","",IFERROR(IF(ISNUMBER(SEARCH(Assumptions!$C$5,G44)),Assumptions!$D$5,IF(ISNUMBER(SEARCH(Assumptions!$C$6,G44)),Assumptions!$D$6,IF(ISNUMBER(SEARCH(Assumptions!$C$7,G44)),Assumptions!$D$7,"Other Services"))),"Other Services"))
E45: =IF(D45="","",IFERROR(VLOOKUP(D45,Assumptions!$G$5:$H$16,2,0),"Other")) | J45: =IF(G45="","",IFERROR(IF(ISNUMBER(SEARCH(Assumptions!$C$5,G45)),Assumptions!$D$5,IF(ISNUMBER(SEARCH(Assumptions!$C$6,G45)),Assumptions!$D$6,IF(ISNUMBER(SEARCH(Assumptions!$C$7,G45)),Assumptions!$D$7,"Other Services"))),"Other Services"))
E46: =IF(D46="","",IFERROR(VLOOKUP(D46,Assumptions!$G$5:$H$16,2,0),"Other")) | J46: =IF(G46="","",IFERROR(IF(ISNUMBER(SEARCH(Assumptions!$C$5,G46)),Assumptions!$D$5,IF(ISNUMBER(SEARCH(Assumptions!$C$6,G46)),Assumptions!$D$6,IF(ISNUMBER(SEARCH(Assumptions!$C$7,G46)),Assumptions!$D$7,"Other Services"))),"Other Services"))
E47: =IF(D47="","",IFERROR(VLOOKUP(D47,Assumptions!$G$5:$H$16,2,0),"Other")) | J47: =IF(G47="","",IFERROR(IF(ISNUMBER(SEARCH(Assumptions!$C$5,G47)),Assumptions!$D$5,IF(ISNUMBER(SEARCH(Assumptions!$C$6,G47)),Assumptions!$D$6,IF(ISNUMBER(SEARCH(Assumptions!$C$7,G47)),Assumptions!$D$7,"Other Services"))),"Other Services"))
E48: =IF(D48="","",IFERROR(VLOOKUP(D48,Assumptions!$G$5:$H$16,2,0),"Other")) | J48: =IF(G48="","",IFERROR(IF(ISNUMBER(SEARCH(Assumptions!$C$5,G48)),Assumptions!$D$5,IF(ISNUMBER(SEARCH(Assumptions!$C$6,G48)),Assumptions!$D$6,IF(ISNUMBER(SEARCH(Assumptions!$C$7,G48)),Assumptions!$D$7,"Other Services"))),"Other Services"))
E49: =IF(D49="","",IFERROR(VLOOKUP(D49,Assumptions!$G$5:$H$16,2,0),"Other")) | J49: =IF(G49="","",IFERROR(IF(ISNUMBER(SEARCH(Assumptions!$C$5,G49)),Assumptions!$D$5,IF(ISNUMBER(SEARCH(Assumptions!$C$6,G49)),Assumptions!$D$6,IF(ISNUMBER(SEARCH(Assumptions!$C$7,G49)),Assumptions!$D$7,"Other Services"))),"Other Services"))
E50: =IF(D50="","",IFERROR(VLOOKUP(D50,Assumptions!$G$5:$H$16,2,0),"Other")) | J50: =IF(G50="","",IFERROR(IF(ISNUMBER(SEARCH(Assumptions!$C$5,G50)),Assumptions!$D$5,IF(ISNUMBER(SEARCH(Assumptions!$C$6,G50)),Assumptions!$D$6,IF(ISNUMBER(SEARCH(Assumptions!$C$7,G50)),Assumptions!$D$7,"Other Services"))),"Other Services"))
E51: =IF(D51="","",IFERROR(VLOOKUP(D51,Assumptions!$G$5:$H$16,2,0),"Other")) | J51: =IF(G51="","",IFERROR(IF(ISNUMBER(SEARCH(Assumptions!$C$5,G51)),Assumptions!$D$5,IF(ISNUMBER(SEARCH(Assumptions!$C$6,G51)),Assumptions!$D$6,IF(ISNUMBER(SEARCH(Assumptions!$C$7,G51)),Assumptions!$D$7,"Other Services"))),"Other Services"))
E52: =IF(D52="","",IFERROR(VLOOKUP(D52,Assumptions!$G$5:$H$16,2,0),"Other")) | J52: =IF(G52="","",IFERROR(IF(ISNUMBER(SEARCH(Assumptions!$C$5,G52)),Assumptions!$D$5,IF(ISNUMBER(SEARCH(Assumptions!$C$6,G52)),Assumptions!$D$6,IF(ISNUMBER(SEARCH(Assumptions!$C$7,G52)),Assumptions!$D$7,"Other Services"))),"Other Services"))
E53: =IF(D53="","",IFERROR(VLOOKUP(D53,Assumptions!$G$5:$H$16,2,0),"Other")) | J53: =IF(G53="","",IFERROR(IF(ISNUMBER(SEARCH(Assumptions!$C$5,G53)),Assumptions!$D$5,IF(ISNUMBER(SEARCH(Assumptions!$C$6,G53)),Assumptions!$D$6,IF(ISNUMBER(SEARCH(Assumptions!$C$7,G53)),Assumptions!$D$7,"Other Services"))),"Other Services"))
E54: =IF(D54="","",IFERROR(VLOOKUP(D54,Assumptions!$G$5:$H$16,2,0),"Other")) | J54: =IF(G54="","",IFERROR(IF(ISNUMBER(SEARCH(Assumptions!$C$5,G54)),Assumptions!$D$5,IF(ISNUMBER(SEARCH(Assumptions!$C$6,G54)),Assumptions!$D$6,IF(ISNUMBER(SEARCH(Assumptions!$C$7,G54)),Assumptions!$D$7,"Other Services"))),"Other Services"))
... E5003: =IF(D5003="","",IFERROR(VLOOKUP(D5003,Assumptions!$G$5:$H$16,2,0),"Other")) | J5003: =IF(G5003="","",IFERROR(IF(ISNUMBER(SEARCH(Assumptions!$C$5,G5003)),Assumptions!$D$5,IF(ISNUMBER(SEARCH(Assumptions!$C$6,G5003)),Assumptions!$D$6,IF(ISNUMBER(SEARCH(Assumptions!$C$7,G5003)),Assumptions!$D$7,"Other Services"))),"Other Services"))

Sheet Bank_Raw
A1: BANK STATEMENT — RAW EXPORT (paste your bank statement CSV/PDF-extracted lines below, starting row 4)
A2: Source: Wio Bank / bank portal statement export. Used for cash position reconciliation on Dashboard. This tab is pre-sized for up to 5,000 rows (through row 5003).
A3: Date | B3: Account | C3: Description | D3: Money In (AED) | E3: Money Out (AED) | F3: Balance (AED) | G3: Customer (if applicable — tag receipts that recover Meta ad spend)
A4: 46116 | B4: Wio Bank PJSC - 650 (USD) | C4: Salary run | D4: 0 | E4: 2681.54 | F4: 247318.46
A5: 46119 | B5: Wio Bank PJSC - 451 (AED) | C5: Salary run | D5: 0 | E5: 11858.94 | F5: 235459.52
A6: 46121 | B6: Wio Bank PJSC - 451 (AED) | C6: Customer receipt - Meta ad spend recovery | D6: 15221.41 | E6: 0 | F6: 250680.93 | G6: Growth X Ventures LLC
A7: 46122 | B7: Wio Bank PJSC - 650 (USD) | C7: Customer receipt - Meta ad spend recovery | D7: 10731.66 | E7: 0 | F7: 261412.59 | G7: United Homeware Company (Nice)
A8: 46123 | B8: Wio Bank PJSC - 650 (USD) | C8: SaaS subscription | D8: 0 | E8: 17740.63 | F8: 243671.96
A9: 46126 | B9: Wio Bank PJSC - 451 (AED) | C9: Salary run | D9: 0 | E9: 5116.38 | F9: 238555.58
A10: 46127 | B10: Wio Bank PJSC - 650 (USD) | C10: Customer receipt - Meta ad spend recovery | D10: 29726.01 | E10: 0 | F10: 268281.59 | G10: Growth X Ventures LLC
A11: 46129 | B11: Wio Bank PJSC - 650 (USD) | C11: Salary run | D11: 0 | E11: 17349.25 | F11: 250932.34
A12: 46131 | B12: Wio Bank PJSC - 451 (AED) | C12: Meta Ads payment | D12: 0 | E12: 2607.86 | F12: 248324.48
A13: 46133 | B13: Wio Bank PJSC - 451 (AED) | C13: Customer receipt | D13: 36819.62 | E13: 0 | F13: 285144.1
A14: 46135 | B14: Wio Bank PJSC - 650 (USD) | C14: Salary run | D14: 0 | E14: 17490.8 | F14: 267653.3
A15: 46136 | B15: Wio Bank PJSC - 451 (AED) | C15: Customer receipt | D15: 11865.52 | E15: 0 | F15: 279518.82
A16: 46137 | B16: Wio Bank PJSC - 650 (USD) | C16: Customer receipt | D16: 20866.82 | E16: 0 | F16: 300385.64
A17: 46140 | B17: Wio Bank PJSC - 650 (USD) | C17: Office rent | D17: 0 | E17: 2749.16 | F17: 297636.48
A18: 46141 | B18: Wio Bank PJSC - 650 (USD) | C18: Customer receipt | D18: 24266.28 | E18: 0 | F18: 321902.76
A19: 46143 | B19: Wio Bank PJSC - 650 (USD) | C19: Customer receipt | D19: 39385.2 | E19: 0 | F19: 361287.96
A20: 46144 | B20: Wio Bank PJSC - 650 (USD) | C20: Meta Ads payment | D20: 0 | E20: 4206.54 | F20: 357081.42
A21: 46147 | B21: Wio Bank PJSC - 650 (USD) | C21: Customer receipt | D21: 37097.43 | E21: 0 | F21: 394178.85
A22: 46150 | B22: Wio Bank PJSC - 451 (AED) | C22: Customer receipt | D22: 3728.98 | E22: 0 | F22: 397907.83
... A44: 46201 | B44: Wio Bank PJSC - 451 (AED) | C44: Customer receipt | D44: 10019.2 | E44: 0 | F44: 499639.33

Sheet Meta_Invoices
A1: META (FACEBOOK/INSTAGRAM ADS) — MONTHLY INVOICE DETAIL, RE-CHARGED TO CUSTOMERS
A2: Each Meta PDF invoice bundles multiple customer ad accounts. Enter one row per customer/campaign line as shown on the PDF. Meta shows "Amount Charged" NET of any coupon/discount applied — Gross Amount below ADDS the discount back, so the single Gross figure reflects the true ad spend value delivered per customer before any Meta promo credit. This tab is pre-sized for up to 5,000 rows (through row 5003).
A3: Invoice Date | B3: Invoice No. | C3: Month | D3: Customer | E3: Ad Account ID | F3: Campaign | G3: Amount Charged (Net, AED) | H3: Discount / Coupon Applied (AED) | I3: Gross Amount (Charged+Discount) (AED) | J3: Currency | K3: Notes
A4: 46115 | B4: META-100231 | C4: =TEXT(A4,"mmm-yyyy") -> Apr-2026 | D4: Al Fardan Exchange - Sole Proprietorship L.L.C | E4: act_961168 | F4: Prospecting - Reach | G4: 3996.67 | H4: 228.78 | I4: =G4+H4 -> 4225.45 | J4: AED | K4: Coupon applied
A5: 46115 | B5: META-100231 | C5: =IF(A5="","",TEXT(A5,"mmm-yyyy")) -> Apr-2026 | D5: Al Fardan Exchange - Sole Proprietorship L.L.C | E5: act_139317 | F5: Prospecting - Reach | G5: 1726.19 | H5: 217.7 | I5: =IF(G5="","",G5+H5) -> 1943.89 | J5: AED | K5: Coupon applied
A6: 46115 | B6: META-100231 | C6: =IF(A6="","",TEXT(A6,"mmm-yyyy")) -> Apr-2026 | D6: United Homeware Company (Nice) | E6: act_161981 | F6: Prospecting - Reach | G6: 1930.87 | H6: 256.14 | I6: =IF(G6="","",G6+H6) -> 2187.01 | J6: AED | K6: Coupon applied
A7: 46115 | B7: META-100231 | C7: =IF(A7="","",TEXT(A7,"mmm-yyyy")) -> Apr-2026 | D7: United Homeware Company (Nice) | E7: act_711316 | F7: Prospecting - Reach | G7: 3995.05 | H7: 0 | I7: =IF(G7="","",G7+H7) -> 3995.05 | J7: AED
A8: 46115 | B8: META-100231 | C8: =IF(A8="","",TEXT(A8,"mmm-yyyy")) -> Apr-2026 | D8: Growth X Ventures LLC | E8: act_239643 | F8: Brand Awareness | G8: 493.4 | H8: 65.87 | I8: =IF(G8="","",G8+H8) -> 559.27 | J8: AED | K8: Coupon applied
A9: 46115 | B9: META-100231 | C9: =IF(A9="","",TEXT(A9,"mmm-yyyy")) -> Apr-2026 | D9: Growth X Ventures LLC | E9: act_687472 | F9: Retargeting - Conversions | G9: 1934.64 | H9: 262.41 | I9: =IF(G9="","",G9+H9) -> 2197.05 | J9: AED | K9: Coupon applied
A10: 46115 | B10: META-100231 | C10: =IF(A10="","",TEXT(A10,"mmm-yyyy")) -> Apr-2026 | D10: I Farmer Pte Ltd | E10: act_490487 | F10: Prospecting - Reach | G10: 2568.24 | H10: 0 | I10: =IF(G10="","",G10+H10) -> 2568.24 | J10: AED
A11: 46115 | B11: META-100231 | C11: =IF(A11="","",TEXT(A11,"mmm-yyyy")) -> Apr-2026 | D11: Misfit Technologies Pte Ltd | E11: act_620528 | F11: Lead Gen - Lookalike | G11: 2501.04 | H11: 0 | I11: =IF(G11="","",G11+H11) -> 2501.04 | J11: AED
A12: 46115 | B12: META-100231 | C12: =IF(A12="","",TEXT(A12,"mmm-yyyy")) -> Apr-2026 | D12: Nishat Linen UAE | E12: act_479146 | F12: Brand Awareness | G12: 2115.85 | H12: 0 | I12: =IF(G12="","",G12+H12) -> 2115.85 | J12: AED
A13: 46115 | B13: META-100231 | C13: =IF(A13="","",TEXT(A13,"mmm-yyyy")) -> Apr-2026 | D13: Nishat Linen UAE | E13: act_185831 | F13: Brand Awareness | G13: 1268.86 | H13: 211.87 | I13: =IF(G13="","",G13+H13) -> 1480.73 | J13: AED | K13: Coupon applied
A14: 46145 | B14: META-100232 | C14: =IF(A14="","",TEXT(A14,"mmm-yyyy")) -> May-2026 | D14: Al Fardan Exchange - Sole Proprietorship L.L.C | E14: act_401924 | F14: Prospecting - Reach | G14: 3713.04 | H14: 0 | I14: =IF(G14="","",G14+H14) -> 3713.04 | J14: AED
A15: 46145 | B15: META-100232 | C15: =IF(A15="","",TEXT(A15,"mmm-yyyy")) -> May-2026 | D15: Al Fardan Exchange - Sole Proprietorship L.L.C | E15: act_259367 | F15: Lead Gen - Lookalike | G15: 760.46 | H15: 124.39 | I15: =IF(G15="","",G15+H15) -> 884.85 | J15: AED | K15: Coupon applied
A16: 46145 | B16: META-100232 | C16: =IF(A16="","",TEXT(A16,"mmm-yyyy")) -> May-2026 | D16: United Homeware Company (Nice) | E16: act_901710 | F16: Brand Awareness | G16: 452.91 | H16: 0 | I16: =IF(G16="","",G16+H16) -> 452.91 | J16: AED
A17: 46145 | B17: META-100232 | C17: =IF(A17="","",TEXT(A17,"mmm-yyyy")) -> May-2026 | D17: United Homeware Company (Nice) | E17: act_935601 | F17: Lead Gen - Lookalike | G17: 1626.48 | H17: 202.5 | I17: =IF(G17="","",G17+H17) -> 1828.98 | J17: AED | K17: Coupon applied
A18: 46145 | B18: META-100232 | C18: =IF(A18="","",TEXT(A18,"mmm-yyyy")) -> May-2026 | D18: Growth X Ventures LLC | E18: act_597128 | F18: Prospecting - Reach | G18: 3575.87 | H18: 0 | I18: =IF(G18="","",G18+H18) -> 3575.87 | J18: AED
A19: 46145 | B19: META-100232 | C19: =IF(A19="","",TEXT(A19,"mmm-yyyy")) -> May-2026 | D19: I Farmer Pte Ltd | E19: act_814328 | F19: Lead Gen - Lookalike | G19: 3151.52 | H19: 430.79 | I19: =IF(G19="","",G19+H19) -> 3582.31 | J19: AED | K19: Coupon applied
A20: 46145 | B20: META-100232 | C20: =IF(A20="","",TEXT(A20,"mmm-yyyy")) -> May-2026 | D20: Misfit Technologies Pte Ltd | E20: act_463861 | F20: Prospecting - Reach | G20: 3094.85 | H20: 0 | I20: =IF(G20="","",G20+H20) -> 3094.85 | J20: AED
A21: 46145 | B21: META-100232 | C21: =IF(A21="","",TEXT(A21,"mmm-yyyy")) -> May-2026 | D21: Misfit Technologies Pte Ltd | E21: act_617674 | F21: Prospecting - Reach | G21: 3968.53 | H21: 562.09 | I21: =IF(G21="","",G21+H21) -> 4530.62 | J21: AED | K21: Coupon applied
A22: 46145 | B22: META-100232 | C22: =IF(A22="","",TEXT(A22,"mmm-yyyy")) -> May-2026 | D22: Nishat Linen UAE | E22: act_509940 | F22: Lead Gen - Lookalike | G22: 3296.11 | H22: 287.23 | I22: =IF(G22="","",G22+H22) -> 3583.34 | J22: AED | K22: Coupon applied
A23: 46176 | B23: META-100233 | C23: =IF(A23="","",TEXT(A23,"mmm-yyyy")) -> Jun-2026 | D23: Al Fardan Exchange - Sole Proprietorship L.L.C | E23: act_243577 | F23: Lead Gen - Lookalike | G23: 948.83 | H23: 86.98 | I23: =IF(G23="","",G23+H23) -> 1035.81 | J23: AED | K23: Coupon applied
A24: 46176 | B24: META-100233 | C24: =IF(A24="","",TEXT(A24,"mmm-yyyy")) -> Jun-2026 | D24: United Homeware Company (Nice) | E24: act_815887 | F24: Lead Gen - Lookalike | G24: 3054.95 | H24: 0 | I24: =IF(G24="","",G24+H24) -> 3054.95 | J24: AED
A25: 46176 | B25: META-100233 | C25: =IF(A25="","",TEXT(A25,"mmm-yyyy")) -> Jun-2026 | D25: United Homeware Company (Nice) | E25: act_343224 | F25: Retargeting - Conversions | G25: 4035.15 | H25: 308.42 | I25: =IF(G25="","",G25+H25) -> 4343.57 | J25: AED | K25: Coupon applied
A26: 46176 | B26: META-100233 | C26: =IF(A26="","",TEXT(A26,"mmm-yyyy")) -> Jun-2026 | D26: Growth X Ventures LLC | E26: act_375509 | F26: Brand Awareness | G26: 2191.35 | H26: 0 | I26: =IF(G26="","",G26+H26) -> 2191.35 | J26: AED
A27: 46176 | B27: META-100233 | C27: =IF(A27="","",TEXT(A27,"mmm-yyyy")) -> Jun-2026 | D27: I Farmer Pte Ltd | E27: act_434088 | F27: Retargeting - Conversions | G27: 868.14 | H27: 122.82 | I27: =IF(G27="","",G27+H27) -> 990.96 | J27: AED | K27: Coupon applied
A28: 46176 | B28: META-100233 | C28: =IF(A28="","",TEXT(A28,"mmm-yyyy")) -> Jun-2026 | D28: Misfit Technologies Pte Ltd | E28: act_813634 | F28: Lead Gen - Lookalike | G28: 2080.91 | H28: 0 | I28: =IF(G28="","",G28+H28) -> 2080.91 | J28: AED
A29: 46176 | B29: META-100233 | C29: =IF(A29="","",TEXT(A29,"mmm-yyyy")) -> Jun-2026 | D29: Nishat Linen UAE | E29: act_165271 | F29: Retargeting - Conversions | G29: 1856.02 | H29: 269.39 | I29: =IF(G29="","",G29+H29) -> 2125.41 | J29: AED | K29: Coupon applied
A30: 46176 | B30: META-100233 | C30: =IF(A30="","",TEXT(A30,"mmm-yyyy")) -> Jun-2026 | D30: Nishat Linen UAE | E30: act_456572 | F30: Prospecting - Reach | G30: 562.66 | H30: 41.83 | I30: =IF(G30="","",G30+H30) -> 604.49 | J30: AED | K30: Coupon applied
C31: =IF(A31="","",TEXT(A31,"mmm-yyyy")) | I31: =IF(G31="","",G31+H31)
C32: =IF(A32="","",TEXT(A32,"mmm-yyyy")) | I32: =IF(G32="","",G32+H32)
C33: =IF(A33="","",TEXT(A33,"mmm-yyyy")) | I33: =IF(G33="","",G33+H33)
C34: =IF(A34="","",TEXT(A34,"mmm-yyyy")) | I34: =IF(G34="","",G34+H34)
C35: =IF(A35="","",TEXT(A35,"mmm-yyyy")) | I35: =IF(G35="","",G35+H35)
C36: =IF(A36="","",TEXT(A36,"mmm-yyyy")) | I36: =IF(G36="","",G36+H36)
C37: =IF(A37="","",TEXT(A37,"mmm-yyyy")) | I37: =IF(G37="","",G37+H37)
C38: =IF(A38="","",TEXT(A38,"mmm-yyyy")) | I38: =IF(G38="","",G38+H38)
C39: =IF(A39="","",TEXT(A39,"mmm-yyyy")) | I39: =IF(G39="","",G39+H39)
C40: =IF(A40="","",TEXT(A40,"mmm-yyyy")) | I40: =IF(G40="","",G40+H40)
C41: =IF(A41="","",TEXT(A41,"mmm-yyyy")) | I41: =IF(G41="","",G41+H41)
C42: =IF(A42="","",TEXT(A42,"mmm-yyyy")) | I42: =IF(G42="","",G42+H42)
... C5003: =IF(A5003="","",TEXT(A5003,"mmm-yyyy")) | I5003: =IF(G5003="","",G5003+H5003)
A5010: PER-CUSTOMER MONTHLY SUMMARY — SINGLE GROSS AMOUNT (DISCOUNT ADDED BACK)
A5011: Customer | B5011: Month | C5011: Total Amount Charged (Net, AED) | D5011: Total Discount Added Back (AED) | E5011: Single Gross Amount (AED)
A5012: Al Fardan Exchange - Sole Proprietorship L.L.C | B5012: Apr-2026 | C5012: =SUMIFS($G$4:$G$5003,$D$4:$D$5003,$A5012,$C$4:$C$5003,$B5012) -> 5722.86 | D5012: =SUMIFS($H$4:$H$5003,$D$4:$D$5003,$A5012,$C$4:$C$5003,$B5012) -> 446.48 | E5012: =C5012+D5012 -> 6169.34
A5013: United Homeware Company (Nice) | B5013: Apr-2026 | C5013: =SUMIFS($G$4:$G$5003,$D$4:$D$5003,$A5013,$C$4:$C$5003,$B5013) -> 5925.92 | D5013: =SUMIFS($H$4:$H$5003,$D$4:$D$5003,$A5013,$C$4:$C$5003,$B5013) -> 256.14 | E5013: =C5013+D5013 -> 6182.06
A5014: Growth X Ventures LLC | B5014: Apr-2026 | C5014: =SUMIFS($G$4:$G$5003,$D$4:$D$5003,$A5014,$C$4:$C$5003,$B5014) -> 2428.04 | D5014: =SUMIFS($H$4:$H$5003,$D$4:$D$5003,$A5014,$C$4:$C$5003,$B5014) -> 328.28 | E5014: =C5014+D5014 -> 2756.32
A5015: I Farmer Pte Ltd | B5015: Apr-2026 | C5015: =SUMIFS($G$4:$G$5003,$D$4:$D$5003,$A5015,$C$4:$C$5003,$B5015) -> 2568.24 | D5015: =SUMIFS($H$4:$H$5003,$D$4:$D$5003,$A5015,$C$4:$C$5003,$B5015) -> 0 | E5015: =C5015+D5015 -> 2568.24
A5016: Misfit Technologies Pte Ltd | B5016: Apr-2026 | C5016: =SUMIFS($G$4:$G$5003,$D$4:$D$5003,$A5016,$C$4:$C$5003,$B5016) -> 2501.04 | D5016: =SUMIFS($H$4:$H$5003,$D$4:$D$5003,$A5016,$C$4:$C$5003,$B5016) -> 0 | E5016: =C5016+D5016 -> 2501.04
A5017: Nishat Linen UAE | B5017: Apr-2026 | C5017: =SUMIFS($G$4:$G$5003,$D$4:$D$5003,$A5017,$C$4:$C$5003,$B5017) -> 3384.71 | D5017: =SUMIFS($H$4:$H$5003,$D$4:$D$5003,$A5017,$C$4:$C$5003,$B5017) -> 211.87 | E5017: =C5017+D5017 -> 3596.58
A5018: Al Fardan Exchange - Sole Proprietorship L.L.C | B5018: May-2026 | C5018: =SUMIFS($G$4:$G$5003,$D$4:$D$5003,$A5018,$C$4:$C$5003,$B5018) -> 4473.5 | D5018: =SUMIFS($H$4:$H$5003,$D$4:$D$5003,$A5018,$C$4:$C$5003,$B5018) -> 124.39 | E5018: =C5018+D5018 -> 4597.89
A5019: United Homeware Company (Nice) | B5019: May-2026 | C5019: =SUMIFS($G$4:$G$5003,$D$4:$D$5003,$A5019,$C$4:$C$5003,$B5019) -> 2079.39 | D5019: =SUMIFS($H$4:$H$5003,$D$4:$D$5003,$A5019,$C$4:$C$5003,$B5019) -> 202.5 | E5019: =C5019+D5019 -> 2281.89
A5020: Growth X Ventures LLC | B5020: May-2026 | C5020: =SUMIFS($G$4:$G$5003,$D$4:$D$5003,$A5020,$C$4:$C$5003,$B5020) -> 3575.87 | D5020: =SUMIFS($H$4:$H$5003,$D$4:$D$5003,$A5020,$C$4:$C$5003,$B5020) -> 0 | E5020: =C5020+D5020 -> 3575.87
A5021: I Farmer Pte Ltd | B5021: May-2026 | C5021: =SUMIFS($G$4:$G$5003,$D$4:$D$5003,$A5021,$C$4:$C$5003,$B5021) -> 3151.52 | D5021: =SUMIFS($H$4:$H$5003,$D$4:$D$5003,$A5021,$C$4:$C$5003,$B5021) -> 430.79 | E5021: =C5021+D5021 -> 3582.31
A5022: Misfit Technologies Pte Ltd | B5022: May-2026 | C5022: =SUMIFS($G$4:$G$5003,$D$4:$D$5003,$A5022,$C$4:$C$5003,$B5022) -> 7063.38 | D5022: =SUMIFS($H$4:$H$5003,$D$4:$D$5003,$A5022,$C$4:$C$5003,$B5022) -> 562.09 | E5022: =C5022+D5022 -> 7625.47
A5023: Nishat Linen UAE | B5023: May-2026 | C5023: =SUMIFS($G$4:$G$5003,$D$4:$D$5003,$A5023,$C$4:$C$5003,$B5023) -> 3296.11 | D5023: =SUMIFS($H$4:$H$5003,$D$4:$D$5003,$A5023,$C$4:$C$5003,$B5023) -> 287.23 | E5023: =C5023+D5023 -> 3583.34
... A5029: Nishat Linen UAE | B5029: Jun-2026 | C5029: =SUMIFS($G$4:$G$5003,$D$4:$D$5003,$A5029,$C$4:$C$5003,$B5029) -> 2418.68 | D5029: =SUMIFS($H$4:$H$5003,$D$4:$D$5003,$A5029,$C$4:$C$5003,$B5029) -> 311.22 | E5029: =C5029+D5029 -> 2729.9

Sheet Assumptions
A1: ASSUMPTIONS & MAPPING TABLES — EDIT THESE (BLUE) TO RECLASSIFY DATA ACROSS THE WHOLE DASHBOARD
B3: REVENUE CATEGORY KEYWORD MAP | G3: CUSTOMER → COUNTRY MAP (drives UAE / Singapore / Other split on Receivables tab)
B4: # | C4: Keyword (searched in Description, not case-sensitive) | D4: Maps to Category | G4: Customer / Contact Name | H4: Country
B5: 1 | C5: whatsapp | D5: WhatsApp | G5: Al Fardan Exchange - Sole Proprietorship L.L.C | H5: UAE
B6: 2 | C6: subscription | D6: Subscription | G6: United Homeware Company (Nice) | H6: UAE
B7: 3 | C7: development | D7: Development | G7: Jarir Bookstore | H7: Saudi Arabia
G8: Merck Serono Middle East FZ-Ltd | H8: UAE
B9: Note: rows 5-7 are referenced directly by formulas in Stripe_Raw!J and Xero_Raw!J. To add a 4th category, extend the formula in those sheets. | G9: Growth X Ventures LLC | H9: UAE
G10: I Farmer Pte Ltd | H10: Singapore
G11: Misfit Technologies Pte Ltd | H11: Singapore
G12: Curahealth K.S.C.C. | H12: Kuwait
G13: Ticket Wala | H13: Pakistan
G14: Nishat Linen UAE | H14: UAE
G15: Almoudi Group Tabuk ST | H15: Saudi Arabia
G16: Faysal Bank | H16: Pakistan
G18: Add new rows here as new customers/contacts appear in Xero — VLOOKUP range is $G$5:$H$16, extend if needed.
B22: COLOR LEGEND
B23: Blue text | C23: Hardcoded input — raw data pasted from Stripe/Xero/bank/Meta exports, or editable assumptions
B24: Black text | C24: Formula / calculation
B25: Green text | C25: Link pulling from another sheet in this workbook
B26: Yellow fill | C26: Key assumption cell — review/update before relying on outputs
B29: GENERAL ASSUMPTIONS
B30: Reporting Currency | C30: AED
B31: AR Aging Buckets (days) | C31: 0-30 / 31-60 / 61-90 / 90+
B32: Dashboard Period | C32: Apr-2026 to Jun-2026 (sample data)

Sheet Credit_Card_Upload
A1: CREDIT CARD STATEMENTS — UPLOAD ZONE
A2: HOW TO USE: 1) Upload your credit card statement (PDF or Excel/CSV) in the chat to Claude and ask it to extract the transactions into this tab — Claude will read the statement and paste the rows below in this exact format. 2) Or paste your own exported transactions manually, keeping the same columns. Category is auto-classified from the Assumptions keyword map; anything unmatched shows "Other Services" — add keywords in Assumptions if needed. This tab is pre-formulated for up to 5,000 rows (through row 5003) — just paste your data starting row 4.
A3: Source File | B3: Statement Period | C3: Transaction Date | D3: Card / Last 4 Digits | E3: Merchant / Description | F3: Amount (AED) | G3: Category (auto)
A4: CC_Statement_Apr2026.pdf | B4: Apr-2026 | C4: 46138 | D4: Visa ***4821 | E4: Meta Platforms - Ad Spend Top-up | F4: 3142.31 | G4: =IFERROR(IF(ISNUMBER(SEARCH(Assumptions!$C$5,E4)),Assumptions!$D$5,IF(ISNUMBER(SEARCH(Assumptions!$C$6,E4)),Assumptions!$D$6,IF(ISNUMBER(SEARCH(Assumptions!$C$7,E4)),Assumptions!$D$7,"Other Services"))),"Other Services") -> Other Services
A5: CC_Statement_Apr2026.pdf | B5: Apr-2026 | C5: 46129 | D5: Visa ***4821 | E5: AWS Cloud Hosting | F5: 762.28 | G5: =IF(E5="","",IFERROR(IF(ISNUMBER(SEARCH(Assumptions!$C$5,E5)),Assumptions!$D$5,IF(ISNUMBER(SEARCH(Assumptions!$C$6,E5)),Assumptions!$D$6,IF(ISNUMBER(SEARCH(Assumptions!$C$7,E5)),Assumptions!$D$7,"Other Services"))),"Other Services")) -> Other Services
A6: CC_Statement_Apr2026.pdf | B6: Apr-2026 | C6: 46129 | D6: Visa ***4821 | E6: Office Supplies - Depot | F6: 1069.63 | G6: =IF(E6="","",IFERROR(IF(ISNUMBER(SEARCH(Assumptions!$C$5,E6)),Assumptions!$D$5,IF(ISNUMBER(SEARCH(Assumptions!$C$6,E6)),Assumptions!$D$6,IF(ISNUMBER(SEARCH(Assumptions!$C$7,E6)),Assumptions!$D$7,"Other Services"))),"Other Services")) -> Other Services
A7: CC_Statement_Apr2026.pdf | B7: Apr-2026 | C7: 46132 | D7: Visa ***4821 | E7: Google Workspace Subscription | F7: 972.89 | G7: =IF(E7="","",IFERROR(IF(ISNUMBER(SEARCH(Assumptions!$C$5,E7)),Assumptions!$D$5,IF(ISNUMBER(SEARCH(Assumptions!$C$6,E7)),Assumptions!$D$6,IF(ISNUMBER(SEARCH(Assumptions!$C$7,E7)),Assumptions!$D$7,"Other Services"))),"Other Services")) -> Subscription
A8: CC_Statement_Apr2026.pdf | B8: Apr-2026 | C8: 46126 | D8: Visa ***4821 | E8: Careem - Business Travel | F8: 1199.6 | G8: =IF(E8="","",IFERROR(IF(ISNUMBER(SEARCH(Assumptions!$C$5,E8)),Assumptions!$D$5,IF(ISNUMBER(SEARCH(Assumptions!$C$6,E8)),Assumptions!$D$6,IF(ISNUMBER(SEARCH(Assumptions!$C$7,E8)),Assumptions!$D$7,"Other Services"))),"Other Services")) -> Other Services
A9: CC_Statement_Apr2026.pdf | B9: Apr-2026 | C9: 46139 | D9: Visa ***4821 | E9: Careem - Business Travel | F9: 448.14 | G9: =IF(E9="","",IFERROR(IF(ISNUMBER(SEARCH(Assumptions!$C$5,E9)),Assumptions!$D$5,IF(ISNUMBER(SEARCH(Assumptions!$C$6,E9)),Assumptions!$D$6,IF(ISNUMBER(SEARCH(Assumptions!$C$7,E9)),Assumptions!$D$7,"Other Services"))),"Other Services")) -> Other Services
A10: CC_Statement_Apr2026.pdf | B10: Apr-2026 | C10: 46122 | D10: Visa ***4821 | E10: Office Supplies - Depot | F10: 158.18 | G10: =IF(E10="","",IFERROR(IF(ISNUMBER(SEARCH(Assumptions!$C$5,E10)),Assumptions!$D$5,IF(ISNUMBER(SEARCH(Assumptions!$C$6,E10)),Assumptions!$D$6,IF(ISNUMBER(SEARCH(Assumptions!$C$7,E10)),Assumptions!$D$7,"Other Services"))),"Other Services")) -> Other Services
A11: CC_Statement_Apr2026.pdf | B11: Apr-2026 | C11: 46115 | D11: Visa ***4821 | E11: Zoom Subscription | F11: 3227.77 | G11: =IF(E11="","",IFERROR(IF(ISNUMBER(SEARCH(Assumptions!$C$5,E11)),Assumptions!$D$5,IF(ISNUMBER(SEARCH(Assumptions!$C$6,E11)),Assumptions!$D$6,IF(ISNUMBER(SEARCH(Assumptions!$C$7,E11)),Assumptions!$D$7,"Other Services"))),"Other Services")) -> Subscription
A12: CC_Statement_Apr2026.pdf | B12: Apr-2026 | C12: 46130 | D12: Visa ***4821 | E12: AWS Cloud Hosting | F12: 1638.18 | G12: =IF(E12="","",IFERROR(IF(ISNUMBER(SEARCH(Assumptions!$C$5,E12)),Assumptions!$D$5,IF(ISNUMBER(SEARCH(Assumptions!$C$6,E12)),Assumptions!$D$6,IF(ISNUMBER(SEARCH(Assumptions!$C$7,E12)),Assumptions!$D$7,"Other Services"))),"Other Services")) -> Other Services
A13: CC_Statement_Apr2026.pdf | B13: Apr-2026 | C13: 46138 | D13: Visa ***4821 | E13: AWS Cloud Hosting | F13: 416.84 | G13: =IF(E13="","",IFERROR(IF(ISNUMBER(SEARCH(Assumptions!$C$5,E13)),Assumptions!$D$5,IF(ISNUMBER(SEARCH(Assumptions!$C$6,E13)),Assumptions!$D$6,IF(ISNUMBER(SEARCH(Assumptions!$C$7,E13)),Assumptions!$D$7,"Other Services"))),"Other Services")) -> Other Services
A14: CC_Statement_May2026.pdf | B14: May-2026 | C14: 46146 | D14: Visa ***4821 | E14: Meta Platforms - Ad Spend Top-up | F14: 2060.51 | G14: =IF(E14="","",IFERROR(IF(ISNUMBER(SEARCH(Assumptions!$C$5,E14)),Assumptions!$D$5,IF(ISNUMBER(SEARCH(Assumptions!$C$6,E14)),Assumptions!$D$6,IF(ISNUMBER(SEARCH(Assumptions!$C$7,E14)),Assumptions!$D$7,"Other Services"))),"Other Services")) -> Other Services
A15: CC_Statement_May2026.pdf | B15: May-2026 | C15: 46167 | D15: Visa ***4821 | E15: WhatsApp Business API - Twilio | F15: 2996.56 | G15: =IF(E15="","",IFERROR(IF(ISNUMBER(SEARCH(Assumptions!$C$5,E15)),Assumptions!$D$5,IF(ISNUMBER(SEARCH(Assumptions!$C$6,E15)),Assumptions!$D$6,IF(ISNUMBER(SEARCH(Assumptions!$C$7,E15)),Assumptions!$D$7,"Other Services"))),"Other Services")) -> WhatsApp
A16: CC_Statement_May2026.pdf | B16: May-2026 | C16: 46164 | D16: Visa ***4821 | E16: Freelancer.com - Development Contractor | F16: 3463.11 | G16: =IF(E16="","",IFERROR(IF(ISNUMBER(SEARCH(Assumptions!$C$5,E16)),Assumptions!$D$5,IF(ISNUMBER(SEARCH(Assumptions!$C$6,E16)),Assumptions!$D$6,IF(ISNUMBER(SEARCH(Assumptions!$C$7,E16)),Assumptions!$D$7,"Other Services"))),"Other Services")) -> Development
... A33: CC_Statement_Jun2026.pdf | B33: Jun-2026 | C33: 46180 | D33: Visa ***4821 | E33: AWS Cloud Hosting | F33: 1144.57 | G33: =IF(E33="","",IFERROR(IF(ISNUMBER(SEARCH(Assumptions!$C$5,E33)),Assumptions!$D$5,IF(ISNUMBER(SEARCH(Assumptions!$C$6,E33)),Assumptions!$D$6,IF(ISNUMBER(SEARCH(Assumptions!$C$7,E33)),Assumptions!$D$7,"Other Services"))),"Other Services")) -> Other Services
G34: =IF(E34="","",IFERROR(IF(ISNUMBER(SEARCH(Assumptions!$C$5,E34)),Assumptions!$D$5,IF(ISNUMBER(SEARCH(Assumptions!$C$6,E34)),Assumptions!$D$6,IF(ISNUMBER(SEARCH(Assumptions!$C$7,E34)),Assumptions!$D$7,"Other Services"))),"Other Services"))
G35: =IF(E35="","",IFERROR(IF(ISNUMBER(SEARCH(Assumptions!$C$5,E35)),Assumptions!$D$5,IF(ISNUMBER(SEARCH(Assumptions!$C$6,E35)),Assumptions!$D$6,IF(ISNUMBER(SEARCH(Assumptions!$C$7,E35)),Assumptions!$D$7,"Other Services"))),"Other Services"))
G36: =IF(E36="","",IFERROR(IF(ISNUMBER(SEARCH(Assumptions!$C$5,E36)),Assumptions!$D$5,IF(ISNUMBER(SEARCH(Assumptions!$C$6,E36)),Assumptions!$D$6,IF(ISNUMBER(SEARCH(Assumptions!$C$7,E36)),Assumptions!$D$7,"Other Services"))),"Other Services"))
G37: =IF(E37="","",IFERROR(IF(ISNUMBER(SEARCH(Assumptions!$C$5,E37)),Assumptions!$D$5,IF(ISNUMBER(SEARCH(Assumptions!$C$6,E37)),Assumptions!$D$6,IF(ISNUMBER(SEARCH(Assumptions!$C$7,E37)),Assumptions!$D$7,"Other Services"))),"Other Services"))
G38: =IF(E38="","",IFERROR(IF(ISNUMBER(SEARCH(Assumptions!$C$5,E38)),Assumptions!$D$5,IF(ISNUMBER(SEARCH(Assumptions!$C$6,E38)),Assumptions!$D$6,IF(ISNUMBER(SEARCH(Assumptions!$C$7,E38)),Assumptions!$D$7,"Other Services"))),"Other Services"))
G39: =IF(E39="","",IFERROR(IF(ISNUMBER(SEARCH(Assumptions!$C$5,E39)),Assumptions!$D$5,IF(ISNUMBER(SEARCH(Assumptions!$C$6,E39)),Assumptions!$D$6,IF(ISNUMBER(SEARCH(Assumptions!$C$7,E39)),Assumptions!$D$7,"Other Services"))),"Other Services"))
G40: =IF(E40="","",IFERROR(IF(ISNUMBER(SEARCH(Assumptions!$C$5,E40)),Assumptions!$D$5,IF(ISNUMBER(SEARCH(Assumptions!$C$6,E40)),Assumptions!$D$6,IF(ISNUMBER(SEARCH(Assumptions!$C$7,E40)),Assumptions!$D$7,"Other Services"))),"Other Services"))
G41: =IF(E41="","",IFERROR(IF(ISNUMBER(SEARCH(Assumptions!$C$5,E41)),Assumptions!$D$5,IF(ISNUMBER(SEARCH(Assumptions!$C$6,E41)),Assumptions!$D$6,IF(ISNUMBER(SEARCH(Assumptions!$C$7,E41)),Assumptions!$D$7,"Other Services"))),"Other Services"))
G42: =IF(E42="","",IFERROR(IF(ISNUMBER(SEARCH(Assumptions!$C$5,E42)),Assumptions!$D$5,IF(ISNUMBER(SEARCH(Assumptions!$C$6,E42)),Assumptions!$D$6,IF(ISNUMBER(SEARCH(Assumptions!$C$7,E42)),Assumptions!$D$7,"Other Services"))),"Other Services"))
G43: =IF(E43="","",IFERROR(IF(ISNUMBER(SEARCH(Assumptions!$C$5,E43)),Assumptions!$D$5,IF(ISNUMBER(SEARCH(Assumptions!$C$6,E43)),Assumptions!$D$6,IF(ISNUMBER(SEARCH(Assumptions!$C$7,E43)),Assumptions!$D$7,"Other Services"))),"Other Services"))
G44: =IF(E44="","",IFERROR(IF(ISNUMBER(SEARCH(Assumptions!$C$5,E44)),Assumptions!$D$5,IF(ISNUMBER(SEARCH(Assumptions!$C$6,E44)),Assumptions!$D$6,IF(ISNUMBER(SEARCH(Assumptions!$C$7,E44)),Assumptions!$D$7,"Other Services"))),"Other Services"))
G45: =IF(E45="","",IFERROR(IF(ISNUMBER(SEARCH(Assumptions!$C$5,E45)),Assumptions!$D$5,IF(ISNUMBER(SEARCH(Assumptions!$C$6,E45)),Assumptions!$D$6,IF(ISNUMBER(SEARCH(Assumptions!$C$7,E45)),Assumptions!$D$7,"Other Services"))),"Other Services"))
... G5003: =IF(E5003="","",IFERROR(IF(ISNUMBER(SEARCH(Assumptions!$C$5,E5003)),Assumptions!$D$5,IF(ISNUMBER(SEARCH(Assumptions!$C$6,E5003)),Assumptions!$D$6,IF(ISNUMBER(SEARCH(Assumptions!$C$7,E5003)),Assumptions!$D$7,"Other Services"))),"Other Services"))

Sheet Customer_Invoices_Upload
A1: CUSTOMER INVOICES (AR) — UPLOAD ZONE
A2: HOW TO USE: Upload customer invoice files (PDF or Word) in the chat and ask Claude to extract them into this tab — one row per invoice. Or paste manually if you already have the data. Country is auto-looked-up from the Assumptions customer→country map (add new customers there if missing). These rows flow into Revenue_Summary and Receivables alongside any Xero invoices, so they are additive, not a duplicate — do not also enter the same invoice in Xero_Raw. This tab is pre-formulated for up to 5,000 rows (through row 5003) — just paste your data starting row 4.
A3: Source File | B3: Invoice Date | C3: Due Date | D3: Invoice No. | E3: Customer | F3: Country (auto) | G3: Description / Line Item | H3: Amount (AED) | I3: Status | J3: Category (auto)
A4: CustInvoice_5002.pdf | B4: 46127 | C4: 46157 | D4: INV-5002 | E4: Misfit Technologies Pte Ltd | F4: =IFERROR(VLOOKUP(E4,Assumptions!$G$5:$H$16,2,0),"Other") -> Singapore | G4: WhatsApp API - Monthly Usage - Apr-2026 | H4: 2862.59 | I4: Awaiting Payment | J4: =IFERROR(IF(ISNUMBER(SEARCH(Assumptions!$C$5,G4)),Assumptions!$D$5,IF(ISNUMBER(SEARCH(Assumptions!$C$6,G4)),Assumptions!$D$6,IF(ISNUMBER(SEARCH(Assumptions!$C$7,G4)),Assumptions!$D$7,"Other Services"))),"Other Services") -> WhatsApp
A5: CustInvoice_5003.pdf | B5: 46118 | C5: 46148 | D5: INV-5003 | E5: Growth X Ventures LLC | F5: =IF(E5="","",IFERROR(VLOOKUP(E5,Assumptions!$G$5:$H$16,2,0),"Other")) -> UAE | G5: WhatsApp API - Monthly Usage - Apr-2026 | H5: 10453.91 | I5: Paid | J5: =IF(G5="","",IFERROR(IF(ISNUMBER(SEARCH(Assumptions!$C$5,G5)),Assumptions!$D$5,IF(ISNUMBER(SEARCH(Assumptions!$C$6,G5)),Assumptions!$D$6,IF(ISNUMBER(SEARCH(Assumptions!$C$7,G5)),Assumptions!$D$7,"Other Services"))),"Other Services")) -> WhatsApp
A6: CustInvoice_5004.pdf | B6: 46118 | C6: 46148 | D6: INV-5004 | E6: Al Fardan Exchange - Sole Proprietorship L.L.C | F6: =IF(E6="","",IFERROR(VLOOKUP(E6,Assumptions!$G$5:$H$16,2,0),"Other")) -> UAE | G6: WhatsApp API - Monthly Usage - Apr-2026 | H6: 10317.27 | I6: Overdue | J6: =IF(G6="","",IFERROR(IF(ISNUMBER(SEARCH(Assumptions!$C$5,G6)),Assumptions!$D$5,IF(ISNUMBER(SEARCH(Assumptions!$C$6,G6)),Assumptions!$D$6,IF(ISNUMBER(SEARCH(Assumptions!$C$7,G6)),Assumptions!$D$7,"Other Services"))),"Other Services")) -> WhatsApp
A7: CustInvoice_5005.pdf | B7: 46132 | C7: 46162 | D7: INV-5005 | E7: Al Fardan Exchange - Sole Proprietorship L.L.C | F7: =IF(E7="","",IFERROR(VLOOKUP(E7,Assumptions!$G$5:$H$16,2,0),"Other")) -> UAE | G7: WhatsApp API - Monthly Usage - Apr-2026 | H7: 11128.21 | I7: Overdue | J7: =IF(G7="","",IFERROR(IF(ISNUMBER(SEARCH(Assumptions!$C$5,G7)),Assumptions!$D$5,IF(ISNUMBER(SEARCH(Assumptions!$C$6,G7)),Assumptions!$D$6,IF(ISNUMBER(SEARCH(Assumptions!$C$7,G7)),Assumptions!$D$7,"Other Services"))),"Other Services")) -> WhatsApp
A8: CustInvoice_5006.pdf | B8: 46117 | C8: 46147 | D8: INV-5006 | E8: Al Fardan Exchange - Sole Proprietorship L.L.C | F8: =IF(E8="","",IFERROR(VLOOKUP(E8,Assumptions!$G$5:$H$16,2,0),"Other")) -> UAE | G8: Subscription - Pro Plan - Apr-2026 | H8: 1679.78 | I8: Paid | J8: =IF(G8="","",IFERROR(IF(ISNUMBER(SEARCH(Assumptions!$C$5,G8)),Assumptions!$D$5,IF(ISNUMBER(SEARCH(Assumptions!$C$6,G8)),Assumptions!$D$6,IF(ISNUMBER(SEARCH(Assumptions!$C$7,G8)),Assumptions!$D$7,"Other Services"))),"Other Services")) -> Subscription
A9: CustInvoice_5007.pdf | B9: 46144 | C9: 46174 | D9: INV-5007 | E9: Growth X Ventures LLC | F9: =IF(E9="","",IFERROR(VLOOKUP(E9,Assumptions!$G$5:$H$16,2,0),"Other")) -> UAE | G9: Subscription - Pro Plan - May-2026 | H9: 13175.39 | I9: Awaiting Payment | J9: =IF(G9="","",IFERROR(IF(ISNUMBER(SEARCH(Assumptions!$C$5,G9)),Assumptions!$D$5,IF(ISNUMBER(SEARCH(Assumptions!$C$6,G9)),Assumptions!$D$6,IF(ISNUMBER(SEARCH(Assumptions!$C$7,G9)),Assumptions!$D$7,"Other Services"))),"Other Services")) -> Subscription
A10: CustInvoice_5008.pdf | B10: 46151 | C10: 46181 | D10: INV-5008 | E10: I Farmer Pte Ltd | F10: =IF(E10="","",IFERROR(VLOOKUP(E10,Assumptions!$G$5:$H$16,2,0),"Other")) -> Singapore | G10: WhatsApp API - Monthly Usage - May-2026 | H10: 11937.43 | I10: Paid | J10: =IF(G10="","",IFERROR(IF(ISNUMBER(SEARCH(Assumptions!$C$5,G10)),Assumptions!$D$5,IF(ISNUMBER(SEARCH(Assumptions!$C$6,G10)),Assumptions!$D$6,IF(ISNUMBER(SEARCH(Assumptions!$C$7,G10)),Assumptions!$D$7,"Other Services"))),"Other Services")) -> WhatsApp
A11: CustInvoice_5009.pdf | B11: 46149 | C11: 46179 | D11: INV-5009 | E11: I Farmer Pte Ltd | F11: =IF(E11="","",IFERROR(VLOOKUP(E11,Assumptions!$G$5:$H$16,2,0),"Other")) -> Singapore | G11: Custom Development - Sprint Invoice - May-2026 | H11: 2815.34 | I11: Paid | J11: =IF(G11="","",IFERROR(IF(ISNUMBER(SEARCH(Assumptions!$C$5,G11)),Assumptions!$D$5,IF(ISNUMBER(SEARCH(Assumptions!$C$6,G11)),Assumptions!$D$6,IF(ISNUMBER(SEARCH(Assumptions!$C$7,G11)),Assumptions!$D$7,"Other Services"))),"Other Services")) -> Development
A12: CustInvoice_5010.pdf | B12: 46147 | C12: 46177 | D12: INV-5010 | E12: Misfit Technologies Pte Ltd | F12: =IF(E12="","",IFERROR(VLOOKUP(E12,Assumptions!$G$5:$H$16,2,0),"Other")) -> Singapore | G12: Custom Development - Sprint Invoice - May-2026 | H12: 21750.95 | I12: Overdue | J12: =IF(G12="","",IFERROR(IF(ISNUMBER(SEARCH(Assumptions!$C$5,G12)),Assumptions!$D$5,IF(ISNUMBER(SEARCH(Assumptions!$C$6,G12)),Assumptions!$D$6,IF(ISNUMBER(SEARCH(Assumptions!$C$7,G12)),Assumptions!$D$7,"Other Services"))),"Other Services")) -> Development
A13: CustInvoice_5011.pdf | B13: 46152 | C13: 46182 | D13: INV-5011 | E13: I Farmer Pte Ltd | F13: =IF(E13="","",IFERROR(VLOOKUP(E13,Assumptions!$G$5:$H$16,2,0),"Other")) -> Singapore | G13: Custom Development - Sprint Invoice - May-2026 | H13: 14640.03 | I13: Awaiting Payment | J13: =IF(G13="","",IFERROR(IF(ISNUMBER(SEARCH(Assumptions!$C$5,G13)),Assumptions!$D$5,IF(ISNUMBER(SEARCH(Assumptions!$C$6,G13)),Assumptions!$D$6,IF(ISNUMBER(SEARCH(Assumptions!$C$7,G13)),Assumptions!$D$7,"Other Services"))),"Other Services")) -> Development
A14: CustInvoice_5012.pdf | B14: 46190 | C14: 46220 | D14: INV-5012 | E14: I Farmer Pte Ltd | F14: =IF(E14="","",IFERROR(VLOOKUP(E14,Assumptions!$G$5:$H$16,2,0),"Other")) -> Singapore | G14: Custom Development - Sprint Invoice - Jun-2026 | H14: 13168.55 | I14: Overdue | J14: =IF(G14="","",IFERROR(IF(ISNUMBER(SEARCH(Assumptions!$C$5,G14)),Assumptions!$D$5,IF(ISNUMBER(SEARCH(Assumptions!$C$6,G14)),Assumptions!$D$6,IF(ISNUMBER(SEARCH(Assumptions!$C$7,G14)),Assumptions!$D$7,"Other Services"))),"Other Services")) -> Development
A15: CustInvoice_5013.pdf | B15: 46178 | C15: 46208 | D15: INV-5013 | E15: Al Fardan Exchange - Sole Proprietorship L.L.C | F15: =IF(E15="","",IFERROR(VLOOKUP(E15,Assumptions!$G$5:$H$16,2,0),"Other")) -> UAE | G15: WhatsApp API - Monthly Usage - Jun-2026 | H15: 2303.99 | I15: Overdue | J15: =IF(G15="","",IFERROR(IF(ISNUMBER(SEARCH(Assumptions!$C$5,G15)),Assumptions!$D$5,IF(ISNUMBER(SEARCH(Assumptions!$C$6,G15)),Assumptions!$D$6,IF(ISNUMBER(SEARCH(Assumptions!$C$7,G15)),Assumptions!$D$7,"Other Services"))),"Other Services")) -> WhatsApp
A16: CustInvoice_5014.pdf | B16: 46192 | C16: 46222 | D16: INV-5014 | E16: Al Fardan Exchange - Sole Proprietorship L.L.C | F16: =IF(E16="","",IFERROR(VLOOKUP(E16,Assumptions!$G$5:$H$16,2,0),"Other")) -> UAE | G16: Custom Development - Sprint Invoice - Jun-2026 | H16: 19304.61 | I16: Paid | J16: =IF(G16="","",IFERROR(IF(ISNUMBER(SEARCH(Assumptions!$C$5,G16)),Assumptions!$D$5,IF(ISNUMBER(SEARCH(Assumptions!$C$6,G16)),Assumptions!$D$6,IF(ISNUMBER(SEARCH(Assumptions!$C$7,G16)),Assumptions!$D$7,"Other Services"))),"Other Services")) -> Development
... A18: CustInvoice_5016.pdf | B18: 46184 | C18: 46214 | D18: INV-5016 | E18: United Homeware Company (Nice) | F18: =IF(E18="","",IFERROR(VLOOKUP(E18,Assumptions!$G$5:$H$16,2,0),"Other")) -> UAE | G18: Subscription - Pro Plan - Jun-2026 | H18: 21404.62 | I18: Paid | J18: =IF(G18="","",IFERROR(IF(ISNUMBER(SEARCH(Assumptions!$C$5,G18)),Assumptions!$D$5,IF(ISNUMBER(SEARCH(Assumptions!$C$6,G18)),Assumptions!$D$6,IF(ISNUMBER(SEARCH(Assumptions!$C$7,G18)),Assumptions!$D$7,"Other Services"))),"Other Services")) -> Subscription
F19: =IF(E19="","",IFERROR(VLOOKUP(E19,Assumptions!$G$5:$H$16,2,0),"Other")) | J19: =IF(G19="","",IFERROR(IF(ISNUMBER(SEARCH(Assumptions!$C$5,G19)),Assumptions!$D$5,IF(ISNUMBER(SEARCH(Assumptions!$C$6,G19)),Assumptions!$D$6,IF(ISNUMBER(SEARCH(Assumptions!$C$7,G19)),Assumptions!$D$7,"Other Services"))),"Other Services"))
F20: =IF(E20="","",IFERROR(VLOOKUP(E20,Assumptions!$G$5:$H$16,2,0),"Other")) | J20: =IF(G20="","",IFERROR(IF(ISNUMBER(SEARCH(Assumptions!$C$5,G20)),Assumptions!$D$5,IF(ISNUMBER(SEARCH(Assumptions!$C$6,G20)),Assumptions!$D$6,IF(ISNUMBER(SEARCH(Assumptions!$C$7,G20)),Assumptions!$D$7,"Other Services"))),"Other Services"))
F21: =IF(E21="","",IFERROR(VLOOKUP(E21,Assumptions!$G$5:$H$16,2,0),"Other")) | J21: =IF(G21="","",IFERROR(IF(ISNUMBER(SEARCH(Assumptions!$C$5,G21)),Assumptions!$D$5,IF(ISNUMBER(SEARCH(Assumptions!$C$6,G21)),Assumptions!$D$6,IF(ISNUMBER(SEARCH(Assumptions!$C$7,G21)),Assumptions!$D$7,"Other Services"))),"Other Services"))
F22: =IF(E22="","",IFERROR(VLOOKUP(E22,Assumptions!$G$5:$H$16,2,0),"Other")) | J22: =IF(G22="","",IFERROR(IF(ISNUMBER(SEARCH(Assumptions!$C$5,G22)),Assumptions!$D$5,IF(ISNUMBER(SEARCH(Assumptions!$C$6,G22)),Assumptions!$D$6,IF(ISNUMBER(SEARCH(Assumptions!$C$7,G22)),Assumptions!$D$7,"Other Services"))),"Other Services"))
F23: =IF(E23="","",IFERROR(VLOOKUP(E23,Assumptions!$G$5:$H$16,2,0),"Other")) | J23: =IF(G23="","",IFERROR(IF(ISNUMBER(SEARCH(Assumptions!$C$5,G23)),Assumptions!$D$5,IF(ISNUMBER(SEARCH(Assumptions!$C$6,G23)),Assumptions!$D$6,IF(ISNUMBER(SEARCH(Assumptions!$C$7,G23)),Assumptions!$D$7,"Other Services"))),"Other Services"))
F24: =IF(E24="","",IFERROR(VLOOKUP(E24,Assumptions!$G$5:$H$16,2,0),"Other")) | J24: =IF(G24="","",IFERROR(IF(ISNUMBER(SEARCH(Assumptions!$C$5,G24)),Assumptions!$D$5,IF(ISNUMBER(SEARCH(Assumptions!$C$6,G24)),Assumptions!$D$6,IF(ISNUMBER(SEARCH(Assumptions!$C$7,G24)),Assumptions!$D$7,"Other Services"))),"Other Services"))
F25: =IF(E25="","",IFERROR(VLOOKUP(E25,Assumptions!$G$5:$H$16,2,0),"Other")) | J25: =IF(G25="","",IFERROR(IF(ISNUMBER(SEARCH(Assumptions!$C$5,G25)),Assumptions!$D$5,IF(ISNUMBER(SEARCH(Assumptions!$C$6,G25)),Assumptions!$D$6,IF(ISNUMBER(SEARCH(Assumptions!$C$7,G25)),Assumptions!$D$7,"Other Services"))),"Other Services"))
F26: =IF(E26="","",IFERROR(VLOOKUP(E26,Assumptions!$G$5:$H$16,2,0),"Other")) | J26: =IF(G26="","",IFERROR(IF(ISNUMBER(SEARCH(Assumptions!$C$5,G26)),Assumptions!$D$5,IF(ISNUMBER(SEARCH(Assumptions!$C$6,G26)),Assumptions!$D$6,IF(ISNUMBER(SEARCH(Assumptions!$C$7,G26)),Assumptions!$D$7,"Other Services"))),"Other Services"))
F27: =IF(E27="","",IFERROR(VLOOKUP(E27,Assumptions!$G$5:$H$16,2,0),"Other")) | J27: =IF(G27="","",IFERROR(IF(ISNUMBER(SEARCH(Assumptions!$C$5,G27)),Assumptions!$D$5,IF(ISNUMBER(SEARCH(Assumptions!$C$6,G27)),Assumptions!$D$6,IF(ISNUMBER(SEARCH(Assumptions!$C$7,G27)),Assumptions!$D$7,"Other Services"))),"Other Services"))
F28: =IF(E28="","",IFERROR(VLOOKUP(E28,Assumptions!$G$5:$H$16,2,0),"Other")) | J28: =IF(G28="","",IFERROR(IF(ISNUMBER(SEARCH(Assumptions!$C$5,G28)),Assumptions!$D$5,IF(ISNUMBER(SEARCH(Assumptions!$C$6,G28)),Assumptions!$D$6,IF(ISNUMBER(SEARCH(Assumptions!$C$7,G28)),Assumptions!$D$7,"Other Services"))),"Other Services"))
F29: =IF(E29="","",IFERROR(VLOOKUP(E29,Assumptions!$G$5:$H$16,2,0),"Other")) | J29: =IF(G29="","",IFERROR(IF(ISNUMBER(SEARCH(Assumptions!$C$5,G29)),Assumptions!$D$5,IF(ISNUMBER(SEARCH(Assumptions!$C$6,G29)),Assumptions!$D$6,IF(ISNUMBER(SEARCH(Assumptions!$C$7,G29)),Assumptions!$D$7,"Other Services"))),"Other Services"))
F30: =IF(E30="","",IFERROR(VLOOKUP(E30,Assumptions!$G$5:$H$16,2,0),"Other")) | J30: =IF(G30="","",IFERROR(IF(ISNUMBER(SEARCH(Assumptions!$C$5,G30)),Assumptions!$D$5,IF(ISNUMBER(SEARCH(Assumptions!$C$6,G30)),Assumptions!$D$6,IF(ISNUMBER(SEARCH(Assumptions!$C$7,G30)),Assumptions!$D$7,"Other Services"))),"Other Services"))
... F5003: =IF(E5003="","",IFERROR(VLOOKUP(E5003,Assumptions!$G$5:$H$16,2,0),"Other")) | J5003: =IF(G5003="","",IFERROR(IF(ISNUMBER(SEARCH(Assumptions!$C$5,G5003)),Assumptions!$D$5,IF(ISNUMBER(SEARCH(Assumptions!$C$6,G5003)),Assumptions!$D$6,IF(ISNUMBER(SEARCH(Assumptions!$C$7,G5003)),Assumptions!$D$7,"Other Services"))),"Other Services"))

Sheet Vendor_Invoices_Upload
A1: VENDOR / SUPPLIER INVOICES (AP) — UPLOAD ZONE
A2: HOW TO USE: Upload vendor bill files (PDF or Word) in the chat and ask Claude to extract them into this tab — one row per bill. Or paste manually. These rows flow into Expense_Summary and the Payables tab alongside any Xero bills, so they are additive — do not also enter the same bill in Xero_Raw. This tab is pre-formulated for up to 5,000 rows (through row 5003) — just paste your data starting row 4.
A3: Source File | B3: Invoice Date | C3: Due Date | D3: Invoice No. | E3: Vendor | F3: Description / Line Item | G3: Amount (AED) | H3: Status | I3: Category (auto)
A4: VendorBill_9002.pdf | B4: 46127 | C4: 46142 | D4: BILL-9002 | E4: Emirates Trade License Authority | F4: Emirates Trade License Authority - Apr-2026 | G4: 3953.18 | H4: Paid | I4: =IFERROR(IF(ISNUMBER(SEARCH(Assumptions!$C$5,F4)),Assumptions!$D$5,IF(ISNUMBER(SEARCH(Assumptions!$C$6,F4)),Assumptions!$D$6,IF(ISNUMBER(SEARCH(Assumptions!$C$7,F4)),Assumptions!$D$7,"Other Services"))),"Other Services") -> Other Services
A5: VendorBill_9003.pdf | B5: 46115 | C5: 46130 | D5: BILL-9003 | E5: Twilio Inc (WhatsApp API) | F5: Twilio Inc (WhatsApp API) - Apr-2026 | G5: 3126.2 | H5: Paid | I5: =IF(F5="","",IFERROR(IF(ISNUMBER(SEARCH(Assumptions!$C$5,F5)),Assumptions!$D$5,IF(ISNUMBER(SEARCH(Assumptions!$C$6,F5)),Assumptions!$D$6,IF(ISNUMBER(SEARCH(Assumptions!$C$7,F5)),Assumptions!$D$7,"Other Services"))),"Other Services")) -> WhatsApp
A6: VendorBill_9004.pdf | B6: 46136 | C6: 46151 | D6: BILL-9004 | E6: Emirates Trade License Authority | F6: Emirates Trade License Authority - Apr-2026 | G6: 3557.08 | H6: Paid | I6: =IF(F6="","",IFERROR(IF(ISNUMBER(SEARCH(Assumptions!$C$5,F6)),Assumptions!$D$5,IF(ISNUMBER(SEARCH(Assumptions!$C$6,F6)),Assumptions!$D$6,IF(ISNUMBER(SEARCH(Assumptions!$C$7,F6)),Assumptions!$D$7,"Other Services"))),"Other Services")) -> Other Services
A7: VendorBill_9005.pdf | B7: 46115 | C7: 46130 | D7: BILL-9005 | E7: Twilio Inc (WhatsApp API) | F7: Twilio Inc (WhatsApp API) - Apr-2026 | G7: 8804.58 | H7: Paid | I7: =IF(F7="","",IFERROR(IF(ISNUMBER(SEARCH(Assumptions!$C$5,F7)),Assumptions!$D$5,IF(ISNUMBER(SEARCH(Assumptions!$C$6,F7)),Assumptions!$D$6,IF(ISNUMBER(SEARCH(Assumptions!$C$7,F7)),Assumptions!$D$7,"Other Services"))),"Other Services")) -> WhatsApp
A8: VendorBill_9006.pdf | B8: 46148 | C8: 46163 | D8: BILL-9006 | E8: Freelance Dev Studio FZE | F8: Freelance Dev Studio FZE - May-2026 | G8: 4441.12 | H8: Awaiting Payment | I8: =IF(F8="","",IFERROR(IF(ISNUMBER(SEARCH(Assumptions!$C$5,F8)),Assumptions!$D$5,IF(ISNUMBER(SEARCH(Assumptions!$C$6,F8)),Assumptions!$D$6,IF(ISNUMBER(SEARCH(Assumptions!$C$7,F8)),Assumptions!$D$7,"Other Services"))),"Other Services")) -> Other Services
A9: VendorBill_9007.pdf | B9: 46165 | C9: 46180 | D9: BILL-9007 | E9: WPP Cloud Hosting LLC | F9: WPP Cloud Hosting LLC - May-2026 | G9: 5529.73 | H9: Paid | I9: =IF(F9="","",IFERROR(IF(ISNUMBER(SEARCH(Assumptions!$C$5,F9)),Assumptions!$D$5,IF(ISNUMBER(SEARCH(Assumptions!$C$6,F9)),Assumptions!$D$6,IF(ISNUMBER(SEARCH(Assumptions!$C$7,F9)),Assumptions!$D$7,"Other Services"))),"Other Services")) -> Other Services
A10: VendorBill_9008.pdf | B10: 46161 | C10: 46176 | D10: BILL-9008 | E10: WPP Cloud Hosting LLC | F10: WPP Cloud Hosting LLC - May-2026 | G10: 4149.25 | H10: Awaiting Payment | I10: =IF(F10="","",IFERROR(IF(ISNUMBER(SEARCH(Assumptions!$C$5,F10)),Assumptions!$D$5,IF(ISNUMBER(SEARCH(Assumptions!$C$6,F10)),Assumptions!$D$6,IF(ISNUMBER(SEARCH(Assumptions!$C$7,F10)),Assumptions!$D$7,"Other Services"))),"Other Services")) -> Other Services
A11: VendorBill_9009.pdf | B11: 46162 | C11: 46177 | D11: BILL-9009 | E11: Freelance Dev Studio FZE | F11: Freelance Dev Studio FZE - May-2026 | G11: 3190.1 | H11: Paid | I11: =IF(F11="","",IFERROR(IF(ISNUMBER(SEARCH(Assumptions!$C$5,F11)),Assumptions!$D$5,IF(ISNUMBER(SEARCH(Assumptions!$C$6,F11)),Assumptions!$D$6,IF(ISNUMBER(SEARCH(Assumptions!$C$7,F11)),Assumptions!$D$7,"Other Services"))),"Other Services")) -> Other Services
A12: VendorBill_9010.pdf | B12: 46175 | C12: 46190 | D12: BILL-9010 | E12: Emirates Trade License Authority | F12: Emirates Trade License Authority - Jun-2026 | G12: 2783.47 | H12: Paid | I12: =IF(F12="","",IFERROR(IF(ISNUMBER(SEARCH(Assumptions!$C$5,F12)),Assumptions!$D$5,IF(ISNUMBER(SEARCH(Assumptions!$C$6,F12)),Assumptions!$D$6,IF(ISNUMBER(SEARCH(Assumptions!$C$7,F12)),Assumptions!$D$7,"Other Services"))),"Other Services")) -> Other Services
A13: VendorBill_9011.pdf | B13: 46177 | C13: 46192 | D13: BILL-9011 | E13: Twilio Inc (WhatsApp API) | F13: Twilio Inc (WhatsApp API) - Jun-2026 | G13: 5469.6 | H13: Paid | I13: =IF(F13="","",IFERROR(IF(ISNUMBER(SEARCH(Assumptions!$C$5,F13)),Assumptions!$D$5,IF(ISNUMBER(SEARCH(Assumptions!$C$6,F13)),Assumptions!$D$6,IF(ISNUMBER(SEARCH(Assumptions!$C$7,F13)),Assumptions!$D$7,"Other Services"))),"Other Services")) -> WhatsApp
A14: VendorBill_9012.pdf | B14: 46196 | C14: 46211 | D14: BILL-9012 | E14: WPP Cloud Hosting LLC | F14: WPP Cloud Hosting LLC - Jun-2026 | G14: 4267.03 | H14: Paid | I14: =IF(F14="","",IFERROR(IF(ISNUMBER(SEARCH(Assumptions!$C$5,F14)),Assumptions!$D$5,IF(ISNUMBER(SEARCH(Assumptions!$C$6,F14)),Assumptions!$D$6,IF(ISNUMBER(SEARCH(Assumptions!$C$7,F14)),Assumptions!$D$7,"Other Services"))),"Other Services")) -> Other Services
A15: VendorBill_9013.pdf | B15: 46181 | C15: 46196 | D15: BILL-9013 | E15: Emirates Trade License Authority | F15: Emirates Trade License Authority - Jun-2026 | G15: 3442.89 | H15: Awaiting Payment | I15: =IF(F15="","",IFERROR(IF(ISNUMBER(SEARCH(Assumptions!$C$5,F15)),Assumptions!$D$5,IF(ISNUMBER(SEARCH(Assumptions!$C$6,F15)),Assumptions!$D$6,IF(ISNUMBER(SEARCH(Assumptions!$C$7,F15)),Assumptions!$D$7,"Other Services"))),"Other Services")) -> Other Services
I16: =IF(F16="","",IFERROR(IF(ISNUMBER(SEARCH(Assumptions!$C$5,F16)),Assumptions!$D$5,IF(ISNUMBER(SEARCH(Assumptions!$C$6,F16)),Assumptions!$D$6,IF(ISNUMBER(SEARCH(Assumptions!$C$7,F16)),Assumptions!$D$7,"Other Services"))),"Other Services"))
I17: =IF(F17="","",IFERROR(IF(ISNUMBER(SEARCH(Assumptions!$C$5,F17)),Assumptions!$D$5,IF(ISNUMBER(SEARCH(Assumptions!$C$6,F17)),Assumptions!$D$6,IF(ISNUMBER(SEARCH(Assumptions!$C$7,F17)),Assumptions!$D$7,"Other Services"))),"Other Services"))
I18: =IF(F18="","",IFERROR(IF(ISNUMBER(SEARCH(Assumptions!$C$5,F18)),Assumptions!$D$5,IF(ISNUMBER(SEARCH(Assumptions!$C$6,F18)),Assumptions!$D$6,IF(ISNUMBER(SEARCH(Assumptions!$C$7,F18)),Assumptions!$D$7,"Other Services"))),"Other Services"))
I19: =IF(F19="","",IFERROR(IF(ISNUMBER(SEARCH(Assumptions!$C$5,F19)),Assumptions!$D$5,IF(ISNUMBER(SEARCH(Assumptions!$C$6,F19)),Assumptions!$D$6,IF(ISNUMBER(SEARCH(Assumptions!$C$7,F19)),Assumptions!$D$7,"Other Services"))),"Other Services"))
I20: =IF(F20="","",IFERROR(IF(ISNUMBER(SEARCH(Assumptions!$C$5,F20)),Assumptions!$D$5,IF(ISNUMBER(SEARCH(Assumptions!$C$6,F20)),Assumptions!$D$6,IF(ISNUMBER(SEARCH(Assumptions!$C$7,F20)),Assumptions!$D$7,"Other Services"))),"Other Services"))
I21: =IF(F21="","",IFERROR(IF(ISNUMBER(SEARCH(Assumptions!$C$5,F21)),Assumptions!$D$5,IF(ISNUMBER(SEARCH(Assumptions!$C$6,F21)),Assumptions!$D$6,IF(ISNUMBER(SEARCH(Assumptions!$C$7,F21)),Assumptions!$D$7,"Other Services"))),"Other Services"))
I22: =IF(F22="","",IFERROR(IF(ISNUMBER(SEARCH(Assumptions!$C$5,F22)),Assumptions!$D$5,IF(ISNUMBER(SEARCH(Assumptions!$C$6,F22)),Assumptions!$D$6,IF(ISNUMBER(SEARCH(Assumptions!$C$7,F22)),Assumptions!$D$7,"Other Services"))),"Other Services"))
I23: =IF(F23="","",IFERROR(IF(ISNUMBER(SEARCH(Assumptions!$C$5,F23)),Assumptions!$D$5,IF(ISNUMBER(SEARCH(Assumptions!$C$6,F23)),Assumptions!$D$6,IF(ISNUMBER(SEARCH(Assumptions!$C$7,F23)),Assumptions!$D$7,"Other Services"))),"Other Services"))
I24: =IF(F24="","",IFERROR(IF(ISNUMBER(SEARCH(Assumptions!$C$5,F24)),Assumptions!$D$5,IF(ISNUMBER(SEARCH(Assumptions!$C$6,F24)),Assumptions!$D$6,IF(ISNUMBER(SEARCH(Assumptions!$C$7,F24)),Assumptions!$D$7,"Other Services"))),"Other Services"))
I25: =IF(F25="","",IFERROR(IF(ISNUMBER(SEARCH(Assumptions!$C$5,F25)),Assumptions!$D$5,IF(ISNUMBER(SEARCH(Assumptions!$C$6,F25)),Assumptions!$D$6,IF(ISNUMBER(SEARCH(Assumptions!$C$7,F25)),Assumptions!$D$7,"Other Services"))),"Other Services"))
I26: =IF(F26="","",IFERROR(IF(ISNUMBER(SEARCH(Assumptions!$C$5,F26)),Assumptions!$D$5,IF(ISNUMBER(SEARCH(Assumptions!$C$6,F26)),Assumptions!$D$6,IF(ISNUMBER(SEARCH(Assumptions!$C$7,F26)),Assumptions!$D$7,"Other Services"))),"Other Services"))
I27: =IF(F27="","",IFERROR(IF(ISNUMBER(SEARCH(Assumptions!$C$5,F27)),Assumptions!$D$5,IF(ISNUMBER(SEARCH(Assumptions!$C$6,F27)),Assumptions!$D$6,IF(ISNUMBER(SEARCH(Assumptions!$C$7,F27)),Assumptions!$D$7,"Other Services"))),"Other Services"))
... I5003: =IF(F5003="","",IFERROR(IF(ISNUMBER(SEARCH(Assumptions!$C$5,F5003)),Assumptions!$D$5,IF(ISNUMBER(SEARCH(Assumptions!$C$6,F5003)),Assumptions!$D$6,IF(ISNUMBER(SEARCH(Assumptions!$C$7,F5003)),Assumptions!$D$7,"Other Services"))),"Other Services"))

Sheet Document_Log
A1: SOURCE DOCUMENT LOG — AUDIT TRAIL
A2: Every time a bank statement, credit card statement, customer invoice, or vendor invoice is uploaded and extracted, log it here. This gives a clear audit trail of what has been processed, by whom, and where the extracted rows landed — useful for reconciliation and audit sign-off.
A3: Date Logged | B3: Source File Name | C3: Document Type | D3: Period Covered | E3: Rows Extracted | F3: Extracted Into Tab | G3: Extracted By | H3: Status / Notes
A4: 46204 | B4: BankStatement_Apr2026.pdf | C4: Bank Statement | D4: Apr-2026 | E4: 20 | F4: Bank_Raw | G4: Claude (AI-assisted) | H4: Sample — replace with real log entries
A5: 46204 | B5: CC_StatementApr2026.pdf | C5: Credit Card | D5: Apr-2026 | E5: 10 | F5: Credit_Card_Upload | G5: Claude (AI-assisted) | H5: Sample
A6: 46204 | B6: CustInvoice_5002.pdf | C6: Customer Invoice | D6: Apr-2026 | E6: 1 | F6: Customer_Invoices_Upload | G6: Claude (AI-assisted) | H6: Sample
A7: 46204 | B7: VendorBill_9002.pdf | C7: Vendor Invoice | D7: Apr-2026 | E7: 1 | F7: Vendor_Invoices_Upload | G7: Claude (AI-assisted) | H7: Sample

Sheet Payables
A1: ACCOUNTS PAYABLE — AGING BY VENDOR (Vendor Invoice Uploads + Xero Bills)
A2: Outstanding = Vendor_Invoices_Upload rows with Status ≠ Paid, plus Xero_Raw Bills with Status ≠ Paid. As-of date drives aging buckets.
B4: As-of Date: | C4: =DATE(2026,6,30) -> 46203
A6: OUTSTANDING VENDOR INVOICE DETAIL — Vendor_Invoices_Upload (Illustrative sample rows shown — summary totals below reflect the full uploaded range, up to 5,000 rows.)
A7: Invoice Date | B7: Due Date | C7: Vendor | D7: Amount (AED) | E7: Status | F7: Days Overdue | G7: Aging Bucket
A8: =IF(Vendor_Invoices_Upload!$H$4<>"Paid",Vendor_Invoices_Upload!$B$4,"") | B8: =IF(Vendor_Invoices_Upload!$H$4<>"Paid",Vendor_Invoices_Upload!$C$4,"") | C8: =IF(Vendor_Invoices_Upload!$H$4<>"Paid",Vendor_Invoices_Upload!$E$4,"") | D8: =IF(Vendor_Invoices_Upload!$H$4<>"Paid",Vendor_Invoices_Upload!$G$4,"") | E8: =IF(Vendor_Invoices_Upload!$H$4<>"Paid",Vendor_Invoices_Upload!$H$4,"") | F8: =IF(B8="","",MAX($C$4-B8,0)) | G8: =IF(F8="","",IF(F8<=30,"0-30",IF(F8<=60,"31-60",IF(F8<=90,"61-90","90+"))))
A9: =IF(Vendor_Invoices_Upload!$H$5<>"Paid",Vendor_Invoices_Upload!$B$5,"") | B9: =IF(Vendor_Invoices_Upload!$H$5<>"Paid",Vendor_Invoices_Upload!$C$5,"") | C9: =IF(Vendor_Invoices_Upload!$H$5<>"Paid",Vendor_Invoices_Upload!$E$5,"") | D9: =IF(Vendor_Invoices_Upload!$H$5<>"Paid",Vendor_Invoices_Upload!$G$5,"") | E9: =IF(Vendor_Invoices_Upload!$H$5<>"Paid",Vendor_Invoices_Upload!$H$5,"") | F9: =IF(B9="","",MAX($C$4-B9,0)) | G9: =IF(F9="","",IF(F9<=30,"0-30",IF(F9<=60,"31-60",IF(F9<=90,"61-90","90+"))))
A10: =IF(Vendor_Invoices_Upload!$H$6<>"Paid",Vendor_Invoices_Upload!$B$6,"") | B10: =IF(Vendor_Invoices_Upload!$H$6<>"Paid",Vendor_Invoices_Upload!$C$6,"") | C10: =IF(Vendor_Invoices_Upload!$H$6<>"Paid",Vendor_Invoices_Upload!$E$6,"") | D10: =IF(Vendor_Invoices_Upload!$H$6<>"Paid",Vendor_Invoices_Upload!$G$6,"") | E10: =IF(Vendor_Invoices_Upload!$H$6<>"Paid",Vendor_Invoices_Upload!$H$6,"") | F10: =IF(B10="","",MAX($C$4-B10,0)) | G10: =IF(F10="","",IF(F10<=30,"0-30",IF(F10<=60,"31-60",IF(F10<=90,"61-90","90+"))))
A11: =IF(Vendor_Invoices_Upload!$H$7<>"Paid",Vendor_Invoices_Upload!$B$7,"") | B11: =IF(Vendor_Invoices_Upload!$H$7<>"Paid",Vendor_Invoices_Upload!$C$7,"") | C11: =IF(Vendor_Invoices_Upload!$H$7<>"Paid",Vendor_Invoices_Upload!$E$7,"") | D11: =IF(Vendor_Invoices_Upload!$H$7<>"Paid",Vendor_Invoices_Upload!$G$7,"") | E11: =IF(Vendor_Invoices_Upload!$H$7<>"Paid",Vendor_Invoices_Upload!$H$7,"") | F11: =IF(B11="","",MAX($C$4-B11,0)) | G11: =IF(F11="","",IF(F11<=30,"0-30",IF(F11<=60,"31-60",IF(F11<=90,"61-90","90+"))))
A12: =IF(Vendor_Invoices_Upload!$H$8<>"Paid",Vendor_Invoices_Upload!$B$8,"") -> 46148 | B12: =IF(Vendor_Invoices_Upload!$H$8<>"Paid",Vendor_Invoices_Upload!$C$8,"") -> 46163 | C12: =IF(Vendor_Invoices_Upload!$H$8<>"Paid",Vendor_Invoices_Upload!$E$8,"") -> Freelance Dev Studio FZE | D12: =IF(Vendor_Invoices_Upload!$H$8<>"Paid",Vendor_Invoices_Upload!$G$8,"") -> 4441.12 | E12: =IF(Vendor_Invoices_Upload!$H$8<>"Paid",Vendor_Invoices_Upload!$H$8,"") -> Awaiting Payment | F12: =IF(B12="","",MAX($C$4-B12,0)) -> 40 | G12: =IF(F12="","",IF(F12<=30,"0-30",IF(F12<=60,"31-60",IF(F12<=90,"61-90","90+")))) -> 31-60
A13: =IF(Vendor_Invoices_Upload!$H$9<>"Paid",Vendor_Invoices_Upload!$B$9,"") | B13: =IF(Vendor_Invoices_Upload!$H$9<>"Paid",Vendor_Invoices_Upload!$C$9,"") | C13: =IF(Vendor_Invoices_Upload!$H$9<>"Paid",Vendor_Invoices_Upload!$E$9,"") | D13: =IF(Vendor_Invoices_Upload!$H$9<>"Paid",Vendor_Invoices_Upload!$G$9,"") | E13: =IF(Vendor_Invoices_Upload!$H$9<>"Paid",Vendor_Invoices_Upload!$H$9,"") | F13: =IF(B13="","",MAX($C$4-B13,0)) | G13: =IF(F13="","",IF(F13<=30,"0-30",IF(F13<=60,"31-60",IF(F13<=90,"61-90","90+"))))
A14: =IF(Vendor_Invoices_Upload!$H$10<>"Paid",Vendor_Invoices_Upload!$B$10,"") -> 46161 | B14: =IF(Vendor_Invoices_Upload!$H$10<>"Paid",Vendor_Invoices_Upload!$C$10,"") -> 46176 | C14: =IF(Vendor_Invoices_Upload!$H$10<>"Paid",Vendor_Invoices_Upload!$E$10,"") -> WPP Cloud Hosting LLC | D14: =IF(Vendor_Invoices_Upload!$H$10<>"Paid",Vendor_Invoices_Upload!$G$10,"") -> 4149.25 | E14: =IF(Vendor_Invoices_Upload!$H$10<>"Paid",Vendor_Invoices_Upload!$H$10,"") -> Awaiting Payment | F14: =IF(B14="","",MAX($C$4-B14,0)) -> 27 | G14: =IF(F14="","",IF(F14<=30,"0-30",IF(F14<=60,"31-60",IF(F14<=90,"61-90","90+")))) -> 0-30
A15: =IF(Vendor_Invoices_Upload!$H$11<>"Paid",Vendor_Invoices_Upload!$B$11,"") | B15: =IF(Vendor_Invoices_Upload!$H$11<>"Paid",Vendor_Invoices_Upload!$C$11,"") | C15: =IF(Vendor_Invoices_Upload!$H$11<>"Paid",Vendor_Invoices_Upload!$E$11,"") | D15: =IF(Vendor_Invoices_Upload!$H$11<>"Paid",Vendor_Invoices_Upload!$G$11,"") | E15: =IF(Vendor_Invoices_Upload!$H$11<>"Paid",Vendor_Invoices_Upload!$H$11,"") | F15: =IF(B15="","",MAX($C$4-B15,0)) | G15: =IF(F15="","",IF(F15<=30,"0-30",IF(F15<=60,"31-60",IF(F15<=90,"61-90","90+"))))
A16: =IF(Vendor_Invoices_Upload!$H$12<>"Paid",Vendor_Invoices_Upload!$B$12,"") | B16: =IF(Vendor_Invoices_Upload!$H$12<>"Paid",Vendor_Invoices_Upload!$C$12,"") | C16: =IF(Vendor_Invoices_Upload!$H$12<>"Paid",Vendor_Invoices_Upload!$E$12,"") | D16: =IF(Vendor_Invoices_Upload!$H$12<>"Paid",Vendor_Invoices_Upload!$G$12,"") | E16: =IF(Vendor_Invoices_Upload!$H$12<>"Paid",Vendor_Invoices_Upload!$H$12,"") | F16: =IF(B16="","",MAX($C$4-B16,0)) | G16: =IF(F16="","",IF(F16<=30,"0-30",IF(F16<=60,"31-60",IF(F16<=90,"61-90","90+"))))
A17: =IF(Vendor_Invoices_Upload!$H$13<>"Paid",Vendor_Invoices_Upload!$B$13,"") | B17: =IF(Vendor_Invoices_Upload!$H$13<>"Paid",Vendor_Invoices_Upload!$C$13,"") | C17: =IF(Vendor_Invoices_Upload!$H$13<>"Paid",Vendor_Invoices_Upload!$E$13,"") | D17: =IF(Vendor_Invoices_Upload!$H$13<>"Paid",Vendor_Invoices_Upload!$G$13,"") | E17: =IF(Vendor_Invoices_Upload!$H$13<>"Paid",Vendor_Invoices_Upload!$H$13,"") | F17: =IF(B17="","",MAX($C$4-B17,0)) | G17: =IF(F17="","",IF(F17<=30,"0-30",IF(F17<=60,"31-60",IF(F17<=90,"61-90","90+"))))
A18: =IF(Vendor_Invoices_Upload!$H$14<>"Paid",Vendor_Invoices_Upload!$B$14,"") | B18: =IF(Vendor_Invoices_Upload!$H$14<>"Paid",Vendor_Invoices_Upload!$C$14,"") | C18: =IF(Vendor_Invoices_Upload!$H$14<>"Paid",Vendor_Invoices_Upload!$E$14,"") | D18: =IF(Vendor_Invoices_Upload!$H$14<>"Paid",Vendor_Invoices_Upload!$G$14,"") | E18: =IF(Vendor_Invoices_Upload!$H$14<>"Paid",Vendor_Invoices_Upload!$H$14,"") | F18: =IF(B18="","",MAX($C$4-B18,0)) | G18: =IF(F18="","",IF(F18<=30,"0-30",IF(F18<=60,"31-60",IF(F18<=90,"61-90","90+"))))
A19: =IF(Vendor_Invoices_Upload!$H$15<>"Paid",Vendor_Invoices_Upload!$B$15,"") -> 46181 | B19: =IF(Vendor_Invoices_Upload!$H$15<>"Paid",Vendor_Invoices_Upload!$C$15,"") -> 46196 | C19: =IF(Vendor_Invoices_Upload!$H$15<>"Paid",Vendor_Invoices_Upload!$E$15,"") -> Emirates Trade License Authority | D19: =IF(Vendor_Invoices_Upload!$H$15<>"Paid",Vendor_Invoices_Upload!$G$15,"") -> 3442.89 | E19: =IF(Vendor_Invoices_Upload!$H$15<>"Paid",Vendor_Invoices_Upload!$H$15,"") -> Awaiting Payment | F19: =IF(B19="","",MAX($C$4-B19,0)) -> 7 | G19: =IF(F19="","",IF(F19<=30,"0-30",IF(F19<=60,"31-60",IF(F19<=90,"61-90","90+")))) -> 0-30
A21: OUTSTANDING XERO BILLS DETAIL — Xero_Raw (Illustrative sample rows shown — summary totals reflect the full uploaded range.)
A22: Invoice Date | B22: Due Date | C22: Vendor | D22: Amount (AED) | E22: Status | F22: Days Overdue | G22: Aging Bucket
A23: =IF(AND(Xero_Raw!$C$4="Bill",Xero_Raw!$I$4<>"Paid"),Xero_Raw!$A$4,"") | B23: =IF(AND(Xero_Raw!$C$4="Bill",Xero_Raw!$I$4<>"Paid"),Xero_Raw!$A$4+15,"") | C23: =IF(AND(Xero_Raw!$C$4="Bill",Xero_Raw!$I$4<>"Paid"),Xero_Raw!$D$4,"") | D23: =IF(AND(Xero_Raw!$C$4="Bill",Xero_Raw!$I$4<>"Paid"),Xero_Raw!$H$4,"") | E23: =IF(AND(Xero_Raw!$C$4="Bill",Xero_Raw!$I$4<>"Paid"),Xero_Raw!$I$4,"") | F23: =IF(B23="","",MAX($C$4-B23,0)) | G23: =IF(F23="","",IF(F23<=30,"0-30",IF(F23<=60,"31-60",IF(F23<=90,"61-90","90+"))))
A24: =IF(AND(Xero_Raw!$C$5="Bill",Xero_Raw!$I$5<>"Paid"),Xero_Raw!$A$5,"") | B24: =IF(AND(Xero_Raw!$C$5="Bill",Xero_Raw!$I$5<>"Paid"),Xero_Raw!$A$5+15,"") | C24: =IF(AND(Xero_Raw!$C$5="Bill",Xero_Raw!$I$5<>"Paid"),Xero_Raw!$D$5,"") | D24: =IF(AND(Xero_Raw!$C$5="Bill",Xero_Raw!$I$5<>"Paid"),Xero_Raw!$H$5,"") | E24: =IF(AND(Xero_Raw!$C$5="Bill",Xero_Raw!$I$5<>"Paid"),Xero_Raw!$I$5,"") | F24: =IF(B24="","",MAX($C$4-B24,0)) | G24: =IF(F24="","",IF(F24<=30,"0-30",IF(F24<=60,"31-60",IF(F24<=90,"61-90","90+"))))
A25: =IF(AND(Xero_Raw!$C$6="Bill",Xero_Raw!$I$6<>"Paid"),Xero_Raw!$A$6,"") | B25: =IF(AND(Xero_Raw!$C$6="Bill",Xero_Raw!$I$6<>"Paid"),Xero_Raw!$A$6+15,"") | C25: =IF(AND(Xero_Raw!$C$6="Bill",Xero_Raw!$I$6<>"Paid"),Xero_Raw!$D$6,"") | D25: =IF(AND(Xero_Raw!$C$6="Bill",Xero_Raw!$I$6<>"Paid"),Xero_Raw!$H$6,"") | E25: =IF(AND(Xero_Raw!$C$6="Bill",Xero_Raw!$I$6<>"Paid"),Xero_Raw!$I$6,"") | F25: =IF(B25="","",MAX($C$4-B25,0)) | G25: =IF(F25="","",IF(F25<=30,"0-30",IF(F25<=60,"31-60",IF(F25<=90,"61-90","90+"))))
A26: =IF(AND(Xero_Raw!$C$7="Bill",Xero_Raw!$I$7<>"Paid"),Xero_Raw!$A$7,"") | B26: =IF(AND(Xero_Raw!$C$7="Bill",Xero_Raw!$I$7<>"Paid"),Xero_Raw!$A$7+15,"") | C26: =IF(AND(Xero_Raw!$C$7="Bill",Xero_Raw!$I$7<>"Paid"),Xero_Raw!$D$7,"") | D26: =IF(AND(Xero_Raw!$C$7="Bill",Xero_Raw!$I$7<>"Paid"),Xero_Raw!$H$7,"") | E26: =IF(AND(Xero_Raw!$C$7="Bill",Xero_Raw!$I$7<>"Paid"),Xero_Raw!$I$7,"") | F26: =IF(B26="","",MAX($C$4-B26,0)) | G26: =IF(F26="","",IF(F26<=30,"0-30",IF(F26<=60,"31-60",IF(F26<=90,"61-90","90+"))))
A27: =IF(AND(Xero_Raw!$C$8="Bill",Xero_Raw!$I$8<>"Paid"),Xero_Raw!$A$8,"") | B27: =IF(AND(Xero_Raw!$C$8="Bill",Xero_Raw!$I$8<>"Paid"),Xero_Raw!$A$8+15,"") | C27: =IF(AND(Xero_Raw!$C$8="Bill",Xero_Raw!$I$8<>"Paid"),Xero_Raw!$D$8,"") | D27: =IF(AND(Xero_Raw!$C$8="Bill",Xero_Raw!$I$8<>"Paid"),Xero_Raw!$H$8,"") | E27: =IF(AND(Xero_Raw!$C$8="Bill",Xero_Raw!$I$8<>"Paid"),Xero_Raw!$I$8,"") | F27: =IF(B27="","",MAX($C$4-B27,0)) | G27: =IF(F27="","",IF(F27<=30,"0-30",IF(F27<=60,"31-60",IF(F27<=90,"61-90","90+"))))
A28: =IF(AND(Xero_Raw!$C$9="Bill",Xero_Raw!$I$9<>"Paid"),Xero_Raw!$A$9,"") | B28: =IF(AND(Xero_Raw!$C$9="Bill",Xero_Raw!$I$9<>"Paid"),Xero_Raw!$A$9+15,"") | C28: =IF(AND(Xero_Raw!$C$9="Bill",Xero_Raw!$I$9<>"Paid"),Xero_Raw!$D$9,"") | D28: =IF(AND(Xero_Raw!$C$9="Bill",Xero_Raw!$I$9<>"Paid"),Xero_Raw!$H$9,"") | E28: =IF(AND(Xero_Raw!$C$9="Bill",Xero_Raw!$I$9<>"Paid"),Xero_Raw!$I$9,"") | F28: =IF(B28="","",MAX($C$4-B28,0)) | G28: =IF(F28="","",IF(F28<=30,"0-30",IF(F28<=60,"31-60",IF(F28<=90,"61-90","90+"))))
A29: =IF(AND(Xero_Raw!$C$10="Bill",Xero_Raw!$I$10<>"Paid"),Xero_Raw!$A$10,"") | B29: =IF(AND(Xero_Raw!$C$10="Bill",Xero_Raw!$I$10<>"Paid"),Xero_Raw!$A$10+15,"") | C29: =IF(AND(Xero_Raw!$C$10="Bill",Xero_Raw!$I$10<>"Paid"),Xero_Raw!$D$10,"") | D29: =IF(AND(Xero_Raw!$C$10="Bill",Xero_Raw!$I$10<>"Paid"),Xero_Raw!$H$10,"") | E29: =IF(AND(Xero_Raw!$C$10="Bill",Xero_Raw!$I$10<>"Paid"),Xero_Raw!$I$10,"") | F29: =IF(B29="","",MAX($C$4-B29,0)) | G29: =IF(F29="","",IF(F29<=30,"0-30",IF(F29<=60,"31-60",IF(F29<=90,"61-90","90+"))))
A30: =IF(AND(Xero_Raw!$C$11="Bill",Xero_Raw!$I$11<>"Paid"),Xero_Raw!$A$11,"") | B30: =IF(AND(Xero_Raw!$C$11="Bill",Xero_Raw!$I$11<>"Paid"),Xero_Raw!$A$11+15,"") | C30: =IF(AND(Xero_Raw!$C$11="Bill",Xero_Raw!$I$11<>"Paid"),Xero_Raw!$D$11,"") | D30: =IF(AND(Xero_Raw!$C$11="Bill",Xero_Raw!$I$11<>"Paid"),Xero_Raw!$H$11,"") | E30: =IF(AND(Xero_Raw!$C$11="Bill",Xero_Raw!$I$11<>"Paid"),Xero_Raw!$I$11,"") | F30: =IF(B30="","",MAX($C$4-B30,0)) | G30: =IF(F30="","",IF(F30<=30,"0-30",IF(F30<=60,"31-60",IF(F30<=90,"61-90","90+"))))
A31: =IF(AND(Xero_Raw!$C$12="Bill",Xero_Raw!$I$12<>"Paid"),Xero_Raw!$A$12,"") | B31: =IF(AND(Xero_Raw!$C$12="Bill",Xero_Raw!$I$12<>"Paid"),Xero_Raw!$A$12+15,"") | C31: =IF(AND(Xero_Raw!$C$12="Bill",Xero_Raw!$I$12<>"Paid"),Xero_Raw!$D$12,"") | D31: =IF(AND(Xero_Raw!$C$12="Bill",Xero_Raw!$I$12<>"Paid"),Xero_Raw!$H$12,"") | E31: =IF(AND(Xero_Raw!$C$12="Bill",Xero_Raw!$I$12<>"Paid"),Xero_Raw!$I$12,"") | F31: =IF(B31="","",MAX($C$4-B31,0)) | G31: =IF(F31="","",IF(F31<=30,"0-30",IF(F31<=60,"31-60",IF(F31<=90,"61-90","90+"))))
A32: =IF(AND(Xero_Raw!$C$13="Bill",Xero_Raw!$I$13<>"Paid"),Xero_Raw!$A$13,"") | B32: =IF(AND(Xero_Raw!$C$13="Bill",Xero_Raw!$I$13<>"Paid"),Xero_Raw!$A$13+15,"") | C32: =IF(AND(Xero_Raw!$C$13="Bill",Xero_Raw!$I$13<>"Paid"),Xero_Raw!$D$13,"") | D32: =IF(AND(Xero_Raw!$C$13="Bill",Xero_Raw!$I$13<>"Paid"),Xero_Raw!$H$13,"") | E32: =IF(AND(Xero_Raw!$C$13="Bill",Xero_Raw!$I$13<>"Paid"),Xero_Raw!$I$13,"") | F32: =IF(B32="","",MAX($C$4-B32,0)) | G32: =IF(F32="","",IF(F32<=30,"0-30",IF(F32<=60,"31-60",IF(F32<=90,"61-90","90+"))))
A33: =IF(AND(Xero_Raw!$C$14="Bill",Xero_Raw!$I$14<>"Paid"),Xero_Raw!$A$14,"") | B33: =IF(AND(Xero_Raw!$C$14="Bill",Xero_Raw!$I$14<>"Paid"),Xero_Raw!$A$14+15,"") | C33: =IF(AND(Xero_Raw!$C$14="Bill",Xero_Raw!$I$14<>"Paid"),Xero_Raw!$D$14,"") | D33: =IF(AND(Xero_Raw!$C$14="Bill",Xero_Raw!$I$14<>"Paid"),Xero_Raw!$H$14,"") | E33: =IF(AND(Xero_Raw!$C$14="Bill",Xero_Raw!$I$14<>"Paid"),Xero_Raw!$I$14,"") | F33: =IF(B33="","",MAX($C$4-B33,0)) | G33: =IF(F33="","",IF(F33<=30,"0-30",IF(F33<=60,"31-60",IF(F33<=90,"61-90","90+"))))
A34: =IF(AND(Xero_Raw!$C$15="Bill",Xero_Raw!$I$15<>"Paid"),Xero_Raw!$A$15,"") | B34: =IF(AND(Xero_Raw!$C$15="Bill",Xero_Raw!$I$15<>"Paid"),Xero_Raw!$A$15+15,"") | C34: =IF(AND(Xero_Raw!$C$15="Bill",Xero_Raw!$I$15<>"Paid"),Xero_Raw!$D$15,"") | D34: =IF(AND(Xero_Raw!$C$15="Bill",Xero_Raw!$I$15<>"Paid"),Xero_Raw!$H$15,"") | E34: =IF(AND(Xero_Raw!$C$15="Bill",Xero_Raw!$I$15<>"Paid"),Xero_Raw!$I$15,"") | F34: =IF(B34="","",MAX($C$4-B34,0)) | G34: =IF(F34="","",IF(F34<=30,"0-30",IF(F34<=60,"31-60",IF(F34<=90,"61-90","90+"))))
A35: =IF(AND(Xero_Raw!$C$16="Bill",Xero_Raw!$I$16<>"Paid"),Xero_Raw!$A$16,"") | B35: =IF(AND(Xero_Raw!$C$16="Bill",Xero_Raw!$I$16<>"Paid"),Xero_Raw!$A$16+15,"") | C35: =IF(AND(Xero_Raw!$C$16="Bill",Xero_Raw!$I$16<>"Paid"),Xero_Raw!$D$16,"") | D35: =IF(AND(Xero_Raw!$C$16="Bill",Xero_Raw!$I$16<>"Paid"),Xero_Raw!$H$16,"") | E35: =IF(AND(Xero_Raw!$C$16="Bill",Xero_Raw!$I$16<>"Paid"),Xero_Raw!$I$16,"") | F35: =IF(B35="","",MAX($C$4-B35,0)) | G35: =IF(F35="","",IF(F35<=30,"0-30",IF(F35<=60,"31-60",IF(F35<=90,"61-90","90+"))))
A36: =IF(AND(Xero_Raw!$C$17="Bill",Xero_Raw!$I$17<>"Paid"),Xero_Raw!$A$17,"") | B36: =IF(AND(Xero_Raw!$C$17="Bill",Xero_Raw!$I$17<>"Paid"),Xero_Raw!$A$17+15,"") | C36: =IF(AND(Xero_Raw!$C$17="Bill",Xero_Raw!$I$17<>"Paid"),Xero_Raw!$D$17,"") | D36: =IF(AND(Xero_Raw!$C$17="Bill",Xero_Raw!$I$17<>"Paid"),Xero_Raw!$H$17,"") | E36: =IF(AND(Xero_Raw!$C$17="Bill",Xero_Raw!$I$17<>"Paid"),Xero_Raw!$I$17,"") | F36: =IF(B36="","",MAX($C$4-B36,0)) | G36: =IF(F36="","",IF(F36<=30,"0-30",IF(F36<=60,"31-60",IF(F36<=90,"61-90","90+"))))
A37: =IF(AND(Xero_Raw!$C$18="Bill",Xero_Raw!$I$18<>"Paid"),Xero_Raw!$A$18,"") | B37: =IF(AND(Xero_Raw!$C$18="Bill",Xero_Raw!$I$18<>"Paid"),Xero_Raw!$A$18+15,"") | C37: =IF(AND(Xero_Raw!$C$18="Bill",Xero_Raw!$I$18<>"Paid"),Xero_Raw!$D$18,"") | D37: =IF(AND(Xero_Raw!$C$18="Bill",Xero_Raw!$I$18<>"Paid"),Xero_Raw!$H$18,"") | E37: =IF(AND(Xero_Raw!$C$18="Bill",Xero_Raw!$I$18<>"Paid"),Xero_Raw!$I$18,"") | F37: =IF(B37="","",MAX($C$4-B37,0)) | G37: =IF(F37="","",IF(F37<=30,"0-30",IF(F37<=60,"31-60",IF(F37<=90,"61-90","90+"))))
A38: =IF(AND(Xero_Raw!$C$19="Bill",Xero_Raw!$I$19<>"Paid"),Xero_Raw!$A$19,"") | B38: =IF(AND(Xero_Raw!$C$19="Bill",Xero_Raw!$I$19<>"Paid"),Xero_Raw!$A$19+15,"") | C38: =IF(AND(Xero_Raw!$C$19="Bill",Xero_Raw!$I$19<>"Paid"),Xero_Raw!$D$19,"") | D38: =IF(AND(Xero_Raw!$C$19="Bill",Xero_Raw!$I$19<>"Paid"),Xero_Raw!$H$19,"") | E38: =IF(AND(Xero_Raw!$C$19="Bill",Xero_Raw!$I$19<>"Paid"),Xero_Raw!$I$19,"") | F38: =IF(B38="","",MAX($C$4-B38,0)) | G38: =IF(F38="","",IF(F38<=30,"0-30",IF(F38<=60,"31-60",IF(F38<=90,"61-90","90+"))))
A39: =IF(AND(Xero_Raw!$C$20="Bill",Xero_Raw!$I$20<>"Paid"),Xero_Raw!$A$20,"") | B39: =IF(AND(Xero_Raw!$C$20="Bill",Xero_Raw!$I$20<>"Paid"),Xero_Raw!$A$20+15,"") | C39: =IF(AND(Xero_Raw!$C$20="Bill",Xero_Raw!$I$20<>"Paid"),Xero_Raw!$D$20,"") | D39: =IF(AND(Xero_Raw!$C$20="Bill",Xero_Raw!$I$20<>"Paid"),Xero_Raw!$H$20,"") | E39: =IF(AND(Xero_Raw!$C$20="Bill",Xero_Raw!$I$20<>"Paid"),Xero_Raw!$I$20,"") | F39: =IF(B39="","",MAX($C$4-B39,0)) | G39: =IF(F39="","",IF(F39<=30,"0-30",IF(F39<=60,"31-60",IF(F39<=90,"61-90","90+"))))
A40: =IF(AND(Xero_Raw!$C$21="Bill",Xero_Raw!$I$21<>"Paid"),Xero_Raw!$A$21,"") | B40: =IF(AND(Xero_Raw!$C$21="Bill",Xero_Raw!$I$21<>"Paid"),Xero_Raw!$A$21+15,"") | C40: =IF(AND(Xero_Raw!$C$21="Bill",Xero_Raw!$I$21<>"Paid"),Xero_Raw!$D$21,"") | D40: =IF(AND(Xero_Raw!$C$21="Bill",Xero_Raw!$I$21<>"Paid"),Xero_Raw!$H$21,"") | E40: =IF(AND(Xero_Raw!$C$21="Bill",Xero_Raw!$I$21<>"Paid"),Xero_Raw!$I$21,"") | F40: =IF(B40="","",MAX($C$4-B40,0)) | G40: =IF(F40="","",IF(F40<=30,"0-30",IF(F40<=60,"31-60",IF(F40<=90,"61-90","90+"))))
A41: =IF(AND(Xero_Raw!$C$22="Bill",Xero_Raw!$I$22<>"Paid"),Xero_Raw!$A$22,"") | B41: =IF(AND(Xero_Raw!$C$22="Bill",Xero_Raw!$I$22<>"Paid"),Xero_Raw!$A$22+15,"") | C41: =IF(AND(Xero_Raw!$C$22="Bill",Xero_Raw!$I$22<>"Paid"),Xero_Raw!$D$22,"") | D41: =IF(AND(Xero_Raw!$C$22="Bill",Xero_Raw!$I$22<>"Paid"),Xero_Raw!$H$22,"") | E41: =IF(AND(Xero_Raw!$C$22="Bill",Xero_Raw!$I$22<>"Paid"),Xero_Raw!$I$22,"") | F41: =IF(B41="","",MAX($C$4-B41,0)) | G41: =IF(F41="","",IF(F41<=30,"0-30",IF(F41<=60,"31-60",IF(F41<=90,"61-90","90+"))))
A42: =IF(AND(Xero_Raw!$C$23="Bill",Xero_Raw!$I$23<>"Paid"),Xero_Raw!$A$23,"") | B42: =IF(AND(Xero_Raw!$C$23="Bill",Xero_Raw!$I$23<>"Paid"),Xero_Raw!$A$23+15,"") | C42: =IF(AND(Xero_Raw!$C$23="Bill",Xero_Raw!$I$23<>"Paid"),Xero_Raw!$D$23,"") | D42: =IF(AND(Xero_Raw!$C$23="Bill",Xero_Raw!$I$23<>"Paid"),Xero_Raw!$H$23,"") | E42: =IF(AND(Xero_Raw!$C$23="Bill",Xero_Raw!$I$23<>"Paid"),Xero_Raw!$I$23,"") | F42: =IF(B42="","",MAX($C$4-B42,0)) | G42: =IF(F42="","",IF(F42<=30,"0-30",IF(F42<=60,"31-60",IF(F42<=90,"61-90","90+"))))
A43: =IF(AND(Xero_Raw!$C$24="Bill",Xero_Raw!$I$24<>"Paid"),Xero_Raw!$A$24,"") | B43: =IF(AND(Xero_Raw!$C$24="Bill",Xero_Raw!$I$24<>"Paid"),Xero_Raw!$A$24+15,"") | C43: =IF(AND(Xero_Raw!$C$24="Bill",Xero_Raw!$I$24<>"Paid"),Xero_Raw!$D$24,"") | D43: =IF(AND(Xero_Raw!$C$24="Bill",Xero_Raw!$I$24<>"Paid"),Xero_Raw!$H$24,"") | E43: =IF(AND(Xero_Raw!$C$24="Bill",Xero_Raw!$I$24<>"Paid"),Xero_Raw!$I$24,"") | F43: =IF(B43="","",MAX($C$4-B43,0)) | G43: =IF(F43="","",IF(F43<=30,"0-30",IF(F43<=60,"31-60",IF(F43<=90,"61-90","90+"))))
A44: =IF(AND(Xero_Raw!$C$25="Bill",Xero_Raw!$I$25<>"Paid"),Xero_Raw!$A$25,"") | B44: =IF(AND(Xero_Raw!$C$25="Bill",Xero_Raw!$I$25<>"Paid"),Xero_Raw!$A$25+15,"") | C44: =IF(AND(Xero_Raw!$C$25="Bill",Xero_Raw!$I$25<>"Paid"),Xero_Raw!$D$25,"") | D44: =IF(AND(Xero_Raw!$C$25="Bill",Xero_Raw!$I$25<>"Paid"),Xero_Raw!$H$25,"") | E44: =IF(AND(Xero_Raw!$C$25="Bill",Xero_Raw!$I$25<>"Paid"),Xero_Raw!$I$25,"") | F44: =IF(B44="","",MAX($C$4-B44,0)) | G44: =IF(F44="","",IF(F44<=30,"0-30",IF(F44<=60,"31-60",IF(F44<=90,"61-90","90+"))))
A45: =IF(AND(Xero_Raw!$C$26="Bill",Xero_Raw!$I$26<>"Paid"),Xero_Raw!$A$26,"") | B45: =IF(AND(Xero_Raw!$C$26="Bill",Xero_Raw!$I$26<>"Paid"),Xero_Raw!$A$26+15,"") | C45: =IF(AND(Xero_Raw!$C$26="Bill",Xero_Raw!$I$26<>"Paid"),Xero_Raw!$D$26,"") | D45: =IF(AND(Xero_Raw!$C$26="Bill",Xero_Raw!$I$26<>"Paid"),Xero_Raw!$H$26,"") | E45: =IF(AND(Xero_Raw!$C$26="Bill",Xero_Raw!$I$26<>"Paid"),Xero_Raw!$I$26,"") | F45: =IF(B45="","",MAX($C$4-B45,0)) | G45: =IF(F45="","",IF(F45<=30,"0-30",IF(F45<=60,"31-60",IF(F45<=90,"61-90","90+"))))
A46: =IF(AND(Xero_Raw!$C$27="Bill",Xero_Raw!$I$27<>"Paid"),Xero_Raw!$A$27,"") | B46: =IF(AND(Xero_Raw!$C$27="Bill",Xero_Raw!$I$27<>"Paid"),Xero_Raw!$A$27+15,"") | C46: =IF(AND(Xero_Raw!$C$27="Bill",Xero_Raw!$I$27<>"Paid"),Xero_Raw!$D$27,"") | D46: =IF(AND(Xero_Raw!$C$27="Bill",Xero_Raw!$I$27<>"Paid"),Xero_Raw!$H$27,"") | E46: =IF(AND(Xero_Raw!$C$27="Bill",Xero_Raw!$I$27<>"Paid"),Xero_Raw!$I$27,"") | F46: =IF(B46="","",MAX($C$4-B46,0)) | G46: =IF(F46="","",IF(F46<=30,"0-30",IF(F46<=60,"31-60",IF(F46<=90,"61-90","90+"))))
A47: =IF(AND(Xero_Raw!$C$28="Bill",Xero_Raw!$I$28<>"Paid"),Xero_Raw!$A$28,"") | B47: =IF(AND(Xero_Raw!$C$28="Bill",Xero_Raw!$I$28<>"Paid"),Xero_Raw!$A$28+15,"") | C47: =IF(AND(Xero_Raw!$C$28="Bill",Xero_Raw!$I$28<>"Paid"),Xero_Raw!$D$28,"") | D47: =IF(AND(Xero_Raw!$C$28="Bill",Xero_Raw!$I$28<>"Paid"),Xero_Raw!$H$28,"") | E47: =IF(AND(Xero_Raw!$C$28="Bill",Xero_Raw!$I$28<>"Paid"),Xero_Raw!$I$28,"") | F47: =IF(B47="","",MAX($C$4-B47,0)) | G47: =IF(F47="","",IF(F47<=30,"0-30",IF(F47<=60,"31-60",IF(F47<=90,"61-90","90+"))))
A48: =IF(AND(Xero_Raw!$C$29="Bill",Xero_Raw!$I$29<>"Paid"),Xero_Raw!$A$29,"") | B48: =IF(AND(Xero_Raw!$C$29="Bill",Xero_Raw!$I$29<>"Paid"),Xero_Raw!$A$29+15,"") | C48: =IF(AND(Xero_Raw!$C$29="Bill",Xero_Raw!$I$29<>"Paid"),Xero_Raw!$D$29,"") | D48: =IF(AND(Xero_Raw!$C$29="Bill",Xero_Raw!$I$29<>"Paid"),Xero_Raw!$H$29,"") | E48: =IF(AND(Xero_Raw!$C$29="Bill",Xero_Raw!$I$29<>"Paid"),Xero_Raw!$I$29,"") | F48: =IF(B48="","",MAX($C$4-B48,0)) | G48: =IF(F48="","",IF(F48<=30,"0-30",IF(F48<=60,"31-60",IF(F48<=90,"61-90","90+"))))
A49: =IF(AND(Xero_Raw!$C$30="Bill",Xero_Raw!$I$30<>"Paid"),Xero_Raw!$A$30,"") | B49: =IF(AND(Xero_Raw!$C$30="Bill",Xero_Raw!$I$30<>"Paid"),Xero_Raw!$A$30+15,"") | C49: =IF(AND(Xero_Raw!$C$30="Bill",Xero_Raw!$I$30<>"Paid"),Xero_Raw!$D$30,"") | D49: =IF(AND(Xero_Raw!$C$30="Bill",Xero_Raw!$I$30<>"Paid"),Xero_Raw!$H$30,"") | E49: =IF(AND(Xero_Raw!$C$30="Bill",Xero_Raw!$I$30<>"Paid"),Xero_Raw!$I$30,"") | F49: =IF(B49="","",MAX($C$4-B49,0)) | G49: =IF(F49="","",IF(F49<=30,"0-30",IF(F49<=60,"31-60",IF(F49<=90,"61-90","90+"))))
A50: =IF(AND(Xero_Raw!$C$31="Bill",Xero_Raw!$I$31<>"Paid"),Xero_Raw!$A$31,"") | B50: =IF(AND(Xero_Raw!$C$31="Bill",Xero_Raw!$I$31<>"Paid"),Xero_Raw!$A$31+15,"") | C50: =IF(AND(Xero_Raw!$C$31="Bill",Xero_Raw!$I$31<>"Paid"),Xero_Raw!$D$31,"") | D50: =IF(AND(Xero_Raw!$C$31="Bill",Xero_Raw!$I$31<>"Paid"),Xero_Raw!$H$31,"") | E50: =IF(AND(Xero_Raw!$C$31="Bill",Xero_Raw!$I$31<>"Paid"),Xero_Raw!$I$31,"") | F50: =IF(B50="","",MAX($C$4-B50,0)) | G50: =IF(F50="","",IF(F50<=30,"0-30",IF(F50<=60,"31-60",IF(F50<=90,"61-90","90+"))))
A51: =IF(AND(Xero_Raw!$C$32="Bill",Xero_Raw!$I$32<>"Paid"),Xero_Raw!$A$32,"") | B51: =IF(AND(Xero_Raw!$C$32="Bill",Xero_Raw!$I$32<>"Paid"),Xero_Raw!$A$32+15,"") | C51: =IF(AND(Xero_Raw!$C$32="Bill",Xero_Raw!$I$32<>"Paid"),Xero_Raw!$D$32,"") | D51: =IF(AND(Xero_Raw!$C$32="Bill",Xero_Raw!$I$32<>"Paid"),Xero_Raw!$H$32,"") | E51: =IF(AND(Xero_Raw!$C$32="Bill",Xero_Raw!$I$32<>"Paid"),Xero_Raw!$I$32,"") | F51: =IF(B51="","",MAX($C$4-B51,0)) | G51: =IF(F51="","",IF(F51<=30,"0-30",IF(F51<=60,"31-60",IF(F51<=90,"61-90","90+"))))
A52: =IF(AND(Xero_Raw!$C$33="Bill",Xero_Raw!$I$33<>"Paid"),Xero_Raw!$A$33,"") | B52: =IF(AND(Xero_Raw!$C$33="Bill",Xero_Raw!$I$33<>"Paid"),Xero_Raw!$A$33+15,"") | C52: =IF(AND(Xero_Raw!$C$33="Bill",Xero_Raw!$I$33<>"Paid"),Xero_Raw!$D$33,"") | D52: =IF(AND(Xero_Raw!$C$33="Bill",Xero_Raw!$I$33<>"Paid"),Xero_Raw!$H$33,"") | E52: =IF(AND(Xero_Raw!$C$33="Bill",Xero_Raw!$I$33<>"Paid"),Xero_Raw!$I$33,"") | F52: =IF(B52="","",MAX($C$4-B52,0)) | G52: =IF(F52="","",IF(F52<=30,"0-30",IF(F52<=60,"31-60",IF(F52<=90,"61-90","90+"))))
A53: =IF(AND(Xero_Raw!$C$34="Bill",Xero_Raw!$I$34<>"Paid"),Xero_Raw!$A$34,"") | B53: =IF(AND(Xero_Raw!$C$34="Bill",Xero_Raw!$I$34<>"Paid"),Xero_Raw!$A$34+15,"") | C53: =IF(AND(Xero_Raw!$C$34="Bill",Xero_Raw!$I$34<>"Paid"),Xero_Raw!$D$34,"") | D53: =IF(AND(Xero_Raw!$C$34="Bill",Xero_Raw!$I$34<>"Paid"),Xero_Raw!$H$34,"") | E53: =IF(AND(Xero_Raw!$C$34="Bill",Xero_Raw!$I$34<>"Paid"),Xero_Raw!$I$34,"") | F53: =IF(B53="","",MAX($C$4-B53,0)) | G53: =IF(F53="","",IF(F53<=30,"0-30",IF(F53<=60,"31-60",IF(F53<=90,"61-90","90+"))))
A54: =IF(AND(Xero_Raw!$C$35="Bill",Xero_Raw!$I$35<>"Paid"),Xero_Raw!$A$35,"") | B54: =IF(AND(Xero_Raw!$C$35="Bill",Xero_Raw!$I$35<>"Paid"),Xero_Raw!$A$35+15,"") | C54: =IF(AND(Xero_Raw!$C$35="Bill",Xero_Raw!$I$35<>"Paid"),Xero_Raw!$D$35,"") | D54: =IF(AND(Xero_Raw!$C$35="Bill",Xero_Raw!$I$35<>"Paid"),Xero_Raw!$H$35,"") | E54: =IF(AND(Xero_Raw!$C$35="Bill",Xero_Raw!$I$35<>"Paid"),Xero_Raw!$I$35,"") | F54: =IF(B54="","",MAX($C$4-B54,0)) | G54: =IF(F54="","",IF(F54<=30,"0-30",IF(F54<=60,"31-60",IF(F54<=90,"61-90","90+"))))
A55: =IF(AND(Xero_Raw!$C$36="Bill",Xero_Raw!$I$36<>"Paid"),Xero_Raw!$A$36,"") | B55: =IF(AND(Xero_Raw!$C$36="Bill",Xero_Raw!$I$36<>"Paid"),Xero_Raw!$A$36+15,"") | C55: =IF(AND(Xero_Raw!$C$36="Bill",Xero_Raw!$I$36<>"Paid"),Xero_Raw!$D$36,"") | D55: =IF(AND(Xero_Raw!$C$36="Bill",Xero_Raw!$I$36<>"Paid"),Xero_Raw!$H$36,"") | E55: =IF(AND(Xero_Raw!$C$36="Bill",Xero_Raw!$I$36<>"Paid"),Xero_Raw!$I$36,"") | F55: =IF(B55="","",MAX($C$4-B55,0)) | G55: =IF(F55="","",IF(F55<=30,"0-30",IF(F55<=60,"31-60",IF(F55<=90,"61-90","90+"))))
A56: =IF(AND(Xero_Raw!$C$37="Bill",Xero_Raw!$I$37<>"Paid"),Xero_Raw!$A$37,"") | B56: =IF(AND(Xero_Raw!$C$37="Bill",Xero_Raw!$I$37<>"Paid"),Xero_Raw!$A$37+15,"") | C56: =IF(AND(Xero_Raw!$C$37="Bill",Xero_Raw!$I$37<>"Paid"),Xero_Raw!$D$37,"") | D56: =IF(AND(Xero_Raw!$C$37="Bill",Xero_Raw!$I$37<>"Paid"),Xero_Raw!$H$37,"") | E56: =IF(AND(Xero_Raw!$C$37="Bill",Xero_Raw!$I$37<>"Paid"),Xero_Raw!$I$37,"") | F56: =IF(B56="","",MAX($C$4-B56,0)) | G56: =IF(F56="","",IF(F56<=30,"0-30",IF(F56<=60,"31-60",IF(F56<=90,"61-90","90+"))))
A57: =IF(AND(Xero_Raw!$C$38="Bill",Xero_Raw!$I$38<>"Paid"),Xero_Raw!$A$38,"") | B57: =IF(AND(Xero_Raw!$C$38="Bill",Xero_Raw!$I$38<>"Paid"),Xero_Raw!$A$38+15,"") | C57: =IF(AND(Xero_Raw!$C$38="Bill",Xero_Raw!$I$38<>"Paid"),Xero_Raw!$D$38,"") | D57: =IF(AND(Xero_Raw!$C$38="Bill",Xero_Raw!$I$38<>"Paid"),Xero_Raw!$H$38,"") | E57: =IF(AND(Xero_Raw!$C$38="Bill",Xero_Raw!$I$38<>"Paid"),Xero_Raw!$I$38,"") | F57: =IF(B57="","",MAX($C$4-B57,0)) | G57: =IF(F57="","",IF(F57<=30,"0-30",IF(F57<=60,"31-60",IF(F57<=90,"61-90","90+"))))
A58: =IF(AND(Xero_Raw!$C$39="Bill",Xero_Raw!$I$39<>"Paid"),Xero_Raw!$A$39,"") | B58: =IF(AND(Xero_Raw!$C$39="Bill",Xero_Raw!$I$39<>"Paid"),Xero_Raw!$A$39+15,"") | C58: =IF(AND(Xero_Raw!$C$39="Bill",Xero_Raw!$I$39<>"Paid"),Xero_Raw!$D$39,"") | D58: =IF(AND(Xero_Raw!$C$39="Bill",Xero_Raw!$I$39<>"Paid"),Xero_Raw!$H$39,"") | E58: =IF(AND(Xero_Raw!$C$39="Bill",Xero_Raw!$I$39<>"Paid"),Xero_Raw!$I$39,"") | F58: =IF(B58="","",MAX($C$4-B58,0)) | G58: =IF(F58="","",IF(F58<=30,"0-30",IF(F58<=60,"31-60",IF(F58<=90,"61-90","90+"))))
A59: =IF(AND(Xero_Raw!$C$40="Bill",Xero_Raw!$I$40<>"Paid"),Xero_Raw!$A$40,"") | B59: =IF(AND(Xero_Raw!$C$40="Bill",Xero_Raw!$I$40<>"Paid"),Xero_Raw!$A$40+15,"") | C59: =IF(AND(Xero_Raw!$C$40="Bill",Xero_Raw!$I$40<>"Paid"),Xero_Raw!$D$40,"") | D59: =IF(AND(Xero_Raw!$C$40="Bill",Xero_Raw!$I$40<>"Paid"),Xero_Raw!$H$40,"") | E59: =IF(AND(Xero_Raw!$C$40="Bill",Xero_Raw!$I$40<>"Paid"),Xero_Raw!$I$40,"") | F59: =IF(B59="","",MAX($C$4-B59,0)) | G59: =IF(F59="","",IF(F59<=30,"0-30",IF(F59<=60,"31-60",IF(F59<=90,"61-90","90+"))))
A60: =IF(AND(Xero_Raw!$C$41="Bill",Xero_Raw!$I$41<>"Paid"),Xero_Raw!$A$41,"") | B60: =IF(AND(Xero_Raw!$C$41="Bill",Xero_Raw!$I$41<>"Paid"),Xero_Raw!$A$41+15,"") | C60: =IF(AND(Xero_Raw!$C$41="Bill",Xero_Raw!$I$41<>"Paid"),Xero_Raw!$D$41,"") | D60: =IF(AND(Xero_Raw!$C$41="Bill",Xero_Raw!$I$41<>"Paid"),Xero_Raw!$H$41,"") | E60: =IF(AND(Xero_Raw!$C$41="Bill",Xero_Raw!$I$41<>"Paid"),Xero_Raw!$I$41,"") | F60: =IF(B60="","",MAX($C$4-B60,0)) | G60: =IF(F60="","",IF(F60<=30,"0-30",IF(F60<=60,"31-60",IF(F60<=90,"61-90","90+"))))
A61: =IF(AND(Xero_Raw!$C$42="Bill",Xero_Raw!$I$42<>"Paid"),Xero_Raw!$A$42,"") | B61: =IF(AND(Xero_Raw!$C$42="Bill",Xero_Raw!$I$42<>"Paid"),Xero_Raw!$A$42+15,"") | C61: =IF(AND(Xero_Raw!$C$42="Bill",Xero_Raw!$I$42<>"Paid"),Xero_Raw!$D$42,"") | D61: =IF(AND(Xero_Raw!$C$42="Bill",Xero_Raw!$I$42<>"Paid"),Xero_Raw!$H$42,"") | E61: =IF(AND(Xero_Raw!$C$42="Bill",Xero_Raw!$I$42<>"Paid"),Xero_Raw!$I$42,"") | F61: =IF(B61="","",MAX($C$4-B61,0)) | G61: =IF(F61="","",IF(F61<=30,"0-30",IF(F61<=60,"31-60",IF(F61<=90,"61-90","90+"))))
A63: PAYABLES SUMMARY BY VENDOR (0-30 / 31-60 / 61-90 / 90+)
A64: Vendor | B64: 0-30 days | C64: 31-60 days | D64: 61-90 days | E64: 90+ days | F64: Total Outstanding
A65: WPP Cloud Hosting LLC | B65: =SUMPRODUCT((Vendor_Invoices_Upload!$H$4:$H$5003<>"Paid")*(Vendor_Invoices_Upload!$B$4:$B$5003<>"")*(Vendor_Invoices_Upload!$E$4:$E$5003=$A65)*(($C$4-Vendor_Invoices_Upload!$C$4:$C$5003)<=30)*Vendor_Invoices_Upload!$G$4:$G$5003)+SUMPRODUCT((Xero_Raw!$C$4:$C$5003="Bill")*(Xero_Raw!$I$4:$I$5003<>"Paid")*(Xero_Raw!$A$4:$A$5003<>"")*(Xero_Raw!$D$4:$D$5003=$A65)*(($C$4-(Xero_Raw!$A$4:$A$5003+15))<=30)*Xero_Raw!$H$4:$H$5003) -> 4149.25 | C65: =SUMPRODUCT((Vendor_Invoices_Upload!$H$4:$H$5003<>"Paid")*(Vendor_Invoices_Upload!$B$4:$B$5003<>"")*(Vendor_Invoices_Upload!$E$4:$E$5003=$A65)*(($C$4-Vendor_Invoices_Upload!$C$4:$C$5003)>=31)*(($C$4-Vendor_Invoices_Upload!$C$4:$C$5003)<=60)*Vendor_Invoices_Upload!$G$4:$G$5003)+SUMPRODUCT((Xero_Raw!$C$4:$C$5003="Bill")*(Xero_Raw!$I$4:$I$5003<>"Paid")*(Xero_Raw!$A$4:$A$5003<>"")*(Xero_Raw!$D$4:$D$5003=$A65)*(($C$4-(Xero_Raw!$A$4:$A$5003+15))>=31)*(($C$4-(Xero_Raw!$A$4:$A$5003+15))<=60)*Xero_Raw!$H$4:$H$5003) -> 0 | D65: =SUMPRODUCT((Vendor_Invoices_Upload!$H$4:$H$5003<>"Paid")*(Vendor_Invoices_Upload!$B$4:$B$5003<>"")*(Vendor_Invoices_Upload!$E$4:$E$5003=$A65)*(($C$4-Vendor_Invoices_Upload!$C$4:$C$5003)>=61)*(($C$4-Vendor_Invoices_Upload!$C$4:$C$5003)<=90)*Vendor_Invoices_Upload!$G$4:$G$5003)+SUMPRODUCT((Xero_Raw!$C$4:$C$5003="Bill")*(Xero_Raw!$I$4:$I$5003<>"Paid")*(Xero_Raw!$A$4:$A$5003<>"")*(Xero_Raw!$D$4:$D$5003=$A65)*(($C$4-(Xero_Raw!$A$4:$A$5003+15))>=61)*(($C$4-(Xero_Raw!$A$4:$A$5003+15))<=90)*Xero_Raw!$H$4:$H$5003) -> 0 | E65: =SUMPRODUCT((Vendor_Invoices_Upload!$H$4:$H$5003<>"Paid")*(Vendor_Invoices_Upload!$B$4:$B$5003<>"")*(Vendor_Invoices_Upload!$E$4:$E$5003=$A65)*(($C$4-Vendor_Invoices_Upload!$C$4:$C$5003)>=91)*Vendor_Invoices_Upload!$G$4:$G$5003)+SUMPRODUCT((Xero_Raw!$C$4:$C$5003="Bill")*(Xero_Raw!$I$4:$I$5003<>"Paid")*(Xero_Raw!$A$4:$A$5003<>"")*(Xero_Raw!$D$4:$D$5003=$A65)*(($C$4-(Xero_Raw!$A$4:$A$5003+15))>=91)*Xero_Raw!$H$4:$H$5003) -> 0 | F65: =SUM(B65:E65) -> 4149.25
A66: Freelance Dev Studio FZE | B66: =SUMPRODUCT((Vendor_Invoices_Upload!$H$4:$H$5003<>"Paid")*(Vendor_Invoices_Upload!$B$4:$B$5003<>"")*(Vendor_Invoices_Upload!$E$4:$E$5003=$A66)*(($C$4-Vendor_Invoices_Upload!$C$4:$C$5003)<=30)*Vendor_Invoices_Upload!$G$4:$G$5003)+SUMPRODUCT((Xero_Raw!$C$4:$C$5003="Bill")*(Xero_Raw!$I$4:$I$5003<>"Paid")*(Xero_Raw!$A$4:$A$5003<>"")*(Xero_Raw!$D$4:$D$5003=$A66)*(($C$4-(Xero_Raw!$A$4:$A$5003+15))<=30)*Xero_Raw!$H$4:$H$5003) -> 0 | C66: =SUMPRODUCT((Vendor_Invoices_Upload!$H$4:$H$5003<>"Paid")*(Vendor_Invoices_Upload!$B$4:$B$5003<>"")*(Vendor_Invoices_Upload!$E$4:$E$5003=$A66)*(($C$4-Vendor_Invoices_Upload!$C$4:$C$5003)>=31)*(($C$4-Vendor_Invoices_Upload!$C$4:$C$5003)<=60)*Vendor_Invoices_Upload!$G$4:$G$5003)+SUMPRODUCT((Xero_Raw!$C$4:$C$5003="Bill")*(Xero_Raw!$I$4:$I$5003<>"Paid")*(Xero_Raw!$A$4:$A$5003<>"")*(Xero_Raw!$D$4:$D$5003=$A66)*(($C$4-(Xero_Raw!$A$4:$A$5003+15))>=31)*(($C$4-(Xero_Raw!$A$4:$A$5003+15))<=60)*Xero_Raw!$H$4:$H$5003) -> 4441.12 | D66: =SUMPRODUCT((Vendor_Invoices_Upload!$H$4:$H$5003<>"Paid")*(Vendor_Invoices_Upload!$B$4:$B$5003<>"")*(Vendor_Invoices_Upload!$E$4:$E$5003=$A66)*(($C$4-Vendor_Invoices_Upload!$C$4:$C$5003)>=61)*(($C$4-Vendor_Invoices_Upload!$C$4:$C$5003)<=90)*Vendor_Invoices_Upload!$G$4:$G$5003)+SUMPRODUCT((Xero_Raw!$C$4:$C$5003="Bill")*(Xero_Raw!$I$4:$I$5003<>"Paid")*(Xero_Raw!$A$4:$A$5003<>"")*(Xero_Raw!$D$4:$D$5003=$A66)*(($C$4-(Xero_Raw!$A$4:$A$5003+15))>=61)*(($C$4-(Xero_Raw!$A$4:$A$5003+15))<=90)*Xero_Raw!$H$4:$H$5003) -> 0 | E66: =SUMPRODUCT((Vendor_Invoices_Upload!$H$4:$H$5003<>"Paid")*(Vendor_Invoices_Upload!$B$4:$B$5003<>"")*(Vendor_Invoices_Upload!$E$4:$E$5003=$A66)*(($C$4-Vendor_Invoices_Upload!$C$4:$C$5003)>=91)*Vendor_Invoices_Upload!$G$4:$G$5003)+SUMPRODUCT((Xero_Raw!$C$4:$C$5003="Bill")*(Xero_Raw!$I$4:$I$5003<>"Paid")*(Xero_Raw!$A$4:$A$5003<>"")*(Xero_Raw!$D$4:$D$5003=$A66)*(($C$4-(Xero_Raw!$A$4:$A$5003+15))>=91)*Xero_Raw!$H$4:$H$5003) -> 0 | F66: =SUM(B66:E66) -> 4441.12
A67: Twilio Inc (WhatsApp API) | B67: =SUMPRODUCT((Vendor_Invoices_Upload!$H$4:$H$5003<>"Paid")*(Vendor_Invoices_Upload!$B$4:$B$5003<>"")*(Vendor_Invoices_Upload!$E$4:$E$5003=$A67)*(($C$4-Vendor_Invoices_Upload!$C$4:$C$5003)<=30)*Vendor_Invoices_Upload!$G$4:$G$5003)+SUMPRODUCT((Xero_Raw!$C$4:$C$5003="Bill")*(Xero_Raw!$I$4:$I$5003<>"Paid")*(Xero_Raw!$A$4:$A$5003<>"")*(Xero_Raw!$D$4:$D$5003=$A67)*(($C$4-(Xero_Raw!$A$4:$A$5003+15))<=30)*Xero_Raw!$H$4:$H$5003) -> 0 | C67: =SUMPRODUCT((Vendor_Invoices_Upload!$H$4:$H$5003<>"Paid")*(Vendor_Invoices_Upload!$B$4:$B$5003<>"")*(Vendor_Invoices_Upload!$E$4:$E$5003=$A67)*(($C$4-Vendor_Invoices_Upload!$C$4:$C$5003)>=31)*(($C$4-Vendor_Invoices_Upload!$C$4:$C$5003)<=60)*Vendor_Invoices_Upload!$G$4:$G$5003)+SUMPRODUCT((Xero_Raw!$C$4:$C$5003="Bill")*(Xero_Raw!$I$4:$I$5003<>"Paid")*(Xero_Raw!$A$4:$A$5003<>"")*(Xero_Raw!$D$4:$D$5003=$A67)*(($C$4-(Xero_Raw!$A$4:$A$5003+15))>=31)*(($C$4-(Xero_Raw!$A$4:$A$5003+15))<=60)*Xero_Raw!$H$4:$H$5003) -> 0 | D67: =SUMPRODUCT((Vendor_Invoices_Upload!$H$4:$H$5003<>"Paid")*(Vendor_Invoices_Upload!$B$4:$B$5003<>"")*(Vendor_Invoices_Upload!$E$4:$E$5003=$A67)*(($C$4-Vendor_Invoices_Upload!$C$4:$C$5003)>=61)*(($C$4-Vendor_Invoices_Upload!$C$4:$C$5003)<=90)*Vendor_Invoices_Upload!$G$4:$G$5003)+SUMPRODUCT((Xero_Raw!$C$4:$C$5003="Bill")*(Xero_Raw!$I$4:$I$5003<>"Paid")*(Xero_Raw!$A$4:$A$5003<>"")*(Xero_Raw!$D$4:$D$5003=$A67)*(($C$4-(Xero_Raw!$A$4:$A$5003+15))>=61)*(($C$4-(Xero_Raw!$A$4:$A$5003+15))<=90)*Xero_Raw!$H$4:$H$5003) -> 0 | E67: =SUMPRODUCT((Vendor_Invoices_Upload!$H$4:$H$5003<>"Paid")*(Vendor_Invoices_Upload!$B$4:$B$5003<>"")*(Vendor_Invoices_Upload!$E$4:$E$5003=$A67)*(($C$4-Vendor_Invoices_Upload!$C$4:$C$5003)>=91)*Vendor_Invoices_Upload!$G$4:$G$5003)+SUMPRODUCT((Xero_Raw!$C$4:$C$5003="Bill")*(Xero_Raw!$I$4:$I$5003<>"Paid")*(Xero_Raw!$A$4:$A$5003<>"")*(Xero_Raw!$D$4:$D$5003=$A67)*(($C$4-(Xero_Raw!$A$4:$A$5003+15))>=91)*Xero_Raw!$H$4:$H$5003) -> 0 | F67: =SUM(B67:E67) -> 0
A68: Al Manara Office Supplies | B68: =SUMPRODUCT((Vendor_Invoices_Upload!$H$4:$H$5003<>"Paid")*(Vendor_Invoices_Upload!$B$4:$B$5003<>"")*(Vendor_Invoices_Upload!$E$4:$E$5003=$A68)*(($C$4-Vendor_Invoices_Upload!$C$4:$C$5003)<=30)*Vendor_Invoices_Upload!$G$4:$G$5003)+SUMPRODUCT((Xero_Raw!$C$4:$C$5003="Bill")*(Xero_Raw!$I$4:$I$5003<>"Paid")*(Xero_Raw!$A$4:$A$5003<>"")*(Xero_Raw!$D$4:$D$5003=$A68)*(($C$4-(Xero_Raw!$A$4:$A$5003+15))<=30)*Xero_Raw!$H$4:$H$5003) -> 0 | C68: =SUMPRODUCT((Vendor_Invoices_Upload!$H$4:$H$5003<>"Paid")*(Vendor_Invoices_Upload!$B$4:$B$5003<>"")*(Vendor_Invoices_Upload!$E$4:$E$5003=$A68)*(($C$4-Vendor_Invoices_Upload!$C$4:$C$5003)>=31)*(($C$4-Vendor_Invoices_Upload!$C$4:$C$5003)<=60)*Vendor_Invoices_Upload!$G$4:$G$5003)+SUMPRODUCT((Xero_Raw!$C$4:$C$5003="Bill")*(Xero_Raw!$I$4:$I$5003<>"Paid")*(Xero_Raw!$A$4:$A$5003<>"")*(Xero_Raw!$D$4:$D$5003=$A68)*(($C$4-(Xero_Raw!$A$4:$A$5003+15))>=31)*(($C$4-(Xero_Raw!$A$4:$A$5003+15))<=60)*Xero_Raw!$H$4:$H$5003) -> 0 | D68: =SUMPRODUCT((Vendor_Invoices_Upload!$H$4:$H$5003<>"Paid")*(Vendor_Invoices_Upload!$B$4:$B$5003<>"")*(Vendor_Invoices_Upload!$E$4:$E$5003=$A68)*(($C$4-Vendor_Invoices_Upload!$C$4:$C$5003)>=61)*(($C$4-Vendor_Invoices_Upload!$C$4:$C$5003)<=90)*Vendor_Invoices_Upload!$G$4:$G$5003)+SUMPRODUCT((Xero_Raw!$C$4:$C$5003="Bill")*(Xero_Raw!$I$4:$I$5003<>"Paid")*(Xero_Raw!$A$4:$A$5003<>"")*(Xero_Raw!$D$4:$D$5003=$A68)*(($C$4-(Xero_Raw!$A$4:$A$5003+15))>=61)*(($C$4-(Xero_Raw!$A$4:$A$5003+15))<=90)*Xero_Raw!$H$4:$H$5003) -> 0 | E68: =SUMPRODUCT((Vendor_Invoices_Upload!$H$4:$H$5003<>"Paid")*(Vendor_Invoices_Upload!$B$4:$B$5003<>"")*(Vendor_Invoices_Upload!$E$4:$E$5003=$A68)*(($C$4-Vendor_Invoices_Upload!$C$4:$C$5003)>=91)*Vendor_Invoices_Upload!$G$4:$G$5003)+SUMPRODUCT((Xero_Raw!$C$4:$C$5003="Bill")*(Xero_Raw!$I$4:$I$5003<>"Paid")*(Xero_Raw!$A$4:$A$5003<>"")*(Xero_Raw!$D$4:$D$5003=$A68)*(($C$4-(Xero_Raw!$A$4:$A$5003+15))>=91)*Xero_Raw!$H$4:$H$5003) -> 0 | F68: =SUM(B68:E68) -> 0
A69: Emirates Trade License Authority | B69: =SUMPRODUCT((Vendor_Invoices_Upload!$H$4:$H$5003<>"Paid")*(Vendor_Invoices_Upload!$B$4:$B$5003<>"")*(Vendor_Invoices_Upload!$E$4:$E$5003=$A69)*(($C$4-Vendor_Invoices_Upload!$C$4:$C$5003)<=30)*Vendor_Invoices_Upload!$G$4:$G$5003)+SUMPRODUCT((Xero_Raw!$C$4:$C$5003="Bill")*(Xero_Raw!$I$4:$I$5003<>"Paid")*(Xero_Raw!$A$4:$A$5003<>"")*(Xero_Raw!$D$4:$D$5003=$A69)*(($C$4-(Xero_Raw!$A$4:$A$5003+15))<=30)*Xero_Raw!$H$4:$H$5003) -> 3442.89 | C69: =SUMPRODUCT((Vendor_Invoices_Upload!$H$4:$H$5003<>"Paid")*(Vendor_Invoices_Upload!$B$4:$B$5003<>"")*(Vendor_Invoices_Upload!$E$4:$E$5003=$A69)*(($C$4-Vendor_Invoices_Upload!$C$4:$C$5003)>=31)*(($C$4-Vendor_Invoices_Upload!$C$4:$C$5003)<=60)*Vendor_Invoices_Upload!$G$4:$G$5003)+SUMPRODUCT((Xero_Raw!$C$4:$C$5003="Bill")*(Xero_Raw!$I$4:$I$5003<>"Paid")*(Xero_Raw!$A$4:$A$5003<>"")*(Xero_Raw!$D$4:$D$5003=$A69)*(($C$4-(Xero_Raw!$A$4:$A$5003+15))>=31)*(($C$4-(Xero_Raw!$A$4:$A$5003+15))<=60)*Xero_Raw!$H$4:$H$5003) -> 0 | D69: =SUMPRODUCT((Vendor_Invoices_Upload!$H$4:$H$5003<>"Paid")*(Vendor_Invoices_Upload!$B$4:$B$5003<>"")*(Vendor_Invoices_Upload!$E$4:$E$5003=$A69)*(($C$4-Vendor_Invoices_Upload!$C$4:$C$5003)>=61)*(($C$4-Vendor_Invoices_Upload!$C$4:$C$5003)<=90)*Vendor_Invoices_Upload!$G$4:$G$5003)+SUMPRODUCT((Xero_Raw!$C$4:$C$5003="Bill")*(Xero_Raw!$I$4:$I$5003<>"Paid")*(Xero_Raw!$A$4:$A$5003<>"")*(Xero_Raw!$D$4:$D$5003=$A69)*(($C$4-(Xero_Raw!$A$4:$A$5003+15))>=61)*(($C$4-(Xero_Raw!$A$4:$A$5003+15))<=90)*Xero_Raw!$H$4:$H$5003) -> 0 | E69: =SUMPRODUCT((Vendor_Invoices_Upload!$H$4:$H$5003<>"Paid")*(Vendor_Invoices_Upload!$B$4:$B$5003<>"")*(Vendor_Invoices_Upload!$E$4:$E$5003=$A69)*(($C$4-Vendor_Invoices_Upload!$C$4:$C$5003)>=91)*Vendor_Invoices_Upload!$G$4:$G$5003)+SUMPRODUCT((Xero_Raw!$C$4:$C$5003="Bill")*(Xero_Raw!$I$4:$I$5003<>"Paid")*(Xero_Raw!$A$4:$A$5003<>"")*(Xero_Raw!$D$4:$D$5003=$A69)*(($C$4-(Xero_Raw!$A$4:$A$5003+15))>=91)*Xero_Raw!$H$4:$H$5003) -> 0 | F69: =SUM(B69:E69) -> 3442.89
A70: Salary - General & Administration | B70: =SUMPRODUCT((Vendor_Invoices_Upload!$H$4:$H$5003<>"Paid")*(Vendor_Invoices_Upload!$B$4:$B$5003<>"")*(Vendor_Invoices_Upload!$E$4:$E$5003=$A70)*(($C$4-Vendor_Invoices_Upload!$C$4:$C$5003)<=30)*Vendor_Invoices_Upload!$G$4:$G$5003)+SUMPRODUCT((Xero_Raw!$C$4:$C$5003="Bill")*(Xero_Raw!$I$4:$I$5003<>"Paid")*(Xero_Raw!$A$4:$A$5003<>"")*(Xero_Raw!$D$4:$D$5003=$A70)*(($C$4-(Xero_Raw!$A$4:$A$5003+15))<=30)*Xero_Raw!$H$4:$H$5003) -> 0 | C70: =SUMPRODUCT((Vendor_Invoices_Upload!$H$4:$H$5003<>"Paid")*(Vendor_Invoices_Upload!$B$4:$B$5003<>"")*(Vendor_Invoices_Upload!$E$4:$E$5003=$A70)*(($C$4-Vendor_Invoices_Upload!$C$4:$C$5003)>=31)*(($C$4-Vendor_Invoices_Upload!$C$4:$C$5003)<=60)*Vendor_Invoices_Upload!$G$4:$G$5003)+SUMPRODUCT((Xero_Raw!$C$4:$C$5003="Bill")*(Xero_Raw!$I$4:$I$5003<>"Paid")*(Xero_Raw!$A$4:$A$5003<>"")*(Xero_Raw!$D$4:$D$5003=$A70)*(($C$4-(Xero_Raw!$A$4:$A$5003+15))>=31)*(($C$4-(Xero_Raw!$A$4:$A$5003+15))<=60)*Xero_Raw!$H$4:$H$5003) -> 0 | D70: =SUMPRODUCT((Vendor_Invoices_Upload!$H$4:$H$5003<>"Paid")*(Vendor_Invoices_Upload!$B$4:$B$5003<>"")*(Vendor_Invoices_Upload!$E$4:$E$5003=$A70)*(($C$4-Vendor_Invoices_Upload!$C$4:$C$5003)>=61)*(($C$4-Vendor_Invoices_Upload!$C$4:$C$5003)<=90)*Vendor_Invoices_Upload!$G$4:$G$5003)+SUMPRODUCT((Xero_Raw!$C$4:$C$5003="Bill")*(Xero_Raw!$I$4:$I$5003<>"Paid")*(Xero_Raw!$A$4:$A$5003<>"")*(Xero_Raw!$D$4:$D$5003=$A70)*(($C$4-(Xero_Raw!$A$4:$A$5003+15))>=61)*(($C$4-(Xero_Raw!$A$4:$A$5003+15))<=90)*Xero_Raw!$H$4:$H$5003) -> 0 | E70: =SUMPRODUCT((Vendor_Invoices_Upload!$H$4:$H$5003<>"Paid")*(Vendor_Invoices_Upload!$B$4:$B$5003<>"")*(Vendor_Invoices_Upload!$E$4:$E$5003=$A70)*(($C$4-Vendor_Invoices_Upload!$C$4:$C$5003)>=91)*Vendor_Invoices_Upload!$G$4:$G$5003)+SUMPRODUCT((Xero_Raw!$C$4:$C$5003="Bill")*(Xero_Raw!$I$4:$I$5003<>"Paid")*(Xero_Raw!$A$4:$A$5003<>"")*(Xero_Raw!$D$4:$D$5003=$A70)*(($C$4-(Xero_Raw!$A$4:$A$5003+15))>=91)*Xero_Raw!$H$4:$H$5003) -> 0 | F70: =SUM(B70:E70) -> 0
A71: Office Rent | B71: =SUMPRODUCT((Vendor_Invoices_Upload!$H$4:$H$5003<>"Paid")*(Vendor_Invoices_Upload!$B$4:$B$5003<>"")*(Vendor_Invoices_Upload!$E$4:$E$5003=$A71)*(($C$4-Vendor_Invoices_Upload!$C$4:$C$5003)<=30)*Vendor_Invoices_Upload!$G$4:$G$5003)+SUMPRODUCT((Xero_Raw!$C$4:$C$5003="Bill")*(Xero_Raw!$I$4:$I$5003<>"Paid")*(Xero_Raw!$A$4:$A$5003<>"")*(Xero_Raw!$D$4:$D$5003=$A71)*(($C$4-(Xero_Raw!$A$4:$A$5003+15))<=30)*Xero_Raw!$H$4:$H$5003) -> 0 | C71: =SUMPRODUCT((Vendor_Invoices_Upload!$H$4:$H$5003<>"Paid")*(Vendor_Invoices_Upload!$B$4:$B$5003<>"")*(Vendor_Invoices_Upload!$E$4:$E$5003=$A71)*(($C$4-Vendor_Invoices_Upload!$C$4:$C$5003)>=31)*(($C$4-Vendor_Invoices_Upload!$C$4:$C$5003)<=60)*Vendor_Invoices_Upload!$G$4:$G$5003)+SUMPRODUCT((Xero_Raw!$C$4:$C$5003="Bill")*(Xero_Raw!$I$4:$I$5003<>"Paid")*(Xero_Raw!$A$4:$A$5003<>"")*(Xero_Raw!$D$4:$D$5003=$A71)*(($C$4-(Xero_Raw!$A$4:$A$5003+15))>=31)*(($C$4-(Xero_Raw!$A$4:$A$5003+15))<=60)*Xero_Raw!$H$4:$H$5003) -> 0 | D71: =SUMPRODUCT((Vendor_Invoices_Upload!$H$4:$H$5003<>"Paid")*(Vendor_Invoices_Upload!$B$4:$B$5003<>"")*(Vendor_Invoices_Upload!$E$4:$E$5003=$A71)*(($C$4-Vendor_Invoices_Upload!$C$4:$C$5003)>=61)*(($C$4-Vendor_Invoices_Upload!$C$4:$C$5003)<=90)*Vendor_Invoices_Upload!$G$4:$G$5003)+SUMPRODUCT((Xero_Raw!$C$4:$C$5003="Bill")*(Xero_Raw!$I$4:$I$5003<>"Paid")*(Xero_Raw!$A$4:$A$5003<>"")*(Xero_Raw!$D$4:$D$5003=$A71)*(($C$4-(Xero_Raw!$A$4:$A$5003+15))>=61)*(($C$4-(Xero_Raw!$A$4:$A$5003+15))<=90)*Xero_Raw!$H$4:$H$5003) -> 0 | E71: =SUMPRODUCT((Vendor_Invoices_Upload!$H$4:$H$5003<>"Paid")*(Vendor_Invoices_Upload!$B$4:$B$5003<>"")*(Vendor_Invoices_Upload!$E$4:$E$5003=$A71)*(($C$4-Vendor_Invoices_Upload!$C$4:$C$5003)>=91)*Vendor_Invoices_Upload!$G$4:$G$5003)+SUMPRODUCT((Xero_Raw!$C$4:$C$5003="Bill")*(Xero_Raw!$I$4:$I$5003<>"Paid")*(Xero_Raw!$A$4:$A$5003<>"")*(Xero_Raw!$D$4:$D$5003=$A71)*(($C$4-(Xero_Raw!$A$4:$A$5003+15))>=91)*Xero_Raw!$H$4:$H$5003) -> 0 | F71: =SUM(B71:E71) -> 0
A72: SaaS & Software Subscriptions | B72: =SUMPRODUCT((Vendor_Invoices_Upload!$H$4:$H$5003<>"Paid")*(Vendor_Invoices_Upload!$B$4:$B$5003<>"")*(Vendor_Invoices_Upload!$E$4:$E$5003=$A72)*(($C$4-Vendor_Invoices_Upload!$C$4:$C$5003)<=30)*Vendor_Invoices_Upload!$G$4:$G$5003)+SUMPRODUCT((Xero_Raw!$C$4:$C$5003="Bill")*(Xero_Raw!$I$4:$I$5003<>"Paid")*(Xero_Raw!$A$4:$A$5003<>"")*(Xero_Raw!$D$4:$D$5003=$A72)*(($C$4-(Xero_Raw!$A$4:$A$5003+15))<=30)*Xero_Raw!$H$4:$H$5003) -> 0 | C72: =SUMPRODUCT((Vendor_Invoices_Upload!$H$4:$H$5003<>"Paid")*(Vendor_Invoices_Upload!$B$4:$B$5003<>"")*(Vendor_Invoices_Upload!$E$4:$E$5003=$A72)*(($C$4-Vendor_Invoices_Upload!$C$4:$C$5003)>=31)*(($C$4-Vendor_Invoices_Upload!$C$4:$C$5003)<=60)*Vendor_Invoices_Upload!$G$4:$G$5003)+SUMPRODUCT((Xero_Raw!$C$4:$C$5003="Bill")*(Xero_Raw!$I$4:$I$5003<>"Paid")*(Xero_Raw!$A$4:$A$5003<>"")*(Xero_Raw!$D$4:$D$5003=$A72)*(($C$4-(Xero_Raw!$A$4:$A$5003+15))>=31)*(($C$4-(Xero_Raw!$A$4:$A$5003+15))<=60)*Xero_Raw!$H$4:$H$5003) -> 0 | D72: =SUMPRODUCT((Vendor_Invoices_Upload!$H$4:$H$5003<>"Paid")*(Vendor_Invoices_Upload!$B$4:$B$5003<>"")*(Vendor_Invoices_Upload!$E$4:$E$5003=$A72)*(($C$4-Vendor_Invoices_Upload!$C$4:$C$5003)>=61)*(($C$4-Vendor_Invoices_Upload!$C$4:$C$5003)<=90)*Vendor_Invoices_Upload!$G$4:$G$5003)+SUMPRODUCT((Xero_Raw!$C$4:$C$5003="Bill")*(Xero_Raw!$I$4:$I$5003<>"Paid")*(Xero_Raw!$A$4:$A$5003<>"")*(Xero_Raw!$D$4:$D$5003=$A72)*(($C$4-(Xero_Raw!$A$4:$A$5003+15))>=61)*(($C$4-(Xero_Raw!$A$4:$A$5003+15))<=90)*Xero_Raw!$H$4:$H$5003) -> 0 | E72: =SUMPRODUCT((Vendor_Invoices_Upload!$H$4:$H$5003<>"Paid")*(Vendor_Invoices_Upload!$B$4:$B$5003<>"")*(Vendor_Invoices_Upload!$E$4:$E$5003=$A72)*(($C$4-Vendor_Invoices_Upload!$C$4:$C$5003)>=91)*Vendor_Invoices_Upload!$G$4:$G$5003)+SUMPRODUCT((Xero_Raw!$C$4:$C$5003="Bill")*(Xero_Raw!$I$4:$I$5003<>"Paid")*(Xero_Raw!$A$4:$A$5003<>"")*(Xero_Raw!$D$4:$D$5003=$A72)*(($C$4-(Xero_Raw!$A$4:$A$5003+15))>=91)*Xero_Raw!$H$4:$H$5003) -> 0 | F72: =SUM(B72:E72) -> 0
A73: Trade License Fee | B73: =SUMPRODUCT((Vendor_Invoices_Upload!$H$4:$H$5003<>"Paid")*(Vendor_Invoices_Upload!$B$4:$B$5003<>"")*(Vendor_Invoices_Upload!$E$4:$E$5003=$A73)*(($C$4-Vendor_Invoices_Upload!$C$4:$C$5003)<=30)*Vendor_Invoices_Upload!$G$4:$G$5003)+SUMPRODUCT((Xero_Raw!$C$4:$C$5003="Bill")*(Xero_Raw!$I$4:$I$5003<>"Paid")*(Xero_Raw!$A$4:$A$5003<>"")*(Xero_Raw!$D$4:$D$5003=$A73)*(($C$4-(Xero_Raw!$A$4:$A$5003+15))<=30)*Xero_Raw!$H$4:$H$5003) -> 0 | C73: =SUMPRODUCT((Vendor_Invoices_Upload!$H$4:$H$5003<>"Paid")*(Vendor_Invoices_Upload!$B$4:$B$5003<>"")*(Vendor_Invoices_Upload!$E$4:$E$5003=$A73)*(($C$4-Vendor_Invoices_Upload!$C$4:$C$5003)>=31)*(($C$4-Vendor_Invoices_Upload!$C$4:$C$5003)<=60)*Vendor_Invoices_Upload!$G$4:$G$5003)+SUMPRODUCT((Xero_Raw!$C$4:$C$5003="Bill")*(Xero_Raw!$I$4:$I$5003<>"Paid")*(Xero_Raw!$A$4:$A$5003<>"")*(Xero_Raw!$D$4:$D$5003=$A73)*(($C$4-(Xero_Raw!$A$4:$A$5003+15))>=31)*(($C$4-(Xero_Raw!$A$4:$A$5003+15))<=60)*Xero_Raw!$H$4:$H$5003) -> 0 | D73: =SUMPRODUCT((Vendor_Invoices_Upload!$H$4:$H$5003<>"Paid")*(Vendor_Invoices_Upload!$B$4:$B$5003<>"")*(Vendor_Invoices_Upload!$E$4:$E$5003=$A73)*(($C$4-Vendor_Invoices_Upload!$C$4:$C$5003)>=61)*(($C$4-Vendor_Invoices_Upload!$C$4:$C$5003)<=90)*Vendor_Invoices_Upload!$G$4:$G$5003)+SUMPRODUCT((Xero_Raw!$C$4:$C$5003="Bill")*(Xero_Raw!$I$4:$I$5003<>"Paid")*(Xero_Raw!$A$4:$A$5003<>"")*(Xero_Raw!$D$4:$D$5003=$A73)*(($C$4-(Xero_Raw!$A$4:$A$5003+15))>=61)*(($C$4-(Xero_Raw!$A$4:$A$5003+15))<=90)*Xero_Raw!$H$4:$H$5003) -> 0 | E73: =SUMPRODUCT((Vendor_Invoices_Upload!$H$4:$H$5003<>"Paid")*(Vendor_Invoices_Upload!$B$4:$B$5003<>"")*(Vendor_Invoices_Upload!$E$4:$E$5003=$A73)*(($C$4-Vendor_Invoices_Upload!$C$4:$C$5003)>=91)*Vendor_Invoices_Upload!$G$4:$G$5003)+SUMPRODUCT((Xero_Raw!$C$4:$C$5003="Bill")*(Xero_Raw!$I$4:$I$5003<>"Paid")*(Xero_Raw!$A$4:$A$5003<>"")*(Xero_Raw!$D$4:$D$5003=$A73)*(($C$4-(Xero_Raw!$A$4:$A$5003+15))>=91)*Xero_Raw!$H$4:$H$5003) -> 0 | F73: =SUM(B73:E73) -> 0
A74: Travel Expense | B74: =SUMPRODUCT((Vendor_Invoices_Upload!$H$4:$H$5003<>"Paid")*(Vendor_Invoices_Upload!$B$4:$B$5003<>"")*(Vendor_Invoices_Upload!$E$4:$E$5003=$A74)*(($C$4-Vendor_Invoices_Upload!$C$4:$C$5003)<=30)*Vendor_Invoices_Upload!$G$4:$G$5003)+SUMPRODUCT((Xero_Raw!$C$4:$C$5003="Bill")*(Xero_Raw!$I$4:$I$5003<>"Paid")*(Xero_Raw!$A$4:$A$5003<>"")*(Xero_Raw!$D$4:$D$5003=$A74)*(($C$4-(Xero_Raw!$A$4:$A$5003+15))<=30)*Xero_Raw!$H$4:$H$5003) -> 0 | C74: =SUMPRODUCT((Vendor_Invoices_Upload!$H$4:$H$5003<>"Paid")*(Vendor_Invoices_Upload!$B$4:$B$5003<>"")*(Vendor_Invoices_Upload!$E$4:$E$5003=$A74)*(($C$4-Vendor_Invoices_Upload!$C$4:$C$5003)>=31)*(($C$4-Vendor_Invoices_Upload!$C$4:$C$5003)<=60)*Vendor_Invoices_Upload!$G$4:$G$5003)+SUMPRODUCT((Xero_Raw!$C$4:$C$5003="Bill")*(Xero_Raw!$I$4:$I$5003<>"Paid")*(Xero_Raw!$A$4:$A$5003<>"")*(Xero_Raw!$D$4:$D$5003=$A74)*(($C$4-(Xero_Raw!$A$4:$A$5003+15))>=31)*(($C$4-(Xero_Raw!$A$4:$A$5003+15))<=60)*Xero_Raw!$H$4:$H$5003) -> 0 | D74: =SUMPRODUCT((Vendor_Invoices_Upload!$H$4:$H$5003<>"Paid")*(Vendor_Invoices_Upload!$B$4:$B$5003<>"")*(Vendor_Invoices_Upload!$E$4:$E$5003=$A74)*(($C$4-Vendor_Invoices_Upload!$C$4:$C$5003)>=61)*(($C$4-Vendor_Invoices_Upload!$C$4:$C$5003)<=90)*Vendor_Invoices_Upload!$G$4:$G$5003)+SUMPRODUCT((Xero_Raw!$C$4:$C$5003="Bill")*(Xero_Raw!$I$4:$I$5003<>"Paid")*(Xero_Raw!$A$4:$A$5003<>"")*(Xero_Raw!$D$4:$D$5003=$A74)*(($C$4-(Xero_Raw!$A$4:$A$5003+15))>=61)*(($C$4-(Xero_Raw!$A$4:$A$5003+15))<=90)*Xero_Raw!$H$4:$H$5003) -> 0 | E74: =SUMPRODUCT((Vendor_Invoices_Upload!$H$4:$H$5003<>"Paid")*(Vendor_Invoices_Upload!$B$4:$B$5003<>"")*(Vendor_Invoices_Upload!$E$4:$E$5003=$A74)*(($C$4-Vendor_Invoices_Upload!$C$4:$C$5003)>=91)*Vendor_Invoices_Upload!$G$4:$G$5003)+SUMPRODUCT((Xero_Raw!$C$4:$C$5003="Bill")*(Xero_Raw!$I$4:$I$5003<>"Paid")*(Xero_Raw!$A$4:$A$5003<>"")*(Xero_Raw!$D$4:$D$5003=$A74)*(($C$4-(Xero_Raw!$A$4:$A$5003+15))>=91)*Xero_Raw!$H$4:$H$5003) -> 0 | F74: =SUM(B74:E74) -> 0
A75: Consulting Fees - Development | B75: =SUMPRODUCT((Vendor_Invoices_Upload!$H$4:$H$5003<>"Paid")*(Vendor_Invoices_Upload!$B$4:$B$5003<>"")*(Vendor_Invoices_Upload!$E$4:$E$5003=$A75)*(($C$4-Vendor_Invoices_Upload!$C$4:$C$5003)<=30)*Vendor_Invoices_Upload!$G$4:$G$5003)+SUMPRODUCT((Xero_Raw!$C$4:$C$5003="Bill")*(Xero_Raw!$I$4:$I$5003<>"Paid")*(Xero_Raw!$A$4:$A$5003<>"")*(Xero_Raw!$D$4:$D$5003=$A75)*(($C$4-(Xero_Raw!$A$4:$A$5003+15))<=30)*Xero_Raw!$H$4:$H$5003) -> 0 | C75: =SUMPRODUCT((Vendor_Invoices_Upload!$H$4:$H$5003<>"Paid")*(Vendor_Invoices_Upload!$B$4:$B$5003<>"")*(Vendor_Invoices_Upload!$E$4:$E$5003=$A75)*(($C$4-Vendor_Invoices_Upload!$C$4:$C$5003)>=31)*(($C$4-Vendor_Invoices_Upload!$C$4:$C$5003)<=60)*Vendor_Invoices_Upload!$G$4:$G$5003)+SUMPRODUCT((Xero_Raw!$C$4:$C$5003="Bill")*(Xero_Raw!$I$4:$I$5003<>"Paid")*(Xero_Raw!$A$4:$A$5003<>"")*(Xero_Raw!$D$4:$D$5003=$A75)*(($C$4-(Xero_Raw!$A$4:$A$5003+15))>=31)*(($C$4-(Xero_Raw!$A$4:$A$5003+15))<=60)*Xero_Raw!$H$4:$H$5003) -> 0 | D75: =SUMPRODUCT((Vendor_Invoices_Upload!$H$4:$H$5003<>"Paid")*(Vendor_Invoices_Upload!$B$4:$B$5003<>"")*(Vendor_Invoices_Upload!$E$4:$E$5003=$A75)*(($C$4-Vendor_Invoices_Upload!$C$4:$C$5003)>=61)*(($C$4-Vendor_Invoices_Upload!$C$4:$C$5003)<=90)*Vendor_Invoices_Upload!$G$4:$G$5003)+SUMPRODUCT((Xero_Raw!$C$4:$C$5003="Bill")*(Xero_Raw!$I$4:$I$5003<>"Paid")*(Xero_Raw!$A$4:$A$5003<>"")*(Xero_Raw!$D$4:$D$5003=$A75)*(($C$4-(Xero_Raw!$A$4:$A$5003+15))>=61)*(($C$4-(Xero_Raw!$A$4:$A$5003+15))<=90)*Xero_Raw!$H$4:$H$5003) -> 0 | E75: =SUMPRODUCT((Vendor_Invoices_Upload!$H$4:$H$5003<>"Paid")*(Vendor_Invoices_Upload!$B$4:$B$5003<>"")*(Vendor_Invoices_Upload!$E$4:$E$5003=$A75)*(($C$4-Vendor_Invoices_Upload!$C$4:$C$5003)>=91)*Vendor_Invoices_Upload!$G$4:$G$5003)+SUMPRODUCT((Xero_Raw!$C$4:$C$5003="Bill")*(Xero_Raw!$I$4:$I$5003<>"Paid")*(Xero_Raw!$A$4:$A$5003<>"")*(Xero_Raw!$D$4:$D$5003=$A75)*(($C$4-(Xero_Raw!$A$4:$A$5003+15))>=91)*Xero_Raw!$H$4:$H$5003) -> 0 | F75: =SUM(B75:E75) -> 0
A76: Total AP Outstanding | B76: =SUM(B65:B75) -> 7592.14 | C76: =SUM(C65:C75) -> 4441.12 | D76: =SUM(D65:D75) -> 0 | E76: =SUM(E65:E75) -> 0 | F76: =SUM(F65:F75) -> 12033.26

Sheet Revenue_Summary
A1: REVENUE ANALYSIS — BY CATEGORY, BY MONTH (Stripe + Xero + Customer Invoice Uploads)
A2: Categories sourced from Assumptions keyword map. All figures link live via SUMIFS — replace raw data and this table updates automatically.
A4: STRIPE COLLECTIONS (Gross Amount, AED) — by Category
A5: Category | B5: Apr-2026 | C5: May-2026 | D5: Jun-2026 | E5: Total
A6: WhatsApp | B6: =SUMIFS(Stripe_Raw!$E$4:$E$5003,Stripe_Raw!$J$4:$J$5003,$A6,Stripe_Raw!$A$4:$A$5003,">="&DATE(2026,4,1),Stripe_Raw!$A$4:$A$5003,"<"&EDATE(DATE(2026,4,1),1),Stripe_Raw!$I$4:$I$5003,"Paid") -> 48947.56 | C6: =SUMIFS(Stripe_Raw!$E$4:$E$5003,Stripe_Raw!$J$4:$J$5003,$A6,Stripe_Raw!$A$4:$A$5003,">="&DATE(2026,5,1),Stripe_Raw!$A$4:$A$5003,"<"&EDATE(DATE(2026,5,1),1),Stripe_Raw!$I$4:$I$5003,"Paid") -> 17858.06 | D6: =SUMIFS(Stripe_Raw!$E$4:$E$5003,Stripe_Raw!$J$4:$J$5003,$A6,Stripe_Raw!$A$4:$A$5003,">="&DATE(2026,6,1),Stripe_Raw!$A$4:$A$5003,"<"&EDATE(DATE(2026,6,1),1),Stripe_Raw!$I$4:$I$5003,"Paid") -> 42453.24 | E6: =SUM(B6:D6) -> 109258.86
A7: Subscription | B7: =SUMIFS(Stripe_Raw!$E$4:$E$5003,Stripe_Raw!$J$4:$J$5003,$A7,Stripe_Raw!$A$4:$A$5003,">="&DATE(2026,4,1),Stripe_Raw!$A$4:$A$5003,"<"&EDATE(DATE(2026,4,1),1),Stripe_Raw!$I$4:$I$5003,"Paid") -> 20453.21 | C7: =SUMIFS(Stripe_Raw!$E$4:$E$5003,Stripe_Raw!$J$4:$J$5003,$A7,Stripe_Raw!$A$4:$A$5003,">="&DATE(2026,5,1),Stripe_Raw!$A$4:$A$5003,"<"&EDATE(DATE(2026,5,1),1),Stripe_Raw!$I$4:$I$5003,"Paid") -> 54102.76 | D7: =SUMIFS(Stripe_Raw!$E$4:$E$5003,Stripe_Raw!$J$4:$J$5003,$A7,Stripe_Raw!$A$4:$A$5003,">="&DATE(2026,6,1),Stripe_Raw!$A$4:$A$5003,"<"&EDATE(DATE(2026,6,1),1),Stripe_Raw!$I$4:$I$5003,"Paid") -> 48549.79 | E7: =SUM(B7:D7) -> 123105.76
A8: Development | B8: =SUMIFS(Stripe_Raw!$E$4:$E$5003,Stripe_Raw!$J$4:$J$5003,$A8,Stripe_Raw!$A$4:$A$5003,">="&DATE(2026,4,1),Stripe_Raw!$A$4:$A$5003,"<"&EDATE(DATE(2026,4,1),1),Stripe_Raw!$I$4:$I$5003,"Paid") -> 23058.05 | C8: =SUMIFS(Stripe_Raw!$E$4:$E$5003,Stripe_Raw!$J$4:$J$5003,$A8,Stripe_Raw!$A$4:$A$5003,">="&DATE(2026,5,1),Stripe_Raw!$A$4:$A$5003,"<"&EDATE(DATE(2026,5,1),1),Stripe_Raw!$I$4:$I$5003,"Paid") -> 50789.3 | D8: =SUMIFS(Stripe_Raw!$E$4:$E$5003,Stripe_Raw!$J$4:$J$5003,$A8,Stripe_Raw!$A$4:$A$5003,">="&DATE(2026,6,1),Stripe_Raw!$A$4:$A$5003,"<"&EDATE(DATE(2026,6,1),1),Stripe_Raw!$I$4:$I$5003,"Paid") -> 35202.12 | E8: =SUM(B8:D8) -> 109049.47
A9: Other Services | B9: =SUMIFS(Stripe_Raw!$E$4:$E$5003,Stripe_Raw!$J$4:$J$5003,$A9,Stripe_Raw!$A$4:$A$5003,">="&DATE(2026,4,1),Stripe_Raw!$A$4:$A$5003,"<"&EDATE(DATE(2026,4,1),1),Stripe_Raw!$I$4:$I$5003,"Paid") -> 14077.28 | C9: =SUMIFS(Stripe_Raw!$E$4:$E$5003,Stripe_Raw!$J$4:$J$5003,$A9,Stripe_Raw!$A$4:$A$5003,">="&DATE(2026,5,1),Stripe_Raw!$A$4:$A$5003,"<"&EDATE(DATE(2026,5,1),1),Stripe_Raw!$I$4:$I$5003,"Paid") -> 14850.09 | D9: =SUMIFS(Stripe_Raw!$E$4:$E$5003,Stripe_Raw!$J$4:$J$5003,$A9,Stripe_Raw!$A$4:$A$5003,">="&DATE(2026,6,1),Stripe_Raw!$A$4:$A$5003,"<"&EDATE(DATE(2026,6,1),1),Stripe_Raw!$I$4:$I$5003,"Paid") -> 7988.99 | E9: =SUM(B9:D9) -> 36916.36
A10: Total Stripe Revenue | B10: =SUM(B6:B9) -> 106536.1 | C10: =SUM(C6:C9) -> 137600.21 | D10: =SUM(D6:D9) -> 134194.14 | E10: =SUM(E6:E9) -> 378330.45
A12: XERO INVOICED SALES (Amount, AED) — by Category [all invoice statuses]
A13: Category | B13: Apr-2026 | C13: May-2026 | D13: Jun-2026 | E13: Total
A14: WhatsApp | B14: =SUMIFS(Xero_Raw!$H$4:$H$5003,Xero_Raw!$J$4:$J$5003,$A14,Xero_Raw!$C$4:$C$5003,"Invoice",Xero_Raw!$A$4:$A$5003,">="&DATE(2026,4,1),Xero_Raw!$A$4:$A$5003,"<"&EDATE(DATE(2026,4,1),1)) -> 59160.63 | C14: =SUMIFS(Xero_Raw!$H$4:$H$5003,Xero_Raw!$J$4:$J$5003,$A14,Xero_Raw!$C$4:$C$5003,"Invoice",Xero_Raw!$A$4:$A$5003,">="&DATE(2026,5,1),Xero_Raw!$A$4:$A$5003,"<"&EDATE(DATE(2026,5,1),1)) -> 70672.56 | D14: =SUMIFS(Xero_Raw!$H$4:$H$5003,Xero_Raw!$J$4:$J$5003,$A14,Xero_Raw!$C$4:$C$5003,"Invoice",Xero_Raw!$A$4:$A$5003,">="&DATE(2026,6,1),Xero_Raw!$A$4:$A$5003,"<"&EDATE(DATE(2026,6,1),1)) -> 83715.1 | E14: =SUM(B14:D14) -> 213548.29
A15: Subscription | B15: =SUMIFS(Xero_Raw!$H$4:$H$5003,Xero_Raw!$J$4:$J$5003,$A15,Xero_Raw!$C$4:$C$5003,"Invoice",Xero_Raw!$A$4:$A$5003,">="&DATE(2026,4,1),Xero_Raw!$A$4:$A$5003,"<"&EDATE(DATE(2026,4,1),1)) -> 83923.58 | C15: =SUMIFS(Xero_Raw!$H$4:$H$5003,Xero_Raw!$J$4:$J$5003,$A15,Xero_Raw!$C$4:$C$5003,"Invoice",Xero_Raw!$A$4:$A$5003,">="&DATE(2026,5,1),Xero_Raw!$A$4:$A$5003,"<"&EDATE(DATE(2026,5,1),1)) -> 42402.31 | D15: =SUMIFS(Xero_Raw!$H$4:$H$5003,Xero_Raw!$J$4:$J$5003,$A15,Xero_Raw!$C$4:$C$5003,"Invoice",Xero_Raw!$A$4:$A$5003,">="&DATE(2026,6,1),Xero_Raw!$A$4:$A$5003,"<"&EDATE(DATE(2026,6,1),1)) -> 41874.83 | E15: =SUM(B15:D15) -> 168200.72
A16: Development | B16: =SUMIFS(Xero_Raw!$H$4:$H$5003,Xero_Raw!$J$4:$J$5003,$A16,Xero_Raw!$C$4:$C$5003,"Invoice",Xero_Raw!$A$4:$A$5003,">="&DATE(2026,4,1),Xero_Raw!$A$4:$A$5003,"<"&EDATE(DATE(2026,4,1),1)) -> 21609.38 | C16: =SUMIFS(Xero_Raw!$H$4:$H$5003,Xero_Raw!$J$4:$J$5003,$A16,Xero_Raw!$C$4:$C$5003,"Invoice",Xero_Raw!$A$4:$A$5003,">="&DATE(2026,5,1),Xero_Raw!$A$4:$A$5003,"<"&EDATE(DATE(2026,5,1),1)) -> 47679.08 | D16: =SUMIFS(Xero_Raw!$H$4:$H$5003,Xero_Raw!$J$4:$J$5003,$A16,Xero_Raw!$C$4:$C$5003,"Invoice",Xero_Raw!$A$4:$A$5003,">="&DATE(2026,6,1),Xero_Raw!$A$4:$A$5003,"<"&EDATE(DATE(2026,6,1),1)) -> 96009.58 | E16: =SUM(B16:D16) -> 165298.04
A17: Other Services | B17: =SUMIFS(Xero_Raw!$H$4:$H$5003,Xero_Raw!$J$4:$J$5003,$A17,Xero_Raw!$C$4:$C$5003,"Invoice",Xero_Raw!$A$4:$A$5003,">="&DATE(2026,4,1),Xero_Raw!$A$4:$A$5003,"<"&EDATE(DATE(2026,4,1),1)) -> 0 | C17: =SUMIFS(Xero_Raw!$H$4:$H$5003,Xero_Raw!$J$4:$J$5003,$A17,Xero_Raw!$C$4:$C$5003,"Invoice",Xero_Raw!$A$4:$A$5003,">="&DATE(2026,5,1),Xero_Raw!$A$4:$A$5003,"<"&EDATE(DATE(2026,5,1),1)) -> 0 | D17: =SUMIFS(Xero_Raw!$H$4:$H$5003,Xero_Raw!$J$4:$J$5003,$A17,Xero_Raw!$C$4:$C$5003,"Invoice",Xero_Raw!$A$4:$A$5003,">="&DATE(2026,6,1),Xero_Raw!$A$4:$A$5003,"<"&EDATE(DATE(2026,6,1),1)) -> 0 | E17: =SUM(B17:D17) -> 0
A18: Total Xero Invoiced Sales | B18: =SUM(B14:B17) -> 164693.59 | C18: =SUM(C14:C17) -> 160753.95 | D18: =SUM(D14:D17) -> 221599.51 | E18: =SUM(E14:E17) -> 547047.05
A20: CUSTOMER INVOICE UPLOADS (Amount, AED) — by Category [all statuses]
A21: Category | B21: Apr-2026 | C21: May-2026 | D21: Jun-2026 | E21: Total
A22: WhatsApp | B22: =SUMIFS(Customer_Invoices_Upload!$H$4:$H$5003,Customer_Invoices_Upload!$J$4:$J$5003,$A22,Customer_Invoices_Upload!$B$4:$B$5003,">="&DATE(2026,4,1),Customer_Invoices_Upload!$B$4:$B$5003,"<"&EDATE(DATE(2026,4,1),1)) -> 34761.98 | C22: =SUMIFS(Customer_Invoices_Upload!$H$4:$H$5003,Customer_Invoices_Upload!$J$4:$J$5003,$A22,Customer_Invoices_Upload!$B$4:$B$5003,">="&DATE(2026,5,1),Customer_Invoices_Upload!$B$4:$B$5003,"<"&EDATE(DATE(2026,5,1),1)) -> 11937.43 | D22: =SUMIFS(Customer_Invoices_Upload!$H$4:$H$5003,Customer_Invoices_Upload!$J$4:$J$5003,$A22,Customer_Invoices_Upload!$B$4:$B$5003,">="&DATE(2026,6,1),Customer_Invoices_Upload!$B$4:$B$5003,"<"&EDATE(DATE(2026,6,1),1)) -> 2303.99 | E22: =SUM(B22:D22) -> 49003.4
A23: Subscription | B23: =SUMIFS(Customer_Invoices_Upload!$H$4:$H$5003,Customer_Invoices_Upload!$J$4:$J$5003,$A23,Customer_Invoices_Upload!$B$4:$B$5003,">="&DATE(2026,4,1),Customer_Invoices_Upload!$B$4:$B$5003,"<"&EDATE(DATE(2026,4,1),1)) -> 1679.78 | C23: =SUMIFS(Customer_Invoices_Upload!$H$4:$H$5003,Customer_Invoices_Upload!$J$4:$J$5003,$A23,Customer_Invoices_Upload!$B$4:$B$5003,">="&DATE(2026,5,1),Customer_Invoices_Upload!$B$4:$B$5003,"<"&EDATE(DATE(2026,5,1),1)) -> 13175.39 | D23: =SUMIFS(Customer_Invoices_Upload!$H$4:$H$5003,Customer_Invoices_Upload!$J$4:$J$5003,$A23,Customer_Invoices_Upload!$B$4:$B$5003,">="&DATE(2026,6,1),Customer_Invoices_Upload!$B$4:$B$5003,"<"&EDATE(DATE(2026,6,1),1)) -> 21404.62 | E23: =SUM(B23:D23) -> 36259.79
A24: Development | B24: =SUMIFS(Customer_Invoices_Upload!$H$4:$H$5003,Customer_Invoices_Upload!$J$4:$J$5003,$A24,Customer_Invoices_Upload!$B$4:$B$5003,">="&DATE(2026,4,1),Customer_Invoices_Upload!$B$4:$B$5003,"<"&EDATE(DATE(2026,4,1),1)) -> 0 | C24: =SUMIFS(Customer_Invoices_Upload!$H$4:$H$5003,Customer_Invoices_Upload!$J$4:$J$5003,$A24,Customer_Invoices_Upload!$B$4:$B$5003,">="&DATE(2026,5,1),Customer_Invoices_Upload!$B$4:$B$5003,"<"&EDATE(DATE(2026,5,1),1)) -> 39206.32 | D24: =SUMIFS(Customer_Invoices_Upload!$H$4:$H$5003,Customer_Invoices_Upload!$J$4:$J$5003,$A24,Customer_Invoices_Upload!$B$4:$B$5003,">="&DATE(2026,6,1),Customer_Invoices_Upload!$B$4:$B$5003,"<"&EDATE(DATE(2026,6,1),1)) -> 48039.62 | E24: =SUM(B24:D24) -> 87245.94
A25: Other Services | B25: =SUMIFS(Customer_Invoices_Upload!$H$4:$H$5003,Customer_Invoices_Upload!$J$4:$J$5003,$A25,Customer_Invoices_Upload!$B$4:$B$5003,">="&DATE(2026,4,1),Customer_Invoices_Upload!$B$4:$B$5003,"<"&EDATE(DATE(2026,4,1),1)) -> 0 | C25: =SUMIFS(Customer_Invoices_Upload!$H$4:$H$5003,Customer_Invoices_Upload!$J$4:$J$5003,$A25,Customer_Invoices_Upload!$B$4:$B$5003,">="&DATE(2026,5,1),Customer_Invoices_Upload!$B$4:$B$5003,"<"&EDATE(DATE(2026,5,1),1)) -> 0 | D25: =SUMIFS(Customer_Invoices_Upload!$H$4:$H$5003,Customer_Invoices_Upload!$J$4:$J$5003,$A25,Customer_Invoices_Upload!$B$4:$B$5003,">="&DATE(2026,6,1),Customer_Invoices_Upload!$B$4:$B$5003,"<"&EDATE(DATE(2026,6,1),1)) -> 0 | E25: =SUM(B25:D25) -> 0
A26: Total Customer Invoice Uploads | B26: =SUM(B22:B25) -> 36441.76 | C26: =SUM(C22:C25) -> 64319.14 | D26: =SUM(D22:D25) -> 71748.23 | E26: =SUM(E22:E25) -> 172509.13
A28: BLENDED TOTAL REVENUE BY CATEGORY (Stripe + Xero + Customer Invoice Uploads)
A29: Category | B29: Total Revenue (AED) | C29: % of Total
A30: WhatsApp | B30: =E6+E14+E22 -> 371810.55 | C30: =IFERROR(B30/B$34,0) -> 0.33866024
A31: Subscription | B31: =E7+E15+E23 -> 327566.27 | C31: =IFERROR(B31/B$34,0) -> 0.29836074
A32: Development | B32: =E8+E16+E24 -> 361593.45 | C32: =IFERROR(B32/B$34,0) -> 0.32935409
A33: Other Services | B33: =E9+E17+E25 -> 36916.36 | C33: =IFERROR(B33/B$34,0) -> 0.033624929
A34: Grand Total | B34: =SUM(B30:B33) -> 1097886.6

Sheet Expense_Summary
A1: EXPENSE ANALYSIS — XERO BILLS + META AD SPEND + CREDIT CARD + VENDOR INVOICE UPLOADS
A2: Meta uses Gross Amount (discount added back). Credit Card and Vendor Invoice Uploads are additive sources — do not double-enter the same expense in Xero_Raw. All figures link live via SUMIFS.
A4: XERO BILLS (Operating Expenses, AED) — by Account
A5: Expense Account | B5: Apr-2026 | C5: May-2026 | D5: Jun-2026 | E5: Total
A6: Salary - General & Administration | B6: =SUMIFS(Xero_Raw!$H$4:$H$5003,Xero_Raw!$D$4:$D$5003,$A6,Xero_Raw!$C$4:$C$5003,"Bill",Xero_Raw!$A$4:$A$5003,">="&DATE(2026,4,1),Xero_Raw!$A$4:$A$5003,"<"&EDATE(DATE(2026,4,1),1)) -> 20296.54 | C6: =SUMIFS(Xero_Raw!$H$4:$H$5003,Xero_Raw!$D$4:$D$5003,$A6,Xero_Raw!$C$4:$C$5003,"Bill",Xero_Raw!$A$4:$A$5003,">="&DATE(2026,5,1),Xero_Raw!$A$4:$A$5003,"<"&EDATE(DATE(2026,5,1),1)) -> 0 | D6: =SUMIFS(Xero_Raw!$H$4:$H$5003,Xero_Raw!$D$4:$D$5003,$A6,Xero_Raw!$C$4:$C$5003,"Bill",Xero_Raw!$A$4:$A$5003,">="&DATE(2026,6,1),Xero_Raw!$A$4:$A$5003,"<"&EDATE(DATE(2026,6,1),1)) -> 16039.97 | E6: =SUM(B6:D6) -> 36336.51
A7: Office Rent | B7: =SUMIFS(Xero_Raw!$H$4:$H$5003,Xero_Raw!$D$4:$D$5003,$A7,Xero_Raw!$C$4:$C$5003,"Bill",Xero_Raw!$A$4:$A$5003,">="&DATE(2026,4,1),Xero_Raw!$A$4:$A$5003,"<"&EDATE(DATE(2026,4,1),1)) -> 10457.14 | C7: =SUMIFS(Xero_Raw!$H$4:$H$5003,Xero_Raw!$D$4:$D$5003,$A7,Xero_Raw!$C$4:$C$5003,"Bill",Xero_Raw!$A$4:$A$5003,">="&DATE(2026,5,1),Xero_Raw!$A$4:$A$5003,"<"&EDATE(DATE(2026,5,1),1)) -> 28243.45 | D7: =SUMIFS(Xero_Raw!$H$4:$H$5003,Xero_Raw!$D$4:$D$5003,$A7,Xero_Raw!$C$4:$C$5003,"Bill",Xero_Raw!$A$4:$A$5003,">="&DATE(2026,6,1),Xero_Raw!$A$4:$A$5003,"<"&EDATE(DATE(2026,6,1),1)) -> 35830.02 | E7: =SUM(B7:D7) -> 74530.61
A8: SaaS & Software Subscriptions | B8: =SUMIFS(Xero_Raw!$H$4:$H$5003,Xero_Raw!$D$4:$D$5003,$A8,Xero_Raw!$C$4:$C$5003,"Bill",Xero_Raw!$A$4:$A$5003,">="&DATE(2026,4,1),Xero_Raw!$A$4:$A$5003,"<"&EDATE(DATE(2026,4,1),1)) -> 0 | C8: =SUMIFS(Xero_Raw!$H$4:$H$5003,Xero_Raw!$D$4:$D$5003,$A8,Xero_Raw!$C$4:$C$5003,"Bill",Xero_Raw!$A$4:$A$5003,">="&DATE(2026,5,1),Xero_Raw!$A$4:$A$5003,"<"&EDATE(DATE(2026,5,1),1)) -> 0 | D8: =SUMIFS(Xero_Raw!$H$4:$H$5003,Xero_Raw!$D$4:$D$5003,$A8,Xero_Raw!$C$4:$C$5003,"Bill",Xero_Raw!$A$4:$A$5003,">="&DATE(2026,6,1),Xero_Raw!$A$4:$A$5003,"<"&EDATE(DATE(2026,6,1),1)) -> 586.87 | E8: =SUM(B8:D8) -> 586.87
A9: Trade License Fee | B9: =SUMIFS(Xero_Raw!$H$4:$H$5003,Xero_Raw!$D$4:$D$5003,$A9,Xero_Raw!$C$4:$C$5003,"Bill",Xero_Raw!$A$4:$A$5003,">="&DATE(2026,4,1),Xero_Raw!$A$4:$A$5003,"<"&EDATE(DATE(2026,4,1),1)) -> 21683.93 | C9: =SUMIFS(Xero_Raw!$H$4:$H$5003,Xero_Raw!$D$4:$D$5003,$A9,Xero_Raw!$C$4:$C$5003,"Bill",Xero_Raw!$A$4:$A$5003,">="&DATE(2026,5,1),Xero_Raw!$A$4:$A$5003,"<"&EDATE(DATE(2026,5,1),1)) -> 14799.97 | D9: =SUMIFS(Xero_Raw!$H$4:$H$5003,Xero_Raw!$D$4:$D$5003,$A9,Xero_Raw!$C$4:$C$5003,"Bill",Xero_Raw!$A$4:$A$5003,">="&DATE(2026,6,1),Xero_Raw!$A$4:$A$5003,"<"&EDATE(DATE(2026,6,1),1)) -> 0 | E9: =SUM(B9:D9) -> 36483.9
A10: Travel Expense | B10: =SUMIFS(Xero_Raw!$H$4:$H$5003,Xero_Raw!$D$4:$D$5003,$A10,Xero_Raw!$C$4:$C$5003,"Bill",Xero_Raw!$A$4:$A$5003,">="&DATE(2026,4,1),Xero_Raw!$A$4:$A$5003,"<"&EDATE(DATE(2026,4,1),1)) -> 25979.82 | C10: =SUMIFS(Xero_Raw!$H$4:$H$5003,Xero_Raw!$D$4:$D$5003,$A10,Xero_Raw!$C$4:$C$5003,"Bill",Xero_Raw!$A$4:$A$5003,">="&DATE(2026,5,1),Xero_Raw!$A$4:$A$5003,"<"&EDATE(DATE(2026,5,1),1)) -> 23400.3 | D10: =SUMIFS(Xero_Raw!$H$4:$H$5003,Xero_Raw!$D$4:$D$5003,$A10,Xero_Raw!$C$4:$C$5003,"Bill",Xero_Raw!$A$4:$A$5003,">="&DATE(2026,6,1),Xero_Raw!$A$4:$A$5003,"<"&EDATE(DATE(2026,6,1),1)) -> 6652.47 | E10: =SUM(B10:D10) -> 56032.59
A11: Consulting Fees - Development | B11: =SUMIFS(Xero_Raw!$H$4:$H$5003,Xero_Raw!$D$4:$D$5003,$A11,Xero_Raw!$C$4:$C$5003,"Bill",Xero_Raw!$A$4:$A$5003,">="&DATE(2026,4,1),Xero_Raw!$A$4:$A$5003,"<"&EDATE(DATE(2026,4,1),1)) -> 0 | C11: =SUMIFS(Xero_Raw!$H$4:$H$5003,Xero_Raw!$D$4:$D$5003,$A11,Xero_Raw!$C$4:$C$5003,"Bill",Xero_Raw!$A$4:$A$5003,">="&DATE(2026,5,1),Xero_Raw!$A$4:$A$5003,"<"&EDATE(DATE(2026,5,1),1)) -> 7849.93 | D11: =SUMIFS(Xero_Raw!$H$4:$H$5003,Xero_Raw!$D$4:$D$5003,$A11,Xero_Raw!$C$4:$C$5003,"Bill",Xero_Raw!$A$4:$A$5003,">="&DATE(2026,6,1),Xero_Raw!$A$4:$A$5003,"<"&EDATE(DATE(2026,6,1),1)) -> 0 | E11: =SUM(B11:D11) -> 7849.93
A12: Total Xero Bills | B12: =SUM(B6:B11) -> 78417.43 | C12: =SUM(C6:C11) -> 74293.65 | D12: =SUM(D6:D11) -> 59109.33 | E12: =SUM(E6:E11) -> 211820.41
A14: META AD SPEND (Gross AED, discount added back) — by Customer
A15: Customer | B15: Apr-2026 | C15: May-2026 | D15: Jun-2026 | E15: Total
A16: Al Fardan Exchange - Sole Proprietorship L.L.C | B16: =SUMIFS(Meta_Invoices!$E$5012:$E$5029,Meta_Invoices!$A$5012:$A$5029,$A16,Meta_Invoices!$B$5012:$B$5029,"Apr-2026") -> 6169.34 | C16: =SUMIFS(Meta_Invoices!$E$5012:$E$5029,Meta_Invoices!$A$5012:$A$5029,$A16,Meta_Invoices!$B$5012:$B$5029,"May-2026") -> 4597.89 | D16: =SUMIFS(Meta_Invoices!$E$5012:$E$5029,Meta_Invoices!$A$5012:$A$5029,$A16,Meta_Invoices!$B$5012:$B$5029,"Jun-2026") -> 1035.81 | E16: =SUM(B16:D16) -> 11803.04
A17: United Homeware Company (Nice) | B17: =SUMIFS(Meta_Invoices!$E$5012:$E$5029,Meta_Invoices!$A$5012:$A$5029,$A17,Meta_Invoices!$B$5012:$B$5029,"Apr-2026") -> 6182.06 | C17: =SUMIFS(Meta_Invoices!$E$5012:$E$5029,Meta_Invoices!$A$5012:$A$5029,$A17,Meta_Invoices!$B$5012:$B$5029,"May-2026") -> 2281.89 | D17: =SUMIFS(Meta_Invoices!$E$5012:$E$5029,Meta_Invoices!$A$5012:$A$5029,$A17,Meta_Invoices!$B$5012:$B$5029,"Jun-2026") -> 7398.52 | E17: =SUM(B17:D17) -> 15862.47
A18: Growth X Ventures LLC | B18: =SUMIFS(Meta_Invoices!$E$5012:$E$5029,Meta_Invoices!$A$5012:$A$5029,$A18,Meta_Invoices!$B$5012:$B$5029,"Apr-2026") -> 2756.32 | C18: =SUMIFS(Meta_Invoices!$E$5012:$E$5029,Meta_Invoices!$A$5012:$A$5029,$A18,Meta_Invoices!$B$5012:$B$5029,"May-2026") -> 3575.87 | D18: =SUMIFS(Meta_Invoices!$E$5012:$E$5029,Meta_Invoices!$A$5012:$A$5029,$A18,Meta_Invoices!$B$5012:$B$5029,"Jun-2026") -> 2191.35 | E18: =SUM(B18:D18) -> 8523.54
A19: I Farmer Pte Ltd | B19: =SUMIFS(Meta_Invoices!$E$5012:$E$5029,Meta_Invoices!$A$5012:$A$5029,$A19,Meta_Invoices!$B$5012:$B$5029,"Apr-2026") -> 2568.24 | C19: =SUMIFS(Meta_Invoices!$E$5012:$E$5029,Meta_Invoices!$A$5012:$A$5029,$A19,Meta_Invoices!$B$5012:$B$5029,"May-2026") -> 3582.31 | D19: =SUMIFS(Meta_Invoices!$E$5012:$E$5029,Meta_Invoices!$A$5012:$A$5029,$A19,Meta_Invoices!$B$5012:$B$5029,"Jun-2026") -> 990.96 | E19: =SUM(B19:D19) -> 7141.51
A20: Misfit Technologies Pte Ltd | B20: =SUMIFS(Meta_Invoices!$E$5012:$E$5029,Meta_Invoices!$A$5012:$A$5029,$A20,Meta_Invoices!$B$5012:$B$5029,"Apr-2026") -> 2501.04 | C20: =SUMIFS(Meta_Invoices!$E$5012:$E$5029,Meta_Invoices!$A$5012:$A$5029,$A20,Meta_Invoices!$B$5012:$B$5029,"May-2026") -> 7625.47 | D20: =SUMIFS(Meta_Invoices!$E$5012:$E$5029,Meta_Invoices!$A$5012:$A$5029,$A20,Meta_Invoices!$B$5012:$B$5029,"Jun-2026") -> 2080.91 | E20: =SUM(B20:D20) -> 12207.42
A21: Nishat Linen UAE | B21: =SUMIFS(Meta_Invoices!$E$5012:$E$5029,Meta_Invoices!$A$5012:$A$5029,$A21,Meta_Invoices!$B$5012:$B$5029,"Apr-2026") -> 3596.58 | C21: =SUMIFS(Meta_Invoices!$E$5012:$E$5029,Meta_Invoices!$A$5012:$A$5029,$A21,Meta_Invoices!$B$5012:$B$5029,"May-2026") -> 3583.34 | D21: =SUMIFS(Meta_Invoices!$E$5012:$E$5029,Meta_Invoices!$A$5012:$A$5029,$A21,Meta_Invoices!$B$5012:$B$5029,"Jun-2026") -> 2729.9 | E21: =SUM(B21:D21) -> 9909.82
A22: Total Meta Ad Spend | B22: =SUM(B16:B21) -> 23773.58 | C22: =SUM(C16:C21) -> 25246.77 | D22: =SUM(D16:D21) -> 16427.45 | E22: =SUM(E16:E21) -> 65447.8
A24: CREDIT CARD SPEND (AED) — by Category
A25: Category | B25: Apr-2026 | C25: May-2026 | D25: Jun-2026 | E25: Total
A26: WhatsApp | B26: =SUMIFS(Credit_Card_Upload!$F$4:$F$5003,Credit_Card_Upload!$G$4:$G$5003,$A26,Credit_Card_Upload!$C$4:$C$5003,">="&DATE(2026,4,1),Credit_Card_Upload!$C$4:$C$5003,"<"&EDATE(DATE(2026,4,1),1)) -> 0 | C26: =SUMIFS(Credit_Card_Upload!$F$4:$F$5003,Credit_Card_Upload!$G$4:$G$5003,$A26,Credit_Card_Upload!$C$4:$C$5003,">="&DATE(2026,5,1),Credit_Card_Upload!$C$4:$C$5003,"<"&EDATE(DATE(2026,5,1),1)) -> 5726.01 | D26: =SUMIFS(Credit_Card_Upload!$F$4:$F$5003,Credit_Card_Upload!$G$4:$G$5003,$A26,Credit_Card_Upload!$C$4:$C$5003,">="&DATE(2026,6,1),Credit_Card_Upload!$C$4:$C$5003,"<"&EDATE(DATE(2026,6,1),1)) -> 0 | E26: =SUM(B26:D26) -> 5726.01
A27: Subscription | B27: =SUMIFS(Credit_Card_Upload!$F$4:$F$5003,Credit_Card_Upload!$G$4:$G$5003,$A27,Credit_Card_Upload!$C$4:$C$5003,">="&DATE(2026,4,1),Credit_Card_Upload!$C$4:$C$5003,"<"&EDATE(DATE(2026,4,1),1)) -> 4200.66 | C27: =SUMIFS(Credit_Card_Upload!$F$4:$F$5003,Credit_Card_Upload!$G$4:$G$5003,$A27,Credit_Card_Upload!$C$4:$C$5003,">="&DATE(2026,5,1),Credit_Card_Upload!$C$4:$C$5003,"<"&EDATE(DATE(2026,5,1),1)) -> 2799.31 | D27: =SUMIFS(Credit_Card_Upload!$F$4:$F$5003,Credit_Card_Upload!$G$4:$G$5003,$A27,Credit_Card_Upload!$C$4:$C$5003,">="&DATE(2026,6,1),Credit_Card_Upload!$C$4:$C$5003,"<"&EDATE(DATE(2026,6,1),1)) -> 2497.9 | E27: =SUM(B27:D27) -> 9497.87
A28: Development | B28: =SUMIFS(Credit_Card_Upload!$F$4:$F$5003,Credit_Card_Upload!$G$4:$G$5003,$A28,Credit_Card_Upload!$C$4:$C$5003,">="&DATE(2026,4,1),Credit_Card_Upload!$C$4:$C$5003,"<"&EDATE(DATE(2026,4,1),1)) -> 0 | C28: =SUMIFS(Credit_Card_Upload!$F$4:$F$5003,Credit_Card_Upload!$G$4:$G$5003,$A28,Credit_Card_Upload!$C$4:$C$5003,">="&DATE(2026,5,1),Credit_Card_Upload!$C$4:$C$5003,"<"&EDATE(DATE(2026,5,1),1)) -> 9257.15 | D28: =SUMIFS(Credit_Card_Upload!$F$4:$F$5003,Credit_Card_Upload!$G$4:$G$5003,$A28,Credit_Card_Upload!$C$4:$C$5003,">="&DATE(2026,6,1),Credit_Card_Upload!$C$4:$C$5003,"<"&EDATE(DATE(2026,6,1),1)) -> 2872.69 | E28: =SUM(B28:D28) -> 12129.84
A29: Other Services | B29: =SUMIFS(Credit_Card_Upload!$F$4:$F$5003,Credit_Card_Upload!$G$4:$G$5003,$A29,Credit_Card_Upload!$C$4:$C$5003,">="&DATE(2026,4,1),Credit_Card_Upload!$C$4:$C$5003,"<"&EDATE(DATE(2026,4,1),1)) -> 8835.16 | C29: =SUMIFS(Credit_Card_Upload!$F$4:$F$5003,Credit_Card_Upload!$G$4:$G$5003,$A29,Credit_Card_Upload!$C$4:$C$5003,">="&DATE(2026,5,1),Credit_Card_Upload!$C$4:$C$5003,"<"&EDATE(DATE(2026,5,1),1)) -> 2849.57 | D29: =SUMIFS(Credit_Card_Upload!$F$4:$F$5003,Credit_Card_Upload!$G$4:$G$5003,$A29,Credit_Card_Upload!$C$4:$C$5003,">="&DATE(2026,6,1),Credit_Card_Upload!$C$4:$C$5003,"<"&EDATE(DATE(2026,6,1),1)) -> 12554.37 | E29: =SUM(B29:D29) -> 24239.1
A30: Total Credit Card Spend | B30: =SUM(B26:B29) -> 13035.82 | C30: =SUM(C26:C29) -> 20632.04 | D30: =SUM(D26:D29) -> 17924.96 | E30: =SUM(E26:E29) -> 51592.82
A32: VENDOR INVOICE UPLOADS (AED) — by Category
A33: Category | B33: Apr-2026 | C33: May-2026 | D33: Jun-2026 | E33: Total
A34: WhatsApp | B34: =SUMIFS(Vendor_Invoices_Upload!$G$4:$G$5003,Vendor_Invoices_Upload!$I$4:$I$5003,$A34,Vendor_Invoices_Upload!$B$4:$B$5003,">="&DATE(2026,4,1),Vendor_Invoices_Upload!$B$4:$B$5003,"<"&EDATE(DATE(2026,4,1),1)) -> 11930.78 | C34: =SUMIFS(Vendor_Invoices_Upload!$G$4:$G$5003,Vendor_Invoices_Upload!$I$4:$I$5003,$A34,Vendor_Invoices_Upload!$B$4:$B$5003,">="&DATE(2026,5,1),Vendor_Invoices_Upload!$B$4:$B$5003,"<"&EDATE(DATE(2026,5,1),1)) -> 0 | D34: =SUMIFS(Vendor_Invoices_Upload!$G$4:$G$5003,Vendor_Invoices_Upload!$I$4:$I$5003,$A34,Vendor_Invoices_Upload!$B$4:$B$5003,">="&DATE(2026,6,1),Vendor_Invoices_Upload!$B$4:$B$5003,"<"&EDATE(DATE(2026,6,1),1)) -> 5469.6 | E34: =SUM(B34:D34) -> 17400.38
A35: Subscription | B35: =SUMIFS(Vendor_Invoices_Upload!$G$4:$G$5003,Vendor_Invoices_Upload!$I$4:$I$5003,$A35,Vendor_Invoices_Upload!$B$4:$B$5003,">="&DATE(2026,4,1),Vendor_Invoices_Upload!$B$4:$B$5003,"<"&EDATE(DATE(2026,4,1),1)) -> 0 | C35: =SUMIFS(Vendor_Invoices_Upload!$G$4:$G$5003,Vendor_Invoices_Upload!$I$4:$I$5003,$A35,Vendor_Invoices_Upload!$B$4:$B$5003,">="&DATE(2026,5,1),Vendor_Invoices_Upload!$B$4:$B$5003,"<"&EDATE(DATE(2026,5,1),1)) -> 0 | D35: =SUMIFS(Vendor_Invoices_Upload!$G$4:$G$5003,Vendor_Invoices_Upload!$I$4:$I$5003,$A35,Vendor_Invoices_Upload!$B$4:$B$5003,">="&DATE(2026,6,1),Vendor_Invoices_Upload!$B$4:$B$5003,"<"&EDATE(DATE(2026,6,1),1)) -> 0 | E35: =SUM(B35:D35) -> 0
A36: Development | B36: =SUMIFS(Vendor_Invoices_Upload!$G$4:$G$5003,Vendor_Invoices_Upload!$I$4:$I$5003,$A36,Vendor_Invoices_Upload!$B$4:$B$5003,">="&DATE(2026,4,1),Vendor_Invoices_Upload!$B$4:$B$5003,"<"&EDATE(DATE(2026,4,1),1)) -> 0 | C36: =SUMIFS(Vendor_Invoices_Upload!$G$4:$G$5003,Vendor_Invoices_Upload!$I$4:$I$5003,$A36,Vendor_Invoices_Upload!$B$4:$B$5003,">="&DATE(2026,5,1),Vendor_Invoices_Upload!$B$4:$B$5003,"<"&EDATE(DATE(2026,5,1),1)) -> 0 | D36: =SUMIFS(Vendor_Invoices_Upload!$G$4:$G$5003,Vendor_Invoices_Upload!$I$4:$I$5003,$A36,Vendor_Invoices_Upload!$B$4:$B$5003,">="&DATE(2026,6,1),Vendor_Invoices_Upload!$B$4:$B$5003,"<"&EDATE(DATE(2026,6,1),1)) -> 0 | E36: =SUM(B36:D36) -> 0
A37: Other Services | B37: =SUMIFS(Vendor_Invoices_Upload!$G$4:$G$5003,Vendor_Invoices_Upload!$I$4:$I$5003,$A37,Vendor_Invoices_Upload!$B$4:$B$5003,">="&DATE(2026,4,1),Vendor_Invoices_Upload!$B$4:$B$5003,"<"&EDATE(DATE(2026,4,1),1)) -> 7510.26 | C37: =SUMIFS(Vendor_Invoices_Upload!$G$4:$G$5003,Vendor_Invoices_Upload!$I$4:$I$5003,$A37,Vendor_Invoices_Upload!$B$4:$B$5003,">="&DATE(2026,5,1),Vendor_Invoices_Upload!$B$4:$B$5003,"<"&EDATE(DATE(2026,5,1),1)) -> 17310.2 | D37: =SUMIFS(Vendor_Invoices_Upload!$G$4:$G$5003,Vendor_Invoices_Upload!$I$4:$I$5003,$A37,Vendor_Invoices_Upload!$B$4:$B$5003,">="&DATE(2026,6,1),Vendor_Invoices_Upload!$B$4:$B$5003,"<"&EDATE(DATE(2026,6,1),1)) -> 10493.39 | E37: =SUM(B37:D37) -> 35313.85
A38: Total Vendor Invoice Uploads | B38: =SUM(B34:B37) -> 19441.04 | C38: =SUM(C34:C37) -> 17310.2 | D38: =SUM(D34:D37) -> 15962.99 | E38: =SUM(E34:E37) -> 52714.23
A41: TOTAL OPERATING EXPENSES (Xero + Meta + Credit Card + Vendor Uploads) | B41: =B12+B22+B30+B38 -> 134667.87 | C41: =C12+C22+C30+C38 -> 137482.66 | D41: =D12+D22+D30+D38 -> 109424.73 | E41: =E12+E22+E30+E38 -> 381575.26

Sheet Receivables
A1: ACCOUNTS RECEIVABLE — AGING BY CUSTOMER & COUNTRY (Xero Invoices + Customer Invoice Uploads)
A2: Outstanding = unpaid invoices from Xero_Raw AND Customer_Invoices_Upload (additive — do not double-enter the same invoice in both). Country from Assumptions map.
B4: As-of Date: | C4: =DATE(2026,6,30) -> 46203
A6: OUTSTANDING INVOICE DETAIL — XERO_RAW (Illustrative sample rows shown — the summary totals below are computed independently across the FULL uploaded range (up to 5,000 rows), not just what is visible here.)
A7: Invoice Date | B7: Due Date | C7: Customer | D7: Country | E7: Amount (AED) | F7: Status | G7: Days Overdue | H7: Aging Bucket
A8: =IF(AND(Xero_Raw!$C$4="Invoice",AND(Xero_Raw!$I$4<>"Paid",Xero_Raw!$I$4<>"Void",Xero_Raw!$I$4<>"Draft")),Xero_Raw!$A$4,"") | B8: =IF(AND(Xero_Raw!$C$4="Invoice",AND(Xero_Raw!$I$4<>"Paid",Xero_Raw!$I$4<>"Void",Xero_Raw!$I$4<>"Draft")),Xero_Raw!$B$4,"") | C8: =IF(AND(Xero_Raw!$C$4="Invoice",AND(Xero_Raw!$I$4<>"Paid",Xero_Raw!$I$4<>"Void",Xero_Raw!$I$4<>"Draft")),Xero_Raw!$D$4,"") | D8: =IF(C8="","",IFERROR(VLOOKUP(C8,Assumptions!$G$5:$H$16,2,0),"Other")) | E8: =IF(AND(Xero_Raw!$C$4="Invoice",AND(Xero_Raw!$I$4<>"Paid",Xero_Raw!$I$4<>"Void",Xero_Raw!$I$4<>"Draft")),Xero_Raw!$H$4,"") | F8: =IF(AND(Xero_Raw!$C$4="Invoice",AND(Xero_Raw!$I$4<>"Paid",Xero_Raw!$I$4<>"Void",Xero_Raw!$I$4<>"Draft")),Xero_Raw!$I$4,"") | G8: =IF(B8="","",MAX($C$4-B8,0)) | H8: =IF(G8="","",IF(G8<=30,"0-30",IF(G8<=60,"31-60",IF(G8<=90,"61-90","90+"))))
A9: =IF(AND(Xero_Raw!$C$5="Invoice",AND(Xero_Raw!$I$5<>"Paid",Xero_Raw!$I$5<>"Void",Xero_Raw!$I$5<>"Draft")),Xero_Raw!$A$5,"") | B9: =IF(AND(Xero_Raw!$C$5="Invoice",AND(Xero_Raw!$I$5<>"Paid",Xero_Raw!$I$5<>"Void",Xero_Raw!$I$5<>"Draft")),Xero_Raw!$B$5,"") | C9: =IF(AND(Xero_Raw!$C$5="Invoice",AND(Xero_Raw!$I$5<>"Paid",Xero_Raw!$I$5<>"Void",Xero_Raw!$I$5<>"Draft")),Xero_Raw!$D$5,"") | D9: =IF(C9="","",IFERROR(VLOOKUP(C9,Assumptions!$G$5:$H$16,2,0),"Other")) | E9: =IF(AND(Xero_Raw!$C$5="Invoice",AND(Xero_Raw!$I$5<>"Paid",Xero_Raw!$I$5<>"Void",Xero_Raw!$I$5<>"Draft")),Xero_Raw!$H$5,"") | F9: =IF(AND(Xero_Raw!$C$5="Invoice",AND(Xero_Raw!$I$5<>"Paid",Xero_Raw!$I$5<>"Void",Xero_Raw!$I$5<>"Draft")),Xero_Raw!$I$5,"") | G9: =IF(B9="","",MAX($C$4-B9,0)) | H9: =IF(G9="","",IF(G9<=30,"0-30",IF(G9<=60,"31-60",IF(G9<=90,"61-90","90+"))))
A10: =IF(AND(Xero_Raw!$C$6="Invoice",AND(Xero_Raw!$I$6<>"Paid",Xero_Raw!$I$6<>"Void",Xero_Raw!$I$6<>"Draft")),Xero_Raw!$A$6,"") | B10: =IF(AND(Xero_Raw!$C$6="Invoice",AND(Xero_Raw!$I$6<>"Paid",Xero_Raw!$I$6<>"Void",Xero_Raw!$I$6<>"Draft")),Xero_Raw!$B$6,"") | C10: =IF(AND(Xero_Raw!$C$6="Invoice",AND(Xero_Raw!$I$6<>"Paid",Xero_Raw!$I$6<>"Void",Xero_Raw!$I$6<>"Draft")),Xero_Raw!$D$6,"") | D10: =IF(C10="","",IFERROR(VLOOKUP(C10,Assumptions!$G$5:$H$16,2,0),"Other")) | E10: =IF(AND(Xero_Raw!$C$6="Invoice",AND(Xero_Raw!$I$6<>"Paid",Xero_Raw!$I$6<>"Void",Xero_Raw!$I$6<>"Draft")),Xero_Raw!$H$6,"") | F10: =IF(AND(Xero_Raw!$C$6="Invoice",AND(Xero_Raw!$I$6<>"Paid",Xero_Raw!$I$6<>"Void",Xero_Raw!$I$6<>"Draft")),Xero_Raw!$I$6,"") | G10: =IF(B10="","",MAX($C$4-B10,0)) | H10: =IF(G10="","",IF(G10<=30,"0-30",IF(G10<=60,"31-60",IF(G10<=90,"61-90","90+"))))
A11: =IF(AND(Xero_Raw!$C$7="Invoice",AND(Xero_Raw!$I$7<>"Paid",Xero_Raw!$I$7<>"Void",Xero_Raw!$I$7<>"Draft")),Xero_Raw!$A$7,"") | B11: =IF(AND(Xero_Raw!$C$7="Invoice",AND(Xero_Raw!$I$7<>"Paid",Xero_Raw!$I$7<>"Void",Xero_Raw!$I$7<>"Draft")),Xero_Raw!$B$7,"") | C11: =IF(AND(Xero_Raw!$C$7="Invoice",AND(Xero_Raw!$I$7<>"Paid",Xero_Raw!$I$7<>"Void",Xero_Raw!$I$7<>"Draft")),Xero_Raw!$D$7,"") | D11: =IF(C11="","",IFERROR(VLOOKUP(C11,Assumptions!$G$5:$H$16,2,0),"Other")) | E11: =IF(AND(Xero_Raw!$C$7="Invoice",AND(Xero_Raw!$I$7<>"Paid",Xero_Raw!$I$7<>"Void",Xero_Raw!$I$7<>"Draft")),Xero_Raw!$H$7,"") | F11: =IF(AND(Xero_Raw!$C$7="Invoice",AND(Xero_Raw!$I$7<>"Paid",Xero_Raw!$I$7<>"Void",Xero_Raw!$I$7<>"Draft")),Xero_Raw!$I$7,"") | G11: =IF(B11="","",MAX($C$4-B11,0)) | H11: =IF(G11="","",IF(G11<=30,"0-30",IF(G11<=60,"31-60",IF(G11<=90,"61-90","90+"))))
A12: =IF(AND(Xero_Raw!$C$8="Invoice",AND(Xero_Raw!$I$8<>"Paid",Xero_Raw!$I$8<>"Void",Xero_Raw!$I$8<>"Draft")),Xero_Raw!$A$8,"") -> 46127 | B12: =IF(AND(Xero_Raw!$C$8="Invoice",AND(Xero_Raw!$I$8<>"Paid",Xero_Raw!$I$8<>"Void",Xero_Raw!$I$8<>"Draft")),Xero_Raw!$B$8,"") -> 46157 | C12: =IF(AND(Xero_Raw!$C$8="Invoice",AND(Xero_Raw!$I$8<>"Paid",Xero_Raw!$I$8<>"Void",Xero_Raw!$I$8<>"Draft")),Xero_Raw!$D$8,"") -> Misfit Technologies Pte Ltd | D12: =IF(C12="","",IFERROR(VLOOKUP(C12,Assumptions!$G$5:$H$16,2,0),"Other")) -> Singapore | E12: =IF(AND(Xero_Raw!$C$8="Invoice",AND(Xero_Raw!$I$8<>"Paid",Xero_Raw!$I$8<>"Void",Xero_Raw!$I$8<>"Draft")),Xero_Raw!$H$8,"") -> 52102.53 | F12: =IF(AND(Xero_Raw!$C$8="Invoice",AND(Xero_Raw!$I$8<>"Paid",Xero_Raw!$I$8<>"Void",Xero_Raw!$I$8<>"Draft")),Xero_Raw!$I$8,"") -> Unsent | G12: =IF(B12="","",MAX($C$4-B12,0)) -> 46 | H12: =IF(G12="","",IF(G12<=30,"0-30",IF(G12<=60,"31-60",IF(G12<=90,"61-90","90+")))) -> 31-60
A13: =IF(AND(Xero_Raw!$C$9="Invoice",AND(Xero_Raw!$I$9<>"Paid",Xero_Raw!$I$9<>"Void",Xero_Raw!$I$9<>"Draft")),Xero_Raw!$A$9,"") -> 46116 | B13: =IF(AND(Xero_Raw!$C$9="Invoice",AND(Xero_Raw!$I$9<>"Paid",Xero_Raw!$I$9<>"Void",Xero_Raw!$I$9<>"Draft")),Xero_Raw!$B$9,"") -> 46146 | C13: =IF(AND(Xero_Raw!$C$9="Invoice",AND(Xero_Raw!$I$9<>"Paid",Xero_Raw!$I$9<>"Void",Xero_Raw!$I$9<>"Draft")),Xero_Raw!$D$9,"") -> Almoudi Group Tabuk ST | D13: =IF(C13="","",IFERROR(VLOOKUP(C13,Assumptions!$G$5:$H$16,2,0),"Other")) -> Saudi Arabia | E13: =IF(AND(Xero_Raw!$C$9="Invoice",AND(Xero_Raw!$I$9<>"Paid",Xero_Raw!$I$9<>"Void",Xero_Raw!$I$9<>"Draft")),Xero_Raw!$H$9,"") -> 5515.54 | F13: =IF(AND(Xero_Raw!$C$9="Invoice",AND(Xero_Raw!$I$9<>"Paid",Xero_Raw!$I$9<>"Void",Xero_Raw!$I$9<>"Draft")),Xero_Raw!$I$9,"") -> Unsent | G13: =IF(B13="","",MAX($C$4-B13,0)) -> 57 | H13: =IF(G13="","",IF(G13<=30,"0-30",IF(G13<=60,"31-60",IF(G13<=90,"61-90","90+")))) -> 31-60
A14: =IF(AND(Xero_Raw!$C$10="Invoice",AND(Xero_Raw!$I$10<>"Paid",Xero_Raw!$I$10<>"Void",Xero_Raw!$I$10<>"Draft")),Xero_Raw!$A$10,"") | B14: =IF(AND(Xero_Raw!$C$10="Invoice",AND(Xero_Raw!$I$10<>"Paid",Xero_Raw!$I$10<>"Void",Xero_Raw!$I$10<>"Draft")),Xero_Raw!$B$10,"") | C14: =IF(AND(Xero_Raw!$C$10="Invoice",AND(Xero_Raw!$I$10<>"Paid",Xero_Raw!$I$10<>"Void",Xero_Raw!$I$10<>"Draft")),Xero_Raw!$D$10,"") | D14: =IF(C14="","",IFERROR(VLOOKUP(C14,Assumptions!$G$5:$H$16,2,0),"Other")) | E14: =IF(AND(Xero_Raw!$C$10="Invoice",AND(Xero_Raw!$I$10<>"Paid",Xero_Raw!$I$10<>"Void",Xero_Raw!$I$10<>"Draft")),Xero_Raw!$H$10,"") | F14: =IF(AND(Xero_Raw!$C$10="Invoice",AND(Xero_Raw!$I$10<>"Paid",Xero_Raw!$I$10<>"Void",Xero_Raw!$I$10<>"Draft")),Xero_Raw!$I$10,"") | G14: =IF(B14="","",MAX($C$4-B14,0)) | H14: =IF(G14="","",IF(G14<=30,"0-30",IF(G14<=60,"31-60",IF(G14<=90,"61-90","90+"))))
A15: =IF(AND(Xero_Raw!$C$11="Invoice",AND(Xero_Raw!$I$11<>"Paid",Xero_Raw!$I$11<>"Void",Xero_Raw!$I$11<>"Draft")),Xero_Raw!$A$11,"") | B15: =IF(AND(Xero_Raw!$C$11="Invoice",AND(Xero_Raw!$I$11<>"Paid",Xero_Raw!$I$11<>"Void",Xero_Raw!$I$11<>"Draft")),Xero_Raw!$B$11,"") | C15: =IF(AND(Xero_Raw!$C$11="Invoice",AND(Xero_Raw!$I$11<>"Paid",Xero_Raw!$I$11<>"Void",Xero_Raw!$I$11<>"Draft")),Xero_Raw!$D$11,"") | D15: =IF(C15="","",IFERROR(VLOOKUP(C15,Assumptions!$G$5:$H$16,2,0),"Other")) | E15: =IF(AND(Xero_Raw!$C$11="Invoice",AND(Xero_Raw!$I$11<>"Paid",Xero_Raw!$I$11<>"Void",Xero_Raw!$I$11<>"Draft")),Xero_Raw!$H$11,"") | F15: =IF(AND(Xero_Raw!$C$11="Invoice",AND(Xero_Raw!$I$11<>"Paid",Xero_Raw!$I$11<>"Void",Xero_Raw!$I$11<>"Draft")),Xero_Raw!$I$11,"") | G15: =IF(B15="","",MAX($C$4-B15,0)) | H15: =IF(G15="","",IF(G15<=30,"0-30",IF(G15<=60,"31-60",IF(G15<=90,"61-90","90+"))))
A16: =IF(AND(Xero_Raw!$C$12="Invoice",AND(Xero_Raw!$I$12<>"Paid",Xero_Raw!$I$12<>"Void",Xero_Raw!$I$12<>"Draft")),Xero_Raw!$A$12,"") | B16: =IF(AND(Xero_Raw!$C$12="Invoice",AND(Xero_Raw!$I$12<>"Paid",Xero_Raw!$I$12<>"Void",Xero_Raw!$I$12<>"Draft")),Xero_Raw!$B$12,"") | C16: =IF(AND(Xero_Raw!$C$12="Invoice",AND(Xero_Raw!$I$12<>"Paid",Xero_Raw!$I$12<>"Void",Xero_Raw!$I$12<>"Draft")),Xero_Raw!$D$12,"") | D16: =IF(C16="","",IFERROR(VLOOKUP(C16,Assumptions!$G$5:$H$16,2,0),"Other")) | E16: =IF(AND(Xero_Raw!$C$12="Invoice",AND(Xero_Raw!$I$12<>"Paid",Xero_Raw!$I$12<>"Void",Xero_Raw!$I$12<>"Draft")),Xero_Raw!$H$12,"") | F16: =IF(AND(Xero_Raw!$C$12="Invoice",AND(Xero_Raw!$I$12<>"Paid",Xero_Raw!$I$12<>"Void",Xero_Raw!$I$12<>"Draft")),Xero_Raw!$I$12,"") | G16: =IF(B16="","",MAX($C$4-B16,0)) | H16: =IF(G16="","",IF(G16<=30,"0-30",IF(G16<=60,"31-60",IF(G16<=90,"61-90","90+"))))
A17: =IF(AND(Xero_Raw!$C$13="Invoice",AND(Xero_Raw!$I$13<>"Paid",Xero_Raw!$I$13<>"Void",Xero_Raw!$I$13<>"Draft")),Xero_Raw!$A$13,"") | B17: =IF(AND(Xero_Raw!$C$13="Invoice",AND(Xero_Raw!$I$13<>"Paid",Xero_Raw!$I$13<>"Void",Xero_Raw!$I$13<>"Draft")),Xero_Raw!$B$13,"") | C17: =IF(AND(Xero_Raw!$C$13="Invoice",AND(Xero_Raw!$I$13<>"Paid",Xero_Raw!$I$13<>"Void",Xero_Raw!$I$13<>"Draft")),Xero_Raw!$D$13,"") | D17: =IF(C17="","",IFERROR(VLOOKUP(C17,Assumptions!$G$5:$H$16,2,0),"Other")) | E17: =IF(AND(Xero_Raw!$C$13="Invoice",AND(Xero_Raw!$I$13<>"Paid",Xero_Raw!$I$13<>"Void",Xero_Raw!$I$13<>"Draft")),Xero_Raw!$H$13,"") | F17: =IF(AND(Xero_Raw!$C$13="Invoice",AND(Xero_Raw!$I$13<>"Paid",Xero_Raw!$I$13<>"Void",Xero_Raw!$I$13<>"Draft")),Xero_Raw!$I$13,"") | G17: =IF(B17="","",MAX($C$4-B17,0)) | H17: =IF(G17="","",IF(G17<=30,"0-30",IF(G17<=60,"31-60",IF(G17<=90,"61-90","90+"))))
A18: =IF(AND(Xero_Raw!$C$14="Invoice",AND(Xero_Raw!$I$14<>"Paid",Xero_Raw!$I$14<>"Void",Xero_Raw!$I$14<>"Draft")),Xero_Raw!$A$14,"") | B18: =IF(AND(Xero_Raw!$C$14="Invoice",AND(Xero_Raw!$I$14<>"Paid",Xero_Raw!$I$14<>"Void",Xero_Raw!$I$14<>"Draft")),Xero_Raw!$B$14,"") | C18: =IF(AND(Xero_Raw!$C$14="Invoice",AND(Xero_Raw!$I$14<>"Paid",Xero_Raw!$I$14<>"Void",Xero_Raw!$I$14<>"Draft")),Xero_Raw!$D$14,"") | D18: =IF(C18="","",IFERROR(VLOOKUP(C18,Assumptions!$G$5:$H$16,2,0),"Other")) | E18: =IF(AND(Xero_Raw!$C$14="Invoice",AND(Xero_Raw!$I$14<>"Paid",Xero_Raw!$I$14<>"Void",Xero_Raw!$I$14<>"Draft")),Xero_Raw!$H$14,"") | F18: =IF(AND(Xero_Raw!$C$14="Invoice",AND(Xero_Raw!$I$14<>"Paid",Xero_Raw!$I$14<>"Void",Xero_Raw!$I$14<>"Draft")),Xero_Raw!$I$14,"") | G18: =IF(B18="","",MAX($C$4-B18,0)) | H18: =IF(G18="","",IF(G18<=30,"0-30",IF(G18<=60,"31-60",IF(G18<=90,"61-90","90+"))))
A19: =IF(AND(Xero_Raw!$C$15="Invoice",AND(Xero_Raw!$I$15<>"Paid",Xero_Raw!$I$15<>"Void",Xero_Raw!$I$15<>"Draft")),Xero_Raw!$A$15,"") | B19: =IF(AND(Xero_Raw!$C$15="Invoice",AND(Xero_Raw!$I$15<>"Paid",Xero_Raw!$I$15<>"Void",Xero_Raw!$I$15<>"Draft")),Xero_Raw!$B$15,"") | C19: =IF(AND(Xero_Raw!$C$15="Invoice",AND(Xero_Raw!$I$15<>"Paid",Xero_Raw!$I$15<>"Void",Xero_Raw!$I$15<>"Draft")),Xero_Raw!$D$15,"") | D19: =IF(C19="","",IFERROR(VLOOKUP(C19,Assumptions!$G$5:$H$16,2,0),"Other")) | E19: =IF(AND(Xero_Raw!$C$15="Invoice",AND(Xero_Raw!$I$15<>"Paid",Xero_Raw!$I$15<>"Void",Xero_Raw!$I$15<>"Draft")),Xero_Raw!$H$15,"") | F19: =IF(AND(Xero_Raw!$C$15="Invoice",AND(Xero_Raw!$I$15<>"Paid",Xero_Raw!$I$15<>"Void",Xero_Raw!$I$15<>"Draft")),Xero_Raw!$I$15,"") | G19: =IF(B19="","",MAX($C$4-B19,0)) | H19: =IF(G19="","",IF(G19<=30,"0-30",IF(G19<=60,"31-60",IF(G19<=90,"61-90","90+"))))
A20: =IF(AND(Xero_Raw!$C$16="Invoice",AND(Xero_Raw!$I$16<>"Paid",Xero_Raw!$I$16<>"Void",Xero_Raw!$I$16<>"Draft")),Xero_Raw!$A$16,"") | B20: =IF(AND(Xero_Raw!$C$16="Invoice",AND(Xero_Raw!$I$16<>"Paid",Xero_Raw!$I$16<>"Void",Xero_Raw!$I$16<>"Draft")),Xero_Raw!$B$16,"") | C20: =IF(AND(Xero_Raw!$C$16="Invoice",AND(Xero_Raw!$I$16<>"Paid",Xero_Raw!$I$16<>"Void",Xero_Raw!$I$16<>"Draft")),Xero_Raw!$D$16,"") | D20: =IF(C20="","",IFERROR(VLOOKUP(C20,Assumptions!$G$5:$H$16,2,0),"Other")) | E20: =IF(AND(Xero_Raw!$C$16="Invoice",AND(Xero_Raw!$I$16<>"Paid",Xero_Raw!$I$16<>"Void",Xero_Raw!$I$16<>"Draft")),Xero_Raw!$H$16,"") | F20: =IF(AND(Xero_Raw!$C$16="Invoice",AND(Xero_Raw!$I$16<>"Paid",Xero_Raw!$I$16<>"Void",Xero_Raw!$I$16<>"Draft")),Xero_Raw!$I$16,"") | G20: =IF(B20="","",MAX($C$4-B20,0)) | H20: =IF(G20="","",IF(G20<=30,"0-30",IF(G20<=60,"31-60",IF(G20<=90,"61-90","90+"))))
A21: =IF(AND(Xero_Raw!$C$17="Invoice",AND(Xero_Raw!$I$17<>"Paid",Xero_Raw!$I$17<>"Void",Xero_Raw!$I$17<>"Draft")),Xero_Raw!$A$17,"") | B21: =IF(AND(Xero_Raw!$C$17="Invoice",AND(Xero_Raw!$I$17<>"Paid",Xero_Raw!$I$17<>"Void",Xero_Raw!$I$17<>"Draft")),Xero_Raw!$B$17,"") | C21: =IF(AND(Xero_Raw!$C$17="Invoice",AND(Xero_Raw!$I$17<>"Paid",Xero_Raw!$I$17<>"Void",Xero_Raw!$I$17<>"Draft")),Xero_Raw!$D$17,"") | D21: =IF(C21="","",IFERROR(VLOOKUP(C21,Assumptions!$G$5:$H$16,2,0),"Other")) | E21: =IF(AND(Xero_Raw!$C$17="Invoice",AND(Xero_Raw!$I$17<>"Paid",Xero_Raw!$I$17<>"Void",Xero_Raw!$I$17<>"Draft")),Xero_Raw!$H$17,"") | F21: =IF(AND(Xero_Raw!$C$17="Invoice",AND(Xero_Raw!$I$17<>"Paid",Xero_Raw!$I$17<>"Void",Xero_Raw!$I$17<>"Draft")),Xero_Raw!$I$17,"") | G21: =IF(B21="","",MAX($C$4-B21,0)) | H21: =IF(G21="","",IF(G21<=30,"0-30",IF(G21<=60,"31-60",IF(G21<=90,"61-90","90+"))))
A22: =IF(AND(Xero_Raw!$C$18="Invoice",AND(Xero_Raw!$I$18<>"Paid",Xero_Raw!$I$18<>"Void",Xero_Raw!$I$18<>"Draft")),Xero_Raw!$A$18,"") -> 46156 | B22: =IF(AND(Xero_Raw!$C$18="Invoice",AND(Xero_Raw!$I$18<>"Paid",Xero_Raw!$I$18<>"Void",Xero_Raw!$I$18<>"Draft")),Xero_Raw!$B$18,"") -> 46186 | C22: =IF(AND(Xero_Raw!$C$18="Invoice",AND(Xero_Raw!$I$18<>"Paid",Xero_Raw!$I$18<>"Void",Xero_Raw!$I$18<>"Draft")),Xero_Raw!$D$18,"") -> Curahealth K.S.C.C. | D22: =IF(C22="","",IFERROR(VLOOKUP(C22,Assumptions!$G$5:$H$16,2,0),"Other")) -> Kuwait | E22: =IF(AND(Xero_Raw!$C$18="Invoice",AND(Xero_Raw!$I$18<>"Paid",Xero_Raw!$I$18<>"Void",Xero_Raw!$I$18<>"Draft")),Xero_Raw!$H$18,"") -> 42402.31 | F22: =IF(AND(Xero_Raw!$C$18="Invoice",AND(Xero_Raw!$I$18<>"Paid",Xero_Raw!$I$18<>"Void",Xero_Raw!$I$18<>"Draft")),Xero_Raw!$I$18,"") -> Awaiting Payment | G22: =IF(B22="","",MAX($C$4-B22,0)) -> 17 | H22: =IF(G22="","",IF(G22<=30,"0-30",IF(G22<=60,"31-60",IF(G22<=90,"61-90","90+")))) -> 0-30
A23: =IF(AND(Xero_Raw!$C$19="Invoice",AND(Xero_Raw!$I$19<>"Paid",Xero_Raw!$I$19<>"Void",Xero_Raw!$I$19<>"Draft")),Xero_Raw!$A$19,"") | B23: =IF(AND(Xero_Raw!$C$19="Invoice",AND(Xero_Raw!$I$19<>"Paid",Xero_Raw!$I$19<>"Void",Xero_Raw!$I$19<>"Draft")),Xero_Raw!$B$19,"") | C23: =IF(AND(Xero_Raw!$C$19="Invoice",AND(Xero_Raw!$I$19<>"Paid",Xero_Raw!$I$19<>"Void",Xero_Raw!$I$19<>"Draft")),Xero_Raw!$D$19,"") | D23: =IF(C23="","",IFERROR(VLOOKUP(C23,Assumptions!$G$5:$H$16,2,0),"Other")) | E23: =IF(AND(Xero_Raw!$C$19="Invoice",AND(Xero_Raw!$I$19<>"Paid",Xero_Raw!$I$19<>"Void",Xero_Raw!$I$19<>"Draft")),Xero_Raw!$H$19,"") | F23: =IF(AND(Xero_Raw!$C$19="Invoice",AND(Xero_Raw!$I$19<>"Paid",Xero_Raw!$I$19<>"Void",Xero_Raw!$I$19<>"Draft")),Xero_Raw!$I$19,"") | G23: =IF(B23="","",MAX($C$4-B23,0)) | H23: =IF(G23="","",IF(G23<=30,"0-30",IF(G23<=60,"31-60",IF(G23<=90,"61-90","90+"))))
A24: =IF(AND(Xero_Raw!$C$20="Invoice",AND(Xero_Raw!$I$20<>"Paid",Xero_Raw!$I$20<>"Void",Xero_Raw!$I$20<>"Draft")),Xero_Raw!$A$20,"") | B24: =IF(AND(Xero_Raw!$C$20="Invoice",AND(Xero_Raw!$I$20<>"Paid",Xero_Raw!$I$20<>"Void",Xero_Raw!$I$20<>"Draft")),Xero_Raw!$B$20,"") | C24: =IF(AND(Xero_Raw!$C$20="Invoice",AND(Xero_Raw!$I$20<>"Paid",Xero_Raw!$I$20<>"Void",Xero_Raw!$I$20<>"Draft")),Xero_Raw!$D$20,"") | D24: =IF(C24="","",IFERROR(VLOOKUP(C24,Assumptions!$G$5:$H$16,2,0),"Other")) | E24: =IF(AND(Xero_Raw!$C$20="Invoice",AND(Xero_Raw!$I$20<>"Paid",Xero_Raw!$I$20<>"Void",Xero_Raw!$I$20<>"Draft")),Xero_Raw!$H$20,"") | F24: =IF(AND(Xero_Raw!$C$20="Invoice",AND(Xero_Raw!$I$20<>"Paid",Xero_Raw!$I$20<>"Void",Xero_Raw!$I$20<>"Draft")),Xero_Raw!$I$20,"") | G24: =IF(B24="","",MAX($C$4-B24,0)) | H24: =IF(G24="","",IF(G24<=30,"0-30",IF(G24<=60,"31-60",IF(G24<=90,"61-90","90+"))))
A25: =IF(AND(Xero_Raw!$C$21="Invoice",AND(Xero_Raw!$I$21<>"Paid",Xero_Raw!$I$21<>"Void",Xero_Raw!$I$21<>"Draft")),Xero_Raw!$A$21,"") -> 46158 | B25: =IF(AND(Xero_Raw!$C$21="Invoice",AND(Xero_Raw!$I$21<>"Paid",Xero_Raw!$I$21<>"Void",Xero_Raw!$I$21<>"Draft")),Xero_Raw!$B$21,"") -> 46188 | C25: =IF(AND(Xero_Raw!$C$21="Invoice",AND(Xero_Raw!$I$21<>"Paid",Xero_Raw!$I$21<>"Void",Xero_Raw!$I$21<>"Draft")),Xero_Raw!$D$21,"") -> Al Fardan Exchange - Sole Proprietorship L.L.C | D25: =IF(C25="","",IFERROR(VLOOKUP(C25,Assumptions!$G$5:$H$16,2,0),"Other")) -> UAE | E25: =IF(AND(Xero_Raw!$C$21="Invoice",AND(Xero_Raw!$I$21<>"Paid",Xero_Raw!$I$21<>"Void",Xero_Raw!$I$21<>"Draft")),Xero_Raw!$H$21,"") -> 31165.32 | F25: =IF(AND(Xero_Raw!$C$21="Invoice",AND(Xero_Raw!$I$21<>"Paid",Xero_Raw!$I$21<>"Void",Xero_Raw!$I$21<>"Draft")),Xero_Raw!$I$21,"") -> Overdue | G25: =IF(B25="","",MAX($C$4-B25,0)) -> 15 | H25: =IF(G25="","",IF(G25<=30,"0-30",IF(G25<=60,"31-60",IF(G25<=90,"61-90","90+")))) -> 0-30
A26: =IF(AND(Xero_Raw!$C$22="Invoice",AND(Xero_Raw!$I$22<>"Paid",Xero_Raw!$I$22<>"Void",Xero_Raw!$I$22<>"Draft")),Xero_Raw!$A$22,"") | B26: =IF(AND(Xero_Raw!$C$22="Invoice",AND(Xero_Raw!$I$22<>"Paid",Xero_Raw!$I$22<>"Void",Xero_Raw!$I$22<>"Draft")),Xero_Raw!$B$22,"") | C26: =IF(AND(Xero_Raw!$C$22="Invoice",AND(Xero_Raw!$I$22<>"Paid",Xero_Raw!$I$22<>"Void",Xero_Raw!$I$22<>"Draft")),Xero_Raw!$D$22,"") | D26: =IF(C26="","",IFERROR(VLOOKUP(C26,Assumptions!$G$5:$H$16,2,0),"Other")) | E26: =IF(AND(Xero_Raw!$C$22="Invoice",AND(Xero_Raw!$I$22<>"Paid",Xero_Raw!$I$22<>"Void",Xero_Raw!$I$22<>"Draft")),Xero_Raw!$H$22,"") | F26: =IF(AND(Xero_Raw!$C$22="Invoice",AND(Xero_Raw!$I$22<>"Paid",Xero_Raw!$I$22<>"Void",Xero_Raw!$I$22<>"Draft")),Xero_Raw!$I$22,"") | G26: =IF(B26="","",MAX($C$4-B26,0)) | H26: =IF(G26="","",IF(G26<=30,"0-30",IF(G26<=60,"31-60",IF(G26<=90,"61-90","90+"))))
A27: =IF(AND(Xero_Raw!$C$23="Invoice",AND(Xero_Raw!$I$23<>"Paid",Xero_Raw!$I$23<>"Void",Xero_Raw!$I$23<>"Draft")),Xero_Raw!$A$23,"") -> 46150 | B27: =IF(AND(Xero_Raw!$C$23="Invoice",AND(Xero_Raw!$I$23<>"Paid",Xero_Raw!$I$23<>"Void",Xero_Raw!$I$23<>"Draft")),Xero_Raw!$B$23,"") -> 46180 | C27: =IF(AND(Xero_Raw!$C$23="Invoice",AND(Xero_Raw!$I$23<>"Paid",Xero_Raw!$I$23<>"Void",Xero_Raw!$I$23<>"Draft")),Xero_Raw!$D$23,"") -> Nishat Linen UAE | D27: =IF(C27="","",IFERROR(VLOOKUP(C27,Assumptions!$G$5:$H$16,2,0),"Other")) -> UAE | E27: =IF(AND(Xero_Raw!$C$23="Invoice",AND(Xero_Raw!$I$23<>"Paid",Xero_Raw!$I$23<>"Void",Xero_Raw!$I$23<>"Draft")),Xero_Raw!$H$23,"") -> 25418.98 | F27: =IF(AND(Xero_Raw!$C$23="Invoice",AND(Xero_Raw!$I$23<>"Paid",Xero_Raw!$I$23<>"Void",Xero_Raw!$I$23<>"Draft")),Xero_Raw!$I$23,"") -> Overdue | G27: =IF(B27="","",MAX($C$4-B27,0)) -> 23 | H27: =IF(G27="","",IF(G27<=30,"0-30",IF(G27<=60,"31-60",IF(G27<=90,"61-90","90+")))) -> 0-30
A28: =IF(AND(Xero_Raw!$C$24="Invoice",AND(Xero_Raw!$I$24<>"Paid",Xero_Raw!$I$24<>"Void",Xero_Raw!$I$24<>"Draft")),Xero_Raw!$A$24,"") -> 46161 | B28: =IF(AND(Xero_Raw!$C$24="Invoice",AND(Xero_Raw!$I$24<>"Paid",Xero_Raw!$I$24<>"Void",Xero_Raw!$I$24<>"Draft")),Xero_Raw!$B$24,"") -> 46191 | C28: =IF(AND(Xero_Raw!$C$24="Invoice",AND(Xero_Raw!$I$24<>"Paid",Xero_Raw!$I$24<>"Void",Xero_Raw!$I$24<>"Draft")),Xero_Raw!$D$24,"") -> Nishat Linen UAE | D28: =IF(C28="","",IFERROR(VLOOKUP(C28,Assumptions!$G$5:$H$16,2,0),"Other")) -> UAE | E28: =IF(AND(Xero_Raw!$C$24="Invoice",AND(Xero_Raw!$I$24<>"Paid",Xero_Raw!$I$24<>"Void",Xero_Raw!$I$24<>"Draft")),Xero_Raw!$H$24,"") -> 36482.11 | F28: =IF(AND(Xero_Raw!$C$24="Invoice",AND(Xero_Raw!$I$24<>"Paid",Xero_Raw!$I$24<>"Void",Xero_Raw!$I$24<>"Draft")),Xero_Raw!$I$24,"") -> Awaiting Payment | G28: =IF(B28="","",MAX($C$4-B28,0)) -> 12 | H28: =IF(G28="","",IF(G28<=30,"0-30",IF(G28<=60,"31-60",IF(G28<=90,"61-90","90+")))) -> 0-30
A29: =IF(AND(Xero_Raw!$C$25="Invoice",AND(Xero_Raw!$I$25<>"Paid",Xero_Raw!$I$25<>"Void",Xero_Raw!$I$25<>"Draft")),Xero_Raw!$A$25,"") | B29: =IF(AND(Xero_Raw!$C$25="Invoice",AND(Xero_Raw!$I$25<>"Paid",Xero_Raw!$I$25<>"Void",Xero_Raw!$I$25<>"Draft")),Xero_Raw!$B$25,"") | C29: =IF(AND(Xero_Raw!$C$25="Invoice",AND(Xero_Raw!$I$25<>"Paid",Xero_Raw!$I$25<>"Void",Xero_Raw!$I$25<>"Draft")),Xero_Raw!$D$25,"") | D29: =IF(C29="","",IFERROR(VLOOKUP(C29,Assumptions!$G$5:$H$16,2,0),"Other")) | E29: =IF(AND(Xero_Raw!$C$25="Invoice",AND(Xero_Raw!$I$25<>"Paid",Xero_Raw!$I$25<>"Void",Xero_Raw!$I$25<>"Draft")),Xero_Raw!$H$25,"") | F29: =IF(AND(Xero_Raw!$C$25="Invoice",AND(Xero_Raw!$I$25<>"Paid",Xero_Raw!$I$25<>"Void",Xero_Raw!$I$25<>"Draft")),Xero_Raw!$I$25,"") | G29: =IF(B29="","",MAX($C$4-B29,0)) | H29: =IF(G29="","",IF(G29<=30,"0-30",IF(G29<=60,"31-60",IF(G29<=90,"61-90","90+"))))
A30: =IF(AND(Xero_Raw!$C$26="Invoice",AND(Xero_Raw!$I$26<>"Paid",Xero_Raw!$I$26<>"Void",Xero_Raw!$I$26<>"Draft")),Xero_Raw!$A$26,"") | B30: =IF(AND(Xero_Raw!$C$26="Invoice",AND(Xero_Raw!$I$26<>"Paid",Xero_Raw!$I$26<>"Void",Xero_Raw!$I$26<>"Draft")),Xero_Raw!$B$26,"") | C30: =IF(AND(Xero_Raw!$C$26="Invoice",AND(Xero_Raw!$I$26<>"Paid",Xero_Raw!$I$26<>"Void",Xero_Raw!$I$26<>"Draft")),Xero_Raw!$D$26,"") | D30: =IF(C30="","",IFERROR(VLOOKUP(C30,Assumptions!$G$5:$H$16,2,0),"Other")) | E30: =IF(AND(Xero_Raw!$C$26="Invoice",AND(Xero_Raw!$I$26<>"Paid",Xero_Raw!$I$26<>"Void",Xero_Raw!$I$26<>"Draft")),Xero_Raw!$H$26,"") | F30: =IF(AND(Xero_Raw!$C$26="Invoice",AND(Xero_Raw!$I$26<>"Paid",Xero_Raw!$I$26<>"Void",Xero_Raw!$I$26<>"Draft")),Xero_Raw!$I$26,"") | G30: =IF(B30="","",MAX($C$4-B30,0)) | H30: =IF(G30="","",IF(G30<=30,"0-30",IF(G30<=60,"31-60",IF(G30<=90,"61-90","90+"))))
A31: =IF(AND(Xero_Raw!$C$27="Invoice",AND(Xero_Raw!$I$27<>"Paid",Xero_Raw!$I$27<>"Void",Xero_Raw!$I$27<>"Draft")),Xero_Raw!$A$27,"") | B31: =IF(AND(Xero_Raw!$C$27="Invoice",AND(Xero_Raw!$I$27<>"Paid",Xero_Raw!$I$27<>"Void",Xero_Raw!$I$27<>"Draft")),Xero_Raw!$B$27,"") | C31: =IF(AND(Xero_Raw!$C$27="Invoice",AND(Xero_Raw!$I$27<>"Paid",Xero_Raw!$I$27<>"Void",Xero_Raw!$I$27<>"Draft")),Xero_Raw!$D$27,"") | D31: =IF(C31="","",IFERROR(VLOOKUP(C31,Assumptions!$G$5:$H$16,2,0),"Other")) | E31: =IF(AND(Xero_Raw!$C$27="Invoice",AND(Xero_Raw!$I$27<>"Paid",Xero_Raw!$I$27<>"Void",Xero_Raw!$I$27<>"Draft")),Xero_Raw!$H$27,"") | F31: =IF(AND(Xero_Raw!$C$27="Invoice",AND(Xero_Raw!$I$27<>"Paid",Xero_Raw!$I$27<>"Void",Xero_Raw!$I$27<>"Draft")),Xero_Raw!$I$27,"") | G31: =IF(B31="","",MAX($C$4-B31,0)) | H31: =IF(G31="","",IF(G31<=30,"0-30",IF(G31<=60,"31-60",IF(G31<=90,"61-90","90+"))))
A32: =IF(AND(Xero_Raw!$C$28="Invoice",AND(Xero_Raw!$I$28<>"Paid",Xero_Raw!$I$28<>"Void",Xero_Raw!$I$28<>"Draft")),Xero_Raw!$A$28,"") | B32: =IF(AND(Xero_Raw!$C$28="Invoice",AND(Xero_Raw!$I$28<>"Paid",Xero_Raw!$I$28<>"Void",Xero_Raw!$I$28<>"Draft")),Xero_Raw!$B$28,"") | C32: =IF(AND(Xero_Raw!$C$28="Invoice",AND(Xero_Raw!$I$28<>"Paid",Xero_Raw!$I$28<>"Void",Xero_Raw!$I$28<>"Draft")),Xero_Raw!$D$28,"") | D32: =IF(C32="","",IFERROR(VLOOKUP(C32,Assumptions!$G$5:$H$16,2,0),"Other")) | E32: =IF(AND(Xero_Raw!$C$28="Invoice",AND(Xero_Raw!$I$28<>"Paid",Xero_Raw!$I$28<>"Void",Xero_Raw!$I$28<>"Draft")),Xero_Raw!$H$28,"") | F32: =IF(AND(Xero_Raw!$C$28="Invoice",AND(Xero_Raw!$I$28<>"Paid",Xero_Raw!$I$28<>"Void",Xero_Raw!$I$28<>"Draft")),Xero_Raw!$I$28,"") | G32: =IF(B32="","",MAX($C$4-B32,0)) | H32: =IF(G32="","",IF(G32<=30,"0-30",IF(G32<=60,"31-60",IF(G32<=90,"61-90","90+"))))
A33: =IF(AND(Xero_Raw!$C$29="Invoice",AND(Xero_Raw!$I$29<>"Paid",Xero_Raw!$I$29<>"Void",Xero_Raw!$I$29<>"Draft")),Xero_Raw!$A$29,"") | B33: =IF(AND(Xero_Raw!$C$29="Invoice",AND(Xero_Raw!$I$29<>"Paid",Xero_Raw!$I$29<>"Void",Xero_Raw!$I$29<>"Draft")),Xero_Raw!$B$29,"") | C33: =IF(AND(Xero_Raw!$C$29="Invoice",AND(Xero_Raw!$I$29<>"Paid",Xero_Raw!$I$29<>"Void",Xero_Raw!$I$29<>"Draft")),Xero_Raw!$D$29,"") | D33: =IF(C33="","",IFERROR(VLOOKUP(C33,Assumptions!$G$5:$H$16,2,0),"Other")) | E33: =IF(AND(Xero_Raw!$C$29="Invoice",AND(Xero_Raw!$I$29<>"Paid",Xero_Raw!$I$29<>"Void",Xero_Raw!$I$29<>"Draft")),Xero_Raw!$H$29,"") | F33: =IF(AND(Xero_Raw!$C$29="Invoice",AND(Xero_Raw!$I$29<>"Paid",Xero_Raw!$I$29<>"Void",Xero_Raw!$I$29<>"Draft")),Xero_Raw!$I$29,"") | G33: =IF(B33="","",MAX($C$4-B33,0)) | H33: =IF(G33="","",IF(G33<=30,"0-30",IF(G33<=60,"31-60",IF(G33<=90,"61-90","90+"))))
A34: =IF(AND(Xero_Raw!$C$30="Invoice",AND(Xero_Raw!$I$30<>"Paid",Xero_Raw!$I$30<>"Void",Xero_Raw!$I$30<>"Draft")),Xero_Raw!$A$30,"") -> 46174 | B34: =IF(AND(Xero_Raw!$C$30="Invoice",AND(Xero_Raw!$I$30<>"Paid",Xero_Raw!$I$30<>"Void",Xero_Raw!$I$30<>"Draft")),Xero_Raw!$B$30,"") -> 46204 | C34: =IF(AND(Xero_Raw!$C$30="Invoice",AND(Xero_Raw!$I$30<>"Paid",Xero_Raw!$I$30<>"Void",Xero_Raw!$I$30<>"Draft")),Xero_Raw!$D$30,"") -> I Farmer Pte Ltd | D34: =IF(C34="","",IFERROR(VLOOKUP(C34,Assumptions!$G$5:$H$16,2,0),"Other")) -> Singapore | E34: =IF(AND(Xero_Raw!$C$30="Invoice",AND(Xero_Raw!$I$30<>"Paid",Xero_Raw!$I$30<>"Void",Xero_Raw!$I$30<>"Draft")),Xero_Raw!$H$30,"") -> 28580.56 | F34: =IF(AND(Xero_Raw!$C$30="Invoice",AND(Xero_Raw!$I$30<>"Paid",Xero_Raw!$I$30<>"Void",Xero_Raw!$I$30<>"Draft")),Xero_Raw!$I$30,"") -> Overdue | G34: =IF(B34="","",MAX($C$4-B34,0)) -> 0 | H34: =IF(G34="","",IF(G34<=30,"0-30",IF(G34<=60,"31-60",IF(G34<=90,"61-90","90+")))) -> 0-30
A35: =IF(AND(Xero_Raw!$C$31="Invoice",AND(Xero_Raw!$I$31<>"Paid",Xero_Raw!$I$31<>"Void",Xero_Raw!$I$31<>"Draft")),Xero_Raw!$A$31,"") | B35: =IF(AND(Xero_Raw!$C$31="Invoice",AND(Xero_Raw!$I$31<>"Paid",Xero_Raw!$I$31<>"Void",Xero_Raw!$I$31<>"Draft")),Xero_Raw!$B$31,"") | C35: =IF(AND(Xero_Raw!$C$31="Invoice",AND(Xero_Raw!$I$31<>"Paid",Xero_Raw!$I$31<>"Void",Xero_Raw!$I$31<>"Draft")),Xero_Raw!$D$31,"") | D35: =IF(C35="","",IFERROR(VLOOKUP(C35,Assumptions!$G$5:$H$16,2,0),"Other")) | E35: =IF(AND(Xero_Raw!$C$31="Invoice",AND(Xero_Raw!$I$31<>"Paid",Xero_Raw!$I$31<>"Void",Xero_Raw!$I$31<>"Draft")),Xero_Raw!$H$31,"") | F35: =IF(AND(Xero_Raw!$C$31="Invoice",AND(Xero_Raw!$I$31<>"Paid",Xero_Raw!$I$31<>"Void",Xero_Raw!$I$31<>"Draft")),Xero_Raw!$I$31,"") | G35: =IF(B35="","",MAX($C$4-B35,0)) | H35: =IF(G35="","",IF(G35<=30,"0-30",IF(G35<=60,"31-60",IF(G35<=90,"61-90","90+"))))
A36: =IF(AND(Xero_Raw!$C$32="Invoice",AND(Xero_Raw!$I$32<>"Paid",Xero_Raw!$I$32<>"Void",Xero_Raw!$I$32<>"Draft")),Xero_Raw!$A$32,"") | B36: =IF(AND(Xero_Raw!$C$32="Invoice",AND(Xero_Raw!$I$32<>"Paid",Xero_Raw!$I$32<>"Void",Xero_Raw!$I$32<>"Draft")),Xero_Raw!$B$32,"") | C36: =IF(AND(Xero_Raw!$C$32="Invoice",AND(Xero_Raw!$I$32<>"Paid",Xero_Raw!$I$32<>"Void",Xero_Raw!$I$32<>"Draft")),Xero_Raw!$D$32,"") | D36: =IF(C36="","",IFERROR(VLOOKUP(C36,Assumptions!$G$5:$H$16,2,0),"Other")) | E36: =IF(AND(Xero_Raw!$C$32="Invoice",AND(Xero_Raw!$I$32<>"Paid",Xero_Raw!$I$32<>"Void",Xero_Raw!$I$32<>"Draft")),Xero_Raw!$H$32,"") | F36: =IF(AND(Xero_Raw!$C$32="Invoice",AND(Xero_Raw!$I$32<>"Paid",Xero_Raw!$I$32<>"Void",Xero_Raw!$I$32<>"Draft")),Xero_Raw!$I$32,"") | G36: =IF(B36="","",MAX($C$4-B36,0)) | H36: =IF(G36="","",IF(G36<=30,"0-30",IF(G36<=60,"31-60",IF(G36<=90,"61-90","90+"))))
A37: =IF(AND(Xero_Raw!$C$33="Invoice",AND(Xero_Raw!$I$33<>"Paid",Xero_Raw!$I$33<>"Void",Xero_Raw!$I$33<>"Draft")),Xero_Raw!$A$33,"") -> 46183 | B37: =IF(AND(Xero_Raw!$C$33="Invoice",AND(Xero_Raw!$I$33<>"Paid",Xero_Raw!$I$33<>"Void",Xero_Raw!$I$33<>"Draft")),Xero_Raw!$B$33,"") -> 46213 | C37: =IF(AND(Xero_Raw!$C$33="Invoice",AND(Xero_Raw!$I$33<>"Paid",Xero_Raw!$I$33<>"Void",Xero_Raw!$I$33<>"Draft")),Xero_Raw!$D$33,"") -> Ticket Wala | D37: =IF(C37="","",IFERROR(VLOOKUP(C37,Assumptions!$G$5:$H$16,2,0),"Other")) -> Pakistan | E37: =IF(AND(Xero_Raw!$C$33="Invoice",AND(Xero_Raw!$I$33<>"Paid",Xero_Raw!$I$33<>"Void",Xero_Raw!$I$33<>"Draft")),Xero_Raw!$H$33,"") -> 37477.31 | F37: =IF(AND(Xero_Raw!$C$33="Invoice",AND(Xero_Raw!$I$33<>"Paid",Xero_Raw!$I$33<>"Void",Xero_Raw!$I$33<>"Draft")),Xero_Raw!$I$33,"") -> Overdue | G37: =IF(B37="","",MAX($C$4-B37,0)) -> 0 | H37: =IF(G37="","",IF(G37<=30,"0-30",IF(G37<=60,"31-60",IF(G37<=90,"61-90","90+")))) -> 0-30
A38: =IF(AND(Xero_Raw!$C$34="Invoice",AND(Xero_Raw!$I$34<>"Paid",Xero_Raw!$I$34<>"Void",Xero_Raw!$I$34<>"Draft")),Xero_Raw!$A$34,"") -> 46174 | B38: =IF(AND(Xero_Raw!$C$34="Invoice",AND(Xero_Raw!$I$34<>"Paid",Xero_Raw!$I$34<>"Void",Xero_Raw!$I$34<>"Draft")),Xero_Raw!$B$34,"") -> 46204 | C38: =IF(AND(Xero_Raw!$C$34="Invoice",AND(Xero_Raw!$I$34<>"Paid",Xero_Raw!$I$34<>"Void",Xero_Raw!$I$34<>"Draft")),Xero_Raw!$D$34,"") -> Almoudi Group Tabuk ST | D38: =IF(C38="","",IFERROR(VLOOKUP(C38,Assumptions!$G$5:$H$16,2,0),"Other")) -> Saudi Arabia | E38: =IF(AND(Xero_Raw!$C$34="Invoice",AND(Xero_Raw!$I$34<>"Paid",Xero_Raw!$I$34<>"Void",Xero_Raw!$I$34<>"Draft")),Xero_Raw!$H$34,"") -> 40736.07 | F38: =IF(AND(Xero_Raw!$C$34="Invoice",AND(Xero_Raw!$I$34<>"Paid",Xero_Raw!$I$34<>"Void",Xero_Raw!$I$34<>"Draft")),Xero_Raw!$I$34,"") -> Awaiting Payment | G38: =IF(B38="","",MAX($C$4-B38,0)) -> 0 | H38: =IF(G38="","",IF(G38<=30,"0-30",IF(G38<=60,"31-60",IF(G38<=90,"61-90","90+")))) -> 0-30
A39: =IF(AND(Xero_Raw!$C$35="Invoice",AND(Xero_Raw!$I$35<>"Paid",Xero_Raw!$I$35<>"Void",Xero_Raw!$I$35<>"Draft")),Xero_Raw!$A$35,"") -> 46178 | B39: =IF(AND(Xero_Raw!$C$35="Invoice",AND(Xero_Raw!$I$35<>"Paid",Xero_Raw!$I$35<>"Void",Xero_Raw!$I$35<>"Draft")),Xero_Raw!$B$35,"") -> 46208 | C39: =IF(AND(Xero_Raw!$C$35="Invoice",AND(Xero_Raw!$I$35<>"Paid",Xero_Raw!$I$35<>"Void",Xero_Raw!$I$35<>"Draft")),Xero_Raw!$D$35,"") -> Almoudi Group Tabuk ST | D39: =IF(C39="","",IFERROR(VLOOKUP(C39,Assumptions!$G$5:$H$16,2,0),"Other")) -> Saudi Arabia | E39: =IF(AND(Xero_Raw!$C$35="Invoice",AND(Xero_Raw!$I$35<>"Paid",Xero_Raw!$I$35<>"Void",Xero_Raw!$I$35<>"Draft")),Xero_Raw!$H$35,"") -> 17339.02 | F39: =IF(AND(Xero_Raw!$C$35="Invoice",AND(Xero_Raw!$I$35<>"Paid",Xero_Raw!$I$35<>"Void",Xero_Raw!$I$35<>"Draft")),Xero_Raw!$I$35,"") -> Overdue | G39: =IF(B39="","",MAX($C$4-B39,0)) -> 0 | H39: =IF(G39="","",IF(G39<=30,"0-30",IF(G39<=60,"31-60",IF(G39<=90,"61-90","90+")))) -> 0-30
A40: =IF(AND(Xero_Raw!$C$36="Invoice",AND(Xero_Raw!$I$36<>"Paid",Xero_Raw!$I$36<>"Void",Xero_Raw!$I$36<>"Draft")),Xero_Raw!$A$36,"") -> 46178 | B40: =IF(AND(Xero_Raw!$C$36="Invoice",AND(Xero_Raw!$I$36<>"Paid",Xero_Raw!$I$36<>"Void",Xero_Raw!$I$36<>"Draft")),Xero_Raw!$B$36,"") -> 46208 | C40: =IF(AND(Xero_Raw!$C$36="Invoice",AND(Xero_Raw!$I$36<>"Paid",Xero_Raw!$I$36<>"Void",Xero_Raw!$I$36<>"Draft")),Xero_Raw!$D$36,"") -> Faysal Bank | D40: =IF(C40="","",IFERROR(VLOOKUP(C40,Assumptions!$G$5:$H$16,2,0),"Other")) -> Pakistan | E40: =IF(AND(Xero_Raw!$C$36="Invoice",AND(Xero_Raw!$I$36<>"Paid",Xero_Raw!$I$36<>"Void",Xero_Raw!$I$36<>"Draft")),Xero_Raw!$H$36,"") -> 17796.2 | F40: =IF(AND(Xero_Raw!$C$36="Invoice",AND(Xero_Raw!$I$36<>"Paid",Xero_Raw!$I$36<>"Void",Xero_Raw!$I$36<>"Draft")),Xero_Raw!$I$36,"") -> Awaiting Payment | G40: =IF(B40="","",MAX($C$4-B40,0)) -> 0 | H40: =IF(G40="","",IF(G40<=30,"0-30",IF(G40<=60,"31-60",IF(G40<=90,"61-90","90+")))) -> 0-30
A41: =IF(AND(Xero_Raw!$C$37="Invoice",AND(Xero_Raw!$I$37<>"Paid",Xero_Raw!$I$37<>"Void",Xero_Raw!$I$37<>"Draft")),Xero_Raw!$A$37,"") -> 46180 | B41: =IF(AND(Xero_Raw!$C$37="Invoice",AND(Xero_Raw!$I$37<>"Paid",Xero_Raw!$I$37<>"Void",Xero_Raw!$I$37<>"Draft")),Xero_Raw!$B$37,"") -> 46210 | C41: =IF(AND(Xero_Raw!$C$37="Invoice",AND(Xero_Raw!$I$37<>"Paid",Xero_Raw!$I$37<>"Void",Xero_Raw!$I$37<>"Draft")),Xero_Raw!$D$37,"") -> Faysal Bank | D41: =IF(C41="","",IFERROR(VLOOKUP(C41,Assumptions!$G$5:$H$16,2,0),"Other")) -> Pakistan | E41: =IF(AND(Xero_Raw!$C$37="Invoice",AND(Xero_Raw!$I$37<>"Paid",Xero_Raw!$I$37<>"Void",Xero_Raw!$I$37<>"Draft")),Xero_Raw!$H$37,"") -> 41874.83 | F41: =IF(AND(Xero_Raw!$C$37="Invoice",AND(Xero_Raw!$I$37<>"Paid",Xero_Raw!$I$37<>"Void",Xero_Raw!$I$37<>"Draft")),Xero_Raw!$I$37,"") -> Overdue | G41: =IF(B41="","",MAX($C$4-B41,0)) -> 0 | H41: =IF(G41="","",IF(G41<=30,"0-30",IF(G41<=60,"31-60",IF(G41<=90,"61-90","90+")))) -> 0-30
A42: =IF(AND(Xero_Raw!$C$38="Invoice",AND(Xero_Raw!$I$38<>"Paid",Xero_Raw!$I$38<>"Void",Xero_Raw!$I$38<>"Draft")),Xero_Raw!$A$38,"") | B42: =IF(AND(Xero_Raw!$C$38="Invoice",AND(Xero_Raw!$I$38<>"Paid",Xero_Raw!$I$38<>"Void",Xero_Raw!$I$38<>"Draft")),Xero_Raw!$B$38,"") | C42: =IF(AND(Xero_Raw!$C$38="Invoice",AND(Xero_Raw!$I$38<>"Paid",Xero_Raw!$I$38<>"Void",Xero_Raw!$I$38<>"Draft")),Xero_Raw!$D$38,"") | D42: =IF(C42="","",IFERROR(VLOOKUP(C42,Assumptions!$G$5:$H$16,2,0),"Other")) | E42: =IF(AND(Xero_Raw!$C$38="Invoice",AND(Xero_Raw!$I$38<>"Paid",Xero_Raw!$I$38<>"Void",Xero_Raw!$I$38<>"Draft")),Xero_Raw!$H$38,"") | F42: =IF(AND(Xero_Raw!$C$38="Invoice",AND(Xero_Raw!$I$38<>"Paid",Xero_Raw!$I$38<>"Void",Xero_Raw!$I$38<>"Draft")),Xero_Raw!$I$38,"") | G42: =IF(B42="","",MAX($C$4-B42,0)) | H42: =IF(G42="","",IF(G42<=30,"0-30",IF(G42<=60,"31-60",IF(G42<=90,"61-90","90+"))))
A43: =IF(AND(Xero_Raw!$C$39="Invoice",AND(Xero_Raw!$I$39<>"Paid",Xero_Raw!$I$39<>"Void",Xero_Raw!$I$39<>"Draft")),Xero_Raw!$A$39,"") | B43: =IF(AND(Xero_Raw!$C$39="Invoice",AND(Xero_Raw!$I$39<>"Paid",Xero_Raw!$I$39<>"Void",Xero_Raw!$I$39<>"Draft")),Xero_Raw!$B$39,"") | C43: =IF(AND(Xero_Raw!$C$39="Invoice",AND(Xero_Raw!$I$39<>"Paid",Xero_Raw!$I$39<>"Void",Xero_Raw!$I$39<>"Draft")),Xero_Raw!$D$39,"") | D43: =IF(C43="","",IFERROR(VLOOKUP(C43,Assumptions!$G$5:$H$16,2,0),"Other")) | E43: =IF(AND(Xero_Raw!$C$39="Invoice",AND(Xero_Raw!$I$39<>"Paid",Xero_Raw!$I$39<>"Void",Xero_Raw!$I$39<>"Draft")),Xero_Raw!$H$39,"") | F43: =IF(AND(Xero_Raw!$C$39="Invoice",AND(Xero_Raw!$I$39<>"Paid",Xero_Raw!$I$39<>"Void",Xero_Raw!$I$39<>"Draft")),Xero_Raw!$I$39,"") | G43: =IF(B43="","",MAX($C$4-B43,0)) | H43: =IF(G43="","",IF(G43<=30,"0-30",IF(G43<=60,"31-60",IF(G43<=90,"61-90","90+"))))
A44: =IF(AND(Xero_Raw!$C$40="Invoice",AND(Xero_Raw!$I$40<>"Paid",Xero_Raw!$I$40<>"Void",Xero_Raw!$I$40<>"Draft")),Xero_Raw!$A$40,"") | B44: =IF(AND(Xero_Raw!$C$40="Invoice",AND(Xero_Raw!$I$40<>"Paid",Xero_Raw!$I$40<>"Void",Xero_Raw!$I$40<>"Draft")),Xero_Raw!$B$40,"") | C44: =IF(AND(Xero_Raw!$C$40="Invoice",AND(Xero_Raw!$I$40<>"Paid",Xero_Raw!$I$40<>"Void",Xero_Raw!$I$40<>"Draft")),Xero_Raw!$D$40,"") | D44: =IF(C44="","",IFERROR(VLOOKUP(C44,Assumptions!$G$5:$H$16,2,0),"Other")) | E44: =IF(AND(Xero_Raw!$C$40="Invoice",AND(Xero_Raw!$I$40<>"Paid",Xero_Raw!$I$40<>"Void",Xero_Raw!$I$40<>"Draft")),Xero_Raw!$H$40,"") | F44: =IF(AND(Xero_Raw!$C$40="Invoice",AND(Xero_Raw!$I$40<>"Paid",Xero_Raw!$I$40<>"Void",Xero_Raw!$I$40<>"Draft")),Xero_Raw!$I$40,"") | G44: =IF(B44="","",MAX($C$4-B44,0)) | H44: =IF(G44="","",IF(G44<=30,"0-30",IF(G44<=60,"31-60",IF(G44<=90,"61-90","90+"))))
A45: =IF(AND(Xero_Raw!$C$41="Invoice",AND(Xero_Raw!$I$41<>"Paid",Xero_Raw!$I$41<>"Void",Xero_Raw!$I$41<>"Draft")),Xero_Raw!$A$41,"") | B45: =IF(AND(Xero_Raw!$C$41="Invoice",AND(Xero_Raw!$I$41<>"Paid",Xero_Raw!$I$41<>"Void",Xero_Raw!$I$41<>"Draft")),Xero_Raw!$B$41,"") | C45: =IF(AND(Xero_Raw!$C$41="Invoice",AND(Xero_Raw!$I$41<>"Paid",Xero_Raw!$I$41<>"Void",Xero_Raw!$I$41<>"Draft")),Xero_Raw!$D$41,"") | D45: =IF(C45="","",IFERROR(VLOOKUP(C45,Assumptions!$G$5:$H$16,2,0),"Other")) | E45: =IF(AND(Xero_Raw!$C$41="Invoice",AND(Xero_Raw!$I$41<>"Paid",Xero_Raw!$I$41<>"Void",Xero_Raw!$I$41<>"Draft")),Xero_Raw!$H$41,"") | F45: =IF(AND(Xero_Raw!$C$41="Invoice",AND(Xero_Raw!$I$41<>"Paid",Xero_Raw!$I$41<>"Void",Xero_Raw!$I$41<>"Draft")),Xero_Raw!$I$41,"") | G45: =IF(B45="","",MAX($C$4-B45,0)) | H45: =IF(G45="","",IF(G45<=30,"0-30",IF(G45<=60,"31-60",IF(G45<=90,"61-90","90+"))))
A46: =IF(AND(Xero_Raw!$C$42="Invoice",AND(Xero_Raw!$I$42<>"Paid",Xero_Raw!$I$42<>"Void",Xero_Raw!$I$42<>"Draft")),Xero_Raw!$A$42,"") | B46: =IF(AND(Xero_Raw!$C$42="Invoice",AND(Xero_Raw!$I$42<>"Paid",Xero_Raw!$I$42<>"Void",Xero_Raw!$I$42<>"Draft")),Xero_Raw!$B$42,"") | C46: =IF(AND(Xero_Raw!$C$42="Invoice",AND(Xero_Raw!$I$42<>"Paid",Xero_Raw!$I$42<>"Void",Xero_Raw!$I$42<>"Draft")),Xero_Raw!$D$42,"") | D46: =IF(C46="","",IFERROR(VLOOKUP(C46,Assumptions!$G$5:$H$16,2,0),"Other")) | E46: =IF(AND(Xero_Raw!$C$42="Invoice",AND(Xero_Raw!$I$42<>"Paid",Xero_Raw!$I$42<>"Void",Xero_Raw!$I$42<>"Draft")),Xero_Raw!$H$42,"") | F46: =IF(AND(Xero_Raw!$C$42="Invoice",AND(Xero_Raw!$I$42<>"Paid",Xero_Raw!$I$42<>"Void",Xero_Raw!$I$42<>"Draft")),Xero_Raw!$I$42,"") | G46: =IF(B46="","",MAX($C$4-B46,0)) | H46: =IF(G46="","",IF(G46<=30,"0-30",IF(G46<=60,"31-60",IF(G46<=90,"61-90","90+"))))
A48: OUTSTANDING INVOICE DETAIL — CUSTOMER_INVOICES_UPLOAD (Illustrative sample rows shown — summary totals reflect the full uploaded range.)
A49: Invoice Date | B49: Due Date | C49: Customer | D49: Country | E49: Amount (AED) | F49: Status | G49: Days Overdue | H49: Aging Bucket
A50: =IF(Customer_Invoices_Upload!$I$4<>"Paid",Customer_Invoices_Upload!$B$4,"") -> 46127 | B50: =IF(Customer_Invoices_Upload!$I$4<>"Paid",Customer_Invoices_Upload!$C$4,"") -> 46157 | C50: =IF(Customer_Invoices_Upload!$I$4<>"Paid",Customer_Invoices_Upload!$E$4,"") -> Misfit Technologies Pte Ltd | D50: =IF(C50="","",IFERROR(VLOOKUP(C50,Assumptions!$G$5:$H$16,2,0),"Other")) -> Singapore | E50: =IF(Customer_Invoices_Upload!$I$4<>"Paid",Customer_Invoices_Upload!$H$4,"") -> 2862.59 | F50: =IF(Customer_Invoices_Upload!$I$4<>"Paid",Customer_Invoices_Upload!$I$4,"") -> Awaiting Payment | G50: =IF(B50="","",MAX($C$4-B50,0)) -> 46 | H50: =IF(G50="","",IF(G50<=30,"0-30",IF(G50<=60,"31-60",IF(G50<=90,"61-90","90+")))) -> 31-60
A51: =IF(Customer_Invoices_Upload!$I$5<>"Paid",Customer_Invoices_Upload!$B$5,"") | B51: =IF(Customer_Invoices_Upload!$I$5<>"Paid",Customer_Invoices_Upload!$C$5,"") | C51: =IF(Customer_Invoices_Upload!$I$5<>"Paid",Customer_Invoices_Upload!$E$5,"") | D51: =IF(C51="","",IFERROR(VLOOKUP(C51,Assumptions!$G$5:$H$16,2,0),"Other")) | E51: =IF(Customer_Invoices_Upload!$I$5<>"Paid",Customer_Invoices_Upload!$H$5,"") | F51: =IF(Customer_Invoices_Upload!$I$5<>"Paid",Customer_Invoices_Upload!$I$5,"") | G51: =IF(B51="","",MAX($C$4-B51,0)) | H51: =IF(G51="","",IF(G51<=30,"0-30",IF(G51<=60,"31-60",IF(G51<=90,"61-90","90+"))))
A52: =IF(Customer_Invoices_Upload!$I$6<>"Paid",Customer_Invoices_Upload!$B$6,"") -> 46118 | B52: =IF(Customer_Invoices_Upload!$I$6<>"Paid",Customer_Invoices_Upload!$C$6,"") -> 46148 | C52: =IF(Customer_Invoices_Upload!$I$6<>"Paid",Customer_Invoices_Upload!$E$6,"") -> Al Fardan Exchange - Sole Proprietorship L.L.C | D52: =IF(C52="","",IFERROR(VLOOKUP(C52,Assumptions!$G$5:$H$16,2,0),"Other")) -> UAE | E52: =IF(Customer_Invoices_Upload!$I$6<>"Paid",Customer_Invoices_Upload!$H$6,"") -> 10317.27 | F52: =IF(Customer_Invoices_Upload!$I$6<>"Paid",Customer_Invoices_Upload!$I$6,"") -> Overdue | G52: =IF(B52="","",MAX($C$4-B52,0)) -> 55 | H52: =IF(G52="","",IF(G52<=30,"0-30",IF(G52<=60,"31-60",IF(G52<=90,"61-90","90+")))) -> 31-60
A53: =IF(Customer_Invoices_Upload!$I$7<>"Paid",Customer_Invoices_Upload!$B$7,"") -> 46132 | B53: =IF(Customer_Invoices_Upload!$I$7<>"Paid",Customer_Invoices_Upload!$C$7,"") -> 46162 | C53: =IF(Customer_Invoices_Upload!$I$7<>"Paid",Customer_Invoices_Upload!$E$7,"") -> Al Fardan Exchange - Sole Proprietorship L.L.C | D53: =IF(C53="","",IFERROR(VLOOKUP(C53,Assumptions!$G$5:$H$16,2,0),"Other")) -> UAE | E53: =IF(Customer_Invoices_Upload!$I$7<>"Paid",Customer_Invoices_Upload!$H$7,"") -> 11128.21 | F53: =IF(Customer_Invoices_Upload!$I$7<>"Paid",Customer_Invoices_Upload!$I$7,"") -> Overdue | G53: =IF(B53="","",MAX($C$4-B53,0)) -> 41 | H53: =IF(G53="","",IF(G53<=30,"0-30",IF(G53<=60,"31-60",IF(G53<=90,"61-90","90+")))) -> 31-60
A54: =IF(Customer_Invoices_Upload!$I$8<>"Paid",Customer_Invoices_Upload!$B$8,"") | B54: =IF(Customer_Invoices_Upload!$I$8<>"Paid",Customer_Invoices_Upload!$C$8,"") | C54: =IF(Customer_Invoices_Upload!$I$8<>"Paid",Customer_Invoices_Upload!$E$8,"") | D54: =IF(C54="","",IFERROR(VLOOKUP(C54,Assumptions!$G$5:$H$16,2,0),"Other")) | E54: =IF(Customer_Invoices_Upload!$I$8<>"Paid",Customer_Invoices_Upload!$H$8,"") | F54: =IF(Customer_Invoices_Upload!$I$8<>"Paid",Customer_Invoices_Upload!$I$8,"") | G54: =IF(B54="","",MAX($C$4-B54,0)) | H54: =IF(G54="","",IF(G54<=30,"0-30",IF(G54<=60,"31-60",IF(G54<=90,"61-90","90+"))))
A55: =IF(Customer_Invoices_Upload!$I$9<>"Paid",Customer_Invoices_Upload!$B$9,"") -> 46144 | B55: =IF(Customer_Invoices_Upload!$I$9<>"Paid",Customer_Invoices_Upload!$C$9,"") -> 46174 | C55: =IF(Customer_Invoices_Upload!$I$9<>"Paid",Customer_Invoices_Upload!$E$9,"") -> Growth X Ventures LLC | D55: =IF(C55="","",IFERROR(VLOOKUP(C55,Assumptions!$G$5:$H$16,2,0),"Other")) -> UAE | E55: =IF(Customer_Invoices_Upload!$I$9<>"Paid",Customer_Invoices_Upload!$H$9,"") -> 13175.39 | F55: =IF(Customer_Invoices_Upload!$I$9<>"Paid",Customer_Invoices_Upload!$I$9,"") -> Awaiting Payment | G55: =IF(B55="","",MAX($C$4-B55,0)) -> 29 | H55: =IF(G55="","",IF(G55<=30,"0-30",IF(G55<=60,"31-60",IF(G55<=90,"61-90","90+")))) -> 0-30
A56: =IF(Customer_Invoices_Upload!$I$10<>"Paid",Customer_Invoices_Upload!$B$10,"") | B56: =IF(Customer_Invoices_Upload!$I$10<>"Paid",Customer_Invoices_Upload!$C$10,"") | C56: =IF(Customer_Invoices_Upload!$I$10<>"Paid",Customer_Invoices_Upload!$E$10,"") | D56: =IF(C56="","",IFERROR(VLOOKUP(C56,Assumptions!$G$5:$H$16,2,0),"Other")) | E56: =IF(Customer_Invoices_Upload!$I$10<>"Paid",Customer_Invoices_Upload!$H$10,"") | F56: =IF(Customer_Invoices_Upload!$I$10<>"Paid",Customer_Invoices_Upload!$I$10,"") | G56: =IF(B56="","",MAX($C$4-B56,0)) | H56: =IF(G56="","",IF(G56<=30,"0-30",IF(G56<=60,"31-60",IF(G56<=90,"61-90","90+"))))
A57: =IF(Customer_Invoices_Upload!$I$11<>"Paid",Customer_Invoices_Upload!$B$11,"") | B57: =IF(Customer_Invoices_Upload!$I$11<>"Paid",Customer_Invoices_Upload!$C$11,"") | C57: =IF(Customer_Invoices_Upload!$I$11<>"Paid",Customer_Invoices_Upload!$E$11,"") | D57: =IF(C57="","",IFERROR(VLOOKUP(C57,Assumptions!$G$5:$H$16,2,0),"Other")) | E57: =IF(Customer_Invoices_Upload!$I$11<>"Paid",Customer_Invoices_Upload!$H$11,"") | F57: =IF(Customer_Invoices_Upload!$I$11<>"Paid",Customer_Invoices_Upload!$I$11,"") | G57: =IF(B57="","",MAX($C$4-B57,0)) | H57: =IF(G57="","",IF(G57<=30,"0-30",IF(G57<=60,"31-60",IF(G57<=90,"61-90","90+"))))
A58: =IF(Customer_Invoices_Upload!$I$12<>"Paid",Customer_Invoices_Upload!$B$12,"") -> 46147 | B58: =IF(Customer_Invoices_Upload!$I$12<>"Paid",Customer_Invoices_Upload!$C$12,"") -> 46177 | C58: =IF(Customer_Invoices_Upload!$I$12<>"Paid",Customer_Invoices_Upload!$E$12,"") -> Misfit Technologies Pte Ltd | D58: =IF(C58="","",IFERROR(VLOOKUP(C58,Assumptions!$G$5:$H$16,2,0),"Other")) -> Singapore | E58: =IF(Customer_Invoices_Upload!$I$12<>"Paid",Customer_Invoices_Upload!$H$12,"") -> 21750.95 | F58: =IF(Customer_Invoices_Upload!$I$12<>"Paid",Customer_Invoices_Upload!$I$12,"") -> Overdue | G58: =IF(B58="","",MAX($C$4-B58,0)) -> 26 | H58: =IF(G58="","",IF(G58<=30,"0-30",IF(G58<=60,"31-60",IF(G58<=90,"61-90","90+")))) -> 0-30
A59: =IF(Customer_Invoices_Upload!$I$13<>"Paid",Customer_Invoices_Upload!$B$13,"") -> 46152 | B59: =IF(Customer_Invoices_Upload!$I$13<>"Paid",Customer_Invoices_Upload!$C$13,"") -> 46182 | C59: =IF(Customer_Invoices_Upload!$I$13<>"Paid",Customer_Invoices_Upload!$E$13,"") -> I Farmer Pte Ltd | D59: =IF(C59="","",IFERROR(VLOOKUP(C59,Assumptions!$G$5:$H$16,2,0),"Other")) -> Singapore | E59: =IF(Customer_Invoices_Upload!$I$13<>"Paid",Customer_Invoices_Upload!$H$13,"") -> 14640.03 | F59: =IF(Customer_Invoices_Upload!$I$13<>"Paid",Customer_Invoices_Upload!$I$13,"") -> Awaiting Payment | G59: =IF(B59="","",MAX($C$4-B59,0)) -> 21 | H59: =IF(G59="","",IF(G59<=30,"0-30",IF(G59<=60,"31-60",IF(G59<=90,"61-90","90+")))) -> 0-30
A60: =IF(Customer_Invoices_Upload!$I$14<>"Paid",Customer_Invoices_Upload!$B$14,"") -> 46190 | B60: =IF(Customer_Invoices_Upload!$I$14<>"Paid",Customer_Invoices_Upload!$C$14,"") -> 46220 | C60: =IF(Customer_Invoices_Upload!$I$14<>"Paid",Customer_Invoices_Upload!$E$14,"") -> I Farmer Pte Ltd | D60: =IF(C60="","",IFERROR(VLOOKUP(C60,Assumptions!$G$5:$H$16,2,0),"Other")) -> Singapore | E60: =IF(Customer_Invoices_Upload!$I$14<>"Paid",Customer_Invoices_Upload!$H$14,"") -> 13168.55 | F60: =IF(Customer_Invoices_Upload!$I$14<>"Paid",Customer_Invoices_Upload!$I$14,"") -> Overdue | G60: =IF(B60="","",MAX($C$4-B60,0)) -> 0 | H60: =IF(G60="","",IF(G60<=30,"0-30",IF(G60<=60,"31-60",IF(G60<=90,"61-90","90+")))) -> 0-30
A61: =IF(Customer_Invoices_Upload!$I$15<>"Paid",Customer_Invoices_Upload!$B$15,"") -> 46178 | B61: =IF(Customer_Invoices_Upload!$I$15<>"Paid",Customer_Invoices_Upload!$C$15,"") -> 46208 | C61: =IF(Customer_Invoices_Upload!$I$15<>"Paid",Customer_Invoices_Upload!$E$15,"") -> Al Fardan Exchange - Sole Proprietorship L.L.C | D61: =IF(C61="","",IFERROR(VLOOKUP(C61,Assumptions!$G$5:$H$16,2,0),"Other")) -> UAE | E61: =IF(Customer_Invoices_Upload!$I$15<>"Paid",Customer_Invoices_Upload!$H$15,"") -> 2303.99 | F61: =IF(Customer_Invoices_Upload!$I$15<>"Paid",Customer_Invoices_Upload!$I$15,"") -> Overdue | G61: =IF(B61="","",MAX($C$4-B61,0)) -> 0 | H61: =IF(G61="","",IF(G61<=30,"0-30",IF(G61<=60,"31-60",IF(G61<=90,"61-90","90+")))) -> 0-30
A62: =IF(Customer_Invoices_Upload!$I$16<>"Paid",Customer_Invoices_Upload!$B$16,"") | B62: =IF(Customer_Invoices_Upload!$I$16<>"Paid",Customer_Invoices_Upload!$C$16,"") | C62: =IF(Customer_Invoices_Upload!$I$16<>"Paid",Customer_Invoices_Upload!$E$16,"") | D62: =IF(C62="","",IFERROR(VLOOKUP(C62,Assumptions!$G$5:$H$16,2,0),"Other")) | E62: =IF(Customer_Invoices_Upload!$I$16<>"Paid",Customer_Invoices_Upload!$H$16,"") | F62: =IF(Customer_Invoices_Upload!$I$16<>"Paid",Customer_Invoices_Upload!$I$16,"") | G62: =IF(B62="","",MAX($C$4-B62,0)) | H62: =IF(G62="","",IF(G62<=30,"0-30",IF(G62<=60,"31-60",IF(G62<=90,"61-90","90+"))))
A63: =IF(Customer_Invoices_Upload!$I$17<>"Paid",Customer_Invoices_Upload!$B$17,"") | B63: =IF(Customer_Invoices_Upload!$I$17<>"Paid",Customer_Invoices_Upload!$C$17,"") | C63: =IF(Customer_Invoices_Upload!$I$17<>"Paid",Customer_Invoices_Upload!$E$17,"") | D63: =IF(C63="","",IFERROR(VLOOKUP(C63,Assumptions!$G$5:$H$16,2,0),"Other")) | E63: =IF(Customer_Invoices_Upload!$I$17<>"Paid",Customer_Invoices_Upload!$H$17,"") | F63: =IF(Customer_Invoices_Upload!$I$17<>"Paid",Customer_Invoices_Upload!$I$17,"") | G63: =IF(B63="","",MAX($C$4-B63,0)) | H63: =IF(G63="","",IF(G63<=30,"0-30",IF(G63<=60,"31-60",IF(G63<=90,"61-90","90+"))))
A64: =IF(Customer_Invoices_Upload!$I$18<>"Paid",Customer_Invoices_Upload!$B$18,"") | B64: =IF(Customer_Invoices_Upload!$I$18<>"Paid",Customer_Invoices_Upload!$C$18,"") | C64: =IF(Customer_Invoices_Upload!$I$18<>"Paid",Customer_Invoices_Upload!$E$18,"") | D64: =IF(C64="","",IFERROR(VLOOKUP(C64,Assumptions!$G$5:$H$16,2,0),"Other")) | E64: =IF(Customer_Invoices_Upload!$I$18<>"Paid",Customer_Invoices_Upload!$H$18,"") | F64: =IF(Customer_Invoices_Upload!$I$18<>"Paid",Customer_Invoices_Upload!$I$18,"") | G64: =IF(B64="","",MAX($C$4-B64,0)) | H64: =IF(G64="","",IF(G64<=30,"0-30",IF(G64<=60,"31-60",IF(G64<=90,"61-90","90+"))))
A66: RECEIVABLES SUMMARY BY COUNTRY
A67: Country | B67: 0-30 days | C67: 31-60 days | D67: 61-90 days | E67: 90+ days | F67: Total Outstanding
A68: UAE | B68: =SUMPRODUCT((Xero_Raw!$C$4:$C$5003="Invoice")*(Xero_Raw!$I$4:$I$5003<>"Paid")*(Xero_Raw!$I$4:$I$5003<>"Void")*(Xero_Raw!$I$4:$I$5003<>"Draft")*(Xero_Raw!$A$4:$A$5003<>"")*(Xero_Raw!$E$4:$E$5003="UAE")*(($C$4-Xero_Raw!$B$4:$B$5003)<=30)*Xero_Raw!$H$4:$H$5003)+SUMPRODUCT((Customer_Invoices_Upload!$I$4:$I$5003<>"Paid")*(Customer_Invoices_Upload!$B$4:$B$5003<>"")*(Customer_Invoices_Upload!$F$4:$F$5003="UAE")*(($C$4-Customer_Invoices_Upload!$C$4:$C$5003)<=30)*Customer_Invoices_Upload!$H$4:$H$5003) -> 108545.79 | C68: =SUMPRODUCT((Xero_Raw!$C$4:$C$5003="Invoice")*(Xero_Raw!$I$4:$I$5003<>"Paid")*(Xero_Raw!$I$4:$I$5003<>"Void")*(Xero_Raw!$I$4:$I$5003<>"Draft")*(Xero_Raw!$A$4:$A$5003<>"")*(Xero_Raw!$E$4:$E$5003="UAE")*(($C$4-Xero_Raw!$B$4:$B$5003)>=31)*(($C$4-Xero_Raw!$B$4:$B$5003)<=60)*Xero_Raw!$H$4:$H$5003)+SUMPRODUCT((Customer_Invoices_Upload!$I$4:$I$5003<>"Paid")*(Customer_Invoices_Upload!$B$4:$B$5003<>"")*(Customer_Invoices_Upload!$F$4:$F$5003="UAE")*(($C$4-Customer_Invoices_Upload!$C$4:$C$5003)>=31)*(($C$4-Customer_Invoices_Upload!$C$4:$C$5003)<=60)*Customer_Invoices_Upload!$H$4:$H$5003) -> 21445.48 | D68: =SUMPRODUCT((Xero_Raw!$C$4:$C$5003="Invoice")*(Xero_Raw!$I$4:$I$5003<>"Paid")*(Xero_Raw!$I$4:$I$5003<>"Void")*(Xero_Raw!$I$4:$I$5003<>"Draft")*(Xero_Raw!$A$4:$A$5003<>"")*(Xero_Raw!$E$4:$E$5003="UAE")*(($C$4-Xero_Raw!$B$4:$B$5003)>=61)*(($C$4-Xero_Raw!$B$4:$B$5003)<=90)*Xero_Raw!$H$4:$H$5003)+SUMPRODUCT((Customer_Invoices_Upload!$I$4:$I$5003<>"Paid")*(Customer_Invoices_Upload!$B$4:$B$5003<>"")*(Customer_Invoices_Upload!$F$4:$F$5003="UAE")*(($C$4-Customer_Invoices_Upload!$C$4:$C$5003)>=61)*(($C$4-Customer_Invoices_Upload!$C$4:$C$5003)<=90)*Customer_Invoices_Upload!$H$4:$H$5003) -> 0 | E68: =SUMPRODUCT((Xero_Raw!$C$4:$C$5003="Invoice")*(Xero_Raw!$I$4:$I$5003<>"Paid")*(Xero_Raw!$I$4:$I$5003<>"Void")*(Xero_Raw!$I$4:$I$5003<>"Draft")*(Xero_Raw!$A$4:$A$5003<>"")*(Xero_Raw!$E$4:$E$5003="UAE")*(($C$4-Xero_Raw!$B$4:$B$5003)>=91)*Xero_Raw!$H$4:$H$5003)+SUMPRODUCT((Customer_Invoices_Upload!$I$4:$I$5003<>"Paid")*(Customer_Invoices_Upload!$B$4:$B$5003<>"")*(Customer_Invoices_Upload!$F$4:$F$5003="UAE")*(($C$4-Customer_Invoices_Upload!$C$4:$C$5003)>=91)*Customer_Invoices_Upload!$H$4:$H$5003) -> 0 | F68: =SUM(B68:E68) -> 129991.27
